Workbook
Name trak1: 'Assessments-Master'!$V$2:$AI$694

Sheet Assessments-Master
A1: Joining Year | B1: Track Number | C1: LAST Batch Year | D1: Category | E1: Batch Number | F1: WhatsApp Batch Name | G1: GURUVU GARU 1 | H1: GURUVU GARU 2 / TA | I1: GURUVU GARU 3 / TA | J1: Student Status | K1: LAST 4-WEEKS ATTENDANCE | L1: OVERALL AKSHARA / SWARA JNANAM | M1: OVERALL EXAM BACKLOG | N1: Roll Number | O1: Last Name | P1: First Name | Q1: Full Name | R1: Country Code | S1: Phone Number | T1: Time zone | U1: YOB | V1: Guru Vandana SHLOKAS | W1: YAGNOPAVEETA Dharanam, Avaposanam, panchangam | X1: Shraddha | Y1: Medha | Z1: Durga | AA1: Sri Suktam | AB1: Purusha | AC1: Ganapathi | AD1: Narayana | AE1: Sandhya Vandanam 1 | AF1: Sandhya Vandanam 2 | AG1: Sandhya Vandanam 3 | AH1: Brahma Yagnam | AI1: TRACK 1 CERTIFICATION EXAM STATUS | AJ1: Vishnu | AK1: Bhu Suktam | AL1: Neela | AM1: Bhagya | AN1: Brahma | AO1: Sarpa | AP1: Saraswathi | AQ1: Govu | AR1: Pavamana | AS1: Ayushya | AT1: Navagraha | AU1: Maha Mantra Pushpam | AV1: TRACK 2 CERTIFICATION EXAM STATUS | AW1: Deepa Prajvalanam | AX1: Trisuparnam | AY1: Manyu Suktam | AZ1: Vaishvanara Suktam | BA1: Rudram Namakam | BB1: Rudram Chamakam | BC1: Shakunadi | BD1: Ganapati Pooja | BE1: Punyaha vaachanam | BF1: TRACK 3 CERTIFICATION EXAM STATUS | BG1: Mahanyasam - 1 | BH1: Mahanyasam - 2 | BI1: Mahanyasam - 3 | BJ1: Mahanyasam - 4 | BK1: Dasashanti | BL1: Samrajya Pattabhishekam | BM1: TRACK 4 CERTIFICATION EXAM | BN1: Seeksha Valli | BO1: Ananda Valli | BP1: Brughu Valli | BQ1: Chitti 1 | BR1: Chitti 2 | BS1: Maha Narayanam 1 | BT1: Maha Narayanam 2 | BU1: Maha Narayanam 3 | BV1: TRACK 5 CERTIFICATION EXAM STATUS | BW1: Nakshatreshti 1 | BX1: Nakshatreshti 2 | BY1: Pancha katakamulu 1 Samjnanam 1 | BZ1: Pancha katakamulu 1 Samjnanam 2 | CA1: Pancha katakamulu 2 Lokosi 1 | CB1: Pancha katakamulu 2 Lokosi 2 | CC1: Pancha katakamulu 3 Thubyam 1 | CD1: Pancha katakamulu 3 Thubyam 2 | CE1: TRACK 6 CERTIFICATION EXAM STATUS | CF1: Pancha katakamulu 4 Arunam 1 | CG1: Pancha katakamulu 4 Arunam 2 | CH1: Pancha katakamulu 4 Arunam 3 | CI1: Pancha katakamulu 4 Arunam 4 | CJ1: Pancha katakamulu 5 Swadhyaya Brahmanam 1 | CK1: Pancha katakamulu 5 Swadhyaya Brahmanam 2 | CL1: Pancha katakamulu 5 Swadhyaya Brahmanam 3 | CM1: TRACK 7 CERTIFICATION EXAM STATUS | CN1: Veda Aseervachanam 1 | CO1: Veda Aseervachanam 2 | CP1: Purnakumbha Swagata Mantras | CQ1: Pancha anuvaaka Mantras | CR1: Anna Sooktam 1 | CS1: Anna Sooktam 2 | CT1: Prayojanaartha Mantraah 1 | CU1: Prayojanaartha Mantraah 2 | CV1: Shatpatra Prayogam | CW1: Jayadayah | CX1: Poornahuti &Agni Pradakshina | CY1: TRACK 8 CERTIFICATION EXAM STATUS
A2: {=_xludf.XLOOKUP(S2,Master_Registrations!P:P,Master_Registrations!A:A,"")} -> #NAME? | B2: VED-01 | C2: 2026 | D2: BR | E2: 1 | F2: =CONCATENATE(B2,"-",C2,"-",D2,"-",E2) -> VED-01-2026-BR-1 | G2: Niranjan Penumarthy | H2: Kiran Deshpande | J2: Active | N2: R1 | O2: Ayachitula | P2: Hrishikesh | Q2: =_xludf.TEXTJOIN(" ",TRUE,O2:P2) -> #NAME? | R2: +91 | S2: 9986458997 | T2: 1-INDIA IST | U2: 2010 | V2: 1 | W2: 1 | X2: 1 | Y2: 1 | Z2: 1 | AA2: -1 | AB2: -1 | AC2: -1 | AD2: -1 | AE2: -1 | AF2: -1 | AG2: -1 | AH2: -1 | AI2: -1
A3: {=_xludf.XLOOKUP(S3,Master_Registrations!P:P,Master_Registrations!A:A,"")} -> #NAME? | B3: VED-01 | C3: 2026 | D3: BR | E3: 1 | F3: =CONCATENATE(B3,"-",C3,"-",D3,"-",E3) -> VED-01-2026-BR-1 | G3: Niranjan Penumarthy | H3: Kiran Deshpande | J3: Active | N3: R2 | O3: Ayachitula | P3: Sriram Charan | Q3: =_xludf.TEXTJOIN(" ",TRUE,O3:P3) -> #NAME? | R3: +91 | S3: 9986458997 | T3: 1-INDIA IST | U3: 2012 | V3: 1 | W3: 1 | X3: 1 | Y3: 1 | Z3: 1 | AA3: -1 | AB3: -1 | AC3: -1 | AD3: -1 | AE3: -1 | AF3: -1 | AG3: -1 | AH3: -1 | AI3: -1
A4: {=_xludf.XLOOKUP(S4,Master_Registrations!P:P,Master_Registrations!A:A,"")} -> #NAME? | B4: VED-01 | C4: 2026 | D4: BR | E4: 1 | F4: =CONCATENATE(B4,"-",C4,"-",D4,"-",E4) -> VED-01-2026-BR-1 | G4: Niranjan Penumarthy | H4: Kiran Deshpande | J4: Active | N4: R3 | O4: Challa | P4: Achyuth Ram | Q4: =_xludf.TEXTJOIN(" ",TRUE,O4:P4) -> #NAME? | R4: +91 | S4: 9885600552 | T4: 1-INDIA IST | U4: 2018 | V4: 1 | W4: -1 | X4: 1 | Y4: 1 | Z4: 1 | AA4: -1 | AB4: -1 | AC4: -1 | AD4: -1 | AE4: 1 | AF4: 1 | AG4: 1 | AH4: -1 | AI4: -1
A5: {=_xludf.XLOOKUP(S5,Master_Registrations!P:P,Master_Registrations!A:A,"")} -> #NAME? | B5: VED-01 | C5: 2026 | D5: BR | E5: 1 | F5: =CONCATENATE(B5,"-",C5,"-",D5,"-",E5) -> VED-01-2026-BR-1 | G5: Niranjan Penumarthy | H5: Kiran Deshpande | J5: Active | N5: R4 | O5: Dokka | P5: Jagannadh | Q5: =_xludf.TEXTJOIN(" ",TRUE,O5:P5) -> #NAME? | R5: +1 | S5: 7147913258 | T5: 3-USA CST | U5: 2011 | V5: -1 | W5: -1 | X5: -1 | Y5: -1 | Z5: -1 | AA5: -1 | AB5: -1 | AC5: -1 | AD5: -1 | AE5: -1 | AF5: -1 | AG5: -1 | AH5: -1 | AI5: -1
A6: {=_xludf.XLOOKUP(S6,Master_Registrations!P:P,Master_Registrations!A:A,"")} -> #NAME? | B6: VED-01 | C6: 2026 | D6: BR | E6: 1 | F6: =CONCATENATE(B6,"-",C6,"-",D6,"-",E6) -> VED-01-2026-BR-1 | G6: Niranjan Penumarthy | H6: Kiran Deshpande | J6: Active | N6: R5 | O6: Gorthy | P6: Anand krishna | Q6: =_xludf.TEXTJOIN(" ",TRUE,O6:P6) -> #NAME? | R6: +1 | S6: 8148826399 | T6: 3-USA CST | U6: 2016 | V6: -1 | W6: -1 | X6: 1 | Y6: -1 | Z6: -1 | AA6: -1 | AB6: -1 | AC6: -1 | AD6: -1 | AE6: -1 | AF6: -1 | AG6: -1 | AH6: -1 | AI6: -1
A7: {=_xludf.XLOOKUP(S7,Master_Registrations!P:P,Master_Registrations!A:A,"")} -> #NAME? | B7: VED-01 | C7: 2026 | D7: BR | E7: 1 | F7: =CONCATENATE(B7,"-",C7,"-",D7,"-",E7) -> VED-01-2026-BR-1 | G7: Niranjan Penumarthy | H7: Kiran Deshpande | J7: Active | N7: R6 | O7: Jandhyala | P7: Venkata Karthikeya Aashrith | Q7: =_xludf.TEXTJOIN(" ",TRUE,O7:P7) -> #NAME? | R7: +91 | S7: 9840573053 | T7: 1-INDIA IST | U7: 2016 | V7: -1 | W7: -1 | X7: 1 | Y7: -1 | Z7: -1 | AA7: -1 | AB7: -1 | AC7: -1 | AD7: -1 | AE7: -1 | AF7: -1 | AG7: -1 | AH7: -1 | AI7: -1
A8: {=_xludf.XLOOKUP(S8,Master_Registrations!P:P,Master_Registrations!A:A,"")} -> #NAME? | B8: VED-01 | C8: 2026 | D8: BR | E8: 1 | F8: =CONCATENATE(B8,"-",C8,"-",D8,"-",E8) -> VED-01-2026-BR-1 | G8: Niranjan Penumarthy | H8: Kiran Deshpande | J8: Active | N8: R7 | O8: Kavuri | P8: Sriram | Q8: =_xludf.TEXTJOIN(" ",TRUE,O8:P8) -> #NAME? | R8: +91 | S8: 9441975657 | T8: 1-INDIA IST | U8: 2013 | V8: 1 | W8: 1 | X8: 1 | Y8: 1 | Z8: 1 | AA8: -1 | AB8: -1 | AC8: -1 | AD8: -1 | AE8: 2 | AF8: 2 | AG8: 2 | AH8: -1 | AI8: -1
A9: {=_xludf.XLOOKUP(S9,Master_Registrations!P:P,Master_Registrations!A:A,"")} -> #NAME? | B9: VED-01 | C9: 2026 | D9: BR | E9: 1 | F9: =CONCATENATE(B9,"-",C9,"-",D9,"-",E9) -> VED-01-2026-BR-1 | G9: Niranjan Penumarthy | H9: Kiran Deshpande | J9: Active | N9: R8 | O9: Kidambi | P9: Vedkrishna | Q9: =_xludf.TEXTJOIN(" ",TRUE,O9:P9) -> #NAME? | R9: +91 | S9: 9441346181 | T9: 1-INDIA IST | U9: 2012 | V9: 1 | W9: -1 | X9: 1 | Y9: -1 | Z9: -1 | AA9: -1 | AB9: -1 | AC9: -1 | AD9: -1 | AE9: -1 | AF9: -1 | AG9: -1 | AH9: -1 | AI9: -1
A10: {=_xludf.XLOOKUP(S10,Master_Registrations!P:P,Master_Registrations!A:A,"")} -> #NAME? | B10: VED-01 | C10: 2026 | D10: BR | E10: 1 | F10: =CONCATENATE(B10,"-",C10,"-",D10,"-",E10) -> VED-01-2026-BR-1 | G10: Niranjan Penumarthy | H10: Kiran Deshpande | J10: Active | N10: R9 | O10: Mandapaka | P10: Krishna Sai Sudeep Sarma | Q10: =_xludf.TEXTJOIN(" ",TRUE,O10:P10) -> #NAME? | R10: +91 | S10: 9052550010 | T10: 1-INDIA IST | U10: 2014 | V10: 1 | W10: -1 | X10: 1 | Y10: 1 | Z10: 1 | AA10: -1 | AB10: -1 | AC10: -1 | AD10: -1 | AE10: 1 | AF10: 1 | AG10: 1 | AH10: -1 | AI10: -1
A11: {=_xludf.XLOOKUP(S11,Master_Registrations!P:P,Master_Registrations!A:A,"")} -> #NAME? | B11: VED-01 | C11: 2026 | D11: BR | E11: 1 | F11: =CONCATENATE(B11,"-",C11,"-",D11,"-",E11) -> VED-01-2026-BR-1 | G11: Niranjan Penumarthy | H11: Kiran Deshpande | J11: Active | N11: R10 | O11: Mannava | P11: Atharv | Q11: =_xludf.TEXTJOIN(" ",TRUE,O11:P11) -> #NAME? | R11: +1 | S11: 3182434371 | T11: 3-USA CST | U11: 2010 | V11: -1 | W11: -1 | X11: -1 | Y11: -1 | Z11: -1 | AA11: -1 | AB11: -1 | AC11: -1 | AD11: -1 | AE11: -1 | AF11: -1 | AG11: -1 | AH11: -1 | AI11: -1
A12: {=_xludf.XLOOKUP(S12,Master_Registrations!P:P,Master_Registrations!A:A,"")} -> #NAME? | B12: VED-01 | C12: 2026 | D12: BR | E12: 1 | F12: =CONCATENATE(B12,"-",C12,"-",D12,"-",E12) -> VED-01-2026-BR-1 | G12: Niranjan Penumarthy | H12: Kiran Deshpande | J12: Active | N12: R11 | O12: Mannava | P12: Vahin | Q12: =_xludf.TEXTJOIN(" ",TRUE,O12:P12) -> #NAME? | R12: +1 | S12: 3182434371 | T12: 3-USA CST | U12: 2014 | V12: -1 | W12: -1 | X12: -1 | Y12: -1 | Z12: -1 | AA12: -1 | AB12: -1 | AC12: -1 | AD12: -1 | AE12: -1 | AF12: -1 | AG12: -1 | AH12: -1 | AI12: -1
A13: {=_xludf.XLOOKUP(S13,Master_Registrations!P:P,Master_Registrations!A:A,"")} -> #NAME? | B13: VED-01 | C13: 2026 | D13: BR | E13: 1 | F13: =CONCATENATE(B13,"-",C13,"-",D13,"-",E13) -> VED-01-2026-BR-1 | G13: Niranjan Penumarthy | H13: Kiran Deshpande | J13: Active | N13: R12 | O13: Remella | P13: Srikar Sreshta | Q13: =_xludf.TEXTJOIN(" ",TRUE,O13:P13) -> #NAME? | R13: +91 | S13: 9160750001 | T13: 1-INDIA IST | U13: 2012 | V13: 1 | W13: 1 | X13: 1 | Y13: 1 | Z13: 1 | AA13: -1 | AB13: -1 | AC13: -1 | AD13: -1 | AE13: 1 | AF13: 1 | AG13: 1 | AH13: -1 | AI13: -1
... A15: {=_xludf.XLOOKUP(S15,Master_Registrations!P:P,Master_Registrations!A:A,"")} -> #NAME? | B15: VED-01 | C15: 2026 | D15: BR | E15: 1 | F15: =CONCATENATE(B15,"-",C15,"-",D15,"-",E15) -> VED-01-2026-BR-1 | G15: Niranjan Penumarthy | H15: Kiran Deshpande | J15: Active | N15: R14 | O15: Vemuri | P15: Anand Karthikeya | Q15: =_xludf.TEXTJOIN(" ",TRUE,O15:P15) -> #NAME? | R15: +91 | S15: 9930904698 | T15: 1-INDIA IST | U15: 2016 | V15: 1 | W15: -1 | X15: 1 | Y15: 1 | Z15: 1 | AA15: -1 | AB15: -1 | AC15: -1 | AD15: -1 | AE15: 2 | AF15: 2 | AG15: 2 | AH15: 1 | AI15: -1
A16: {=_xludf.XLOOKUP(S16,Master_Registrations!P:P,Master_Registrations!A:A,"")} -> #NAME? | B16: VED-01 | C16: 2026 | D16: BR | E16: 2 | F16: =CONCATENATE(B16,"-",C16,"-",D16,"-",E16) -> VED-01-2026-BR-2 | G16: Damodaram Tekuru | H16: Mavuduru Uma Maheshwar | J16: Active | K16: 1 | N16: R1 | O16: Akella | P16: Sai Surya Manikya Srikar Sharma | Q16: =_xludf.TEXTJOIN(" ",TRUE,O16:P16) -> #NAME? | R16: +91 | S16: 8985827908 | T16: 1-INDIA IST | U16: 2014 | V16: 1 | W16: -1 | X16: 1 | Y16: 1 | Z16: 1 | AA16: -1 | AB16: -1
A17: {=_xludf.XLOOKUP(S17,Master_Registrations!P:P,Master_Registrations!A:A,"")} -> #NAME? | B17: VED-01 | C17: 2026 | D17: BR | E17: 2 | F17: =CONCATENATE(B17,"-",C17,"-",D17,"-",E17) -> VED-01-2026-BR-2 | G17: Damodaram Tekuru | H17: Mavuduru Uma Maheshwar | J17: Active | K17: 1 | N17: R2 | O17: Ambatipudi | P17: Vibhu Sankar | Q17: =_xludf.TEXTJOIN(" ",TRUE,O17:P17) -> #NAME? | R17: +91 | S17: 7893641027 | T17: 1-INDIA IST | U17: 2016 | V17: 1 | W17: -1 | X17: -1 | Y17: 1 | Z17: 1 | AA17: -1 | AB17: -1
A18: {=_xludf.XLOOKUP(S18,Master_Registrations!P:P,Master_Registrations!A:A,"")} -> #NAME? | B18: VED-01 | C18: 2026 | D18: BR | E18: 2 | F18: =CONCATENATE(B18,"-",C18,"-",D18,"-",E18) -> VED-01-2026-BR-2 | G18: Damodaram Tekuru | H18: Mavuduru Uma Maheshwar | J18: Active | K18: 1 | N18: R3 | O18: Gorthi | P18: Shanmukha Sri Datta | Q18: =_xludf.TEXTJOIN(" ",TRUE,O18:P18) -> #NAME? | R18: +91 | S18: 9611932143 | T18: 1-INDIA IST | U18: 2012 | V18: 1 | W18: -1 | X18: -1 | Y18: 1 | Z18: -1 | AA18: -1 | AB18: -1
A19: {=_xludf.XLOOKUP(S19,Master_Registrations!P:P,Master_Registrations!A:A,"")} -> #NAME? | B19: VED-01 | C19: 2026 | D19: BR | E19: 2 | F19: =CONCATENATE(B19,"-",C19,"-",D19,"-",E19) -> VED-01-2026-BR-2 | G19: Damodaram Tekuru | H19: Mavuduru Uma Maheshwar | J19: Active | K19: 1 | N19: R4 | O19: Keely | P19: Akshay Rao | Q19: =_xludf.TEXTJOIN(" ",TRUE,O19:P19) -> #NAME? | R19: +91 | S19: 9740274684 | T19: 1-INDIA IST | U19: 2011 | V19: 1 | W19: -1 | X19: -1 | Y19: 1 | Z19: 1 | AA19: -1 | AB19: 1
A20: {=_xludf.XLOOKUP(S20,Master_Registrations!P:P,Master_Registrations!A:A,"")} -> #NAME? | B20: VED-01 | C20: 2026 | D20: BR | E20: 2 | F20: =CONCATENATE(B20,"-",C20,"-",D20,"-",E20) -> VED-01-2026-BR-2 | G20: Damodaram Tekuru | H20: Mavuduru Uma Maheshwar | J20: Active | K20: 1 | N20: R5 | O20: Kota | P20: Yasasvi Pranav | Q20: =_xludf.TEXTJOIN(" ",TRUE,O20:P20) -> #NAME? | R20: +91 | S20: 9494398425 | T20: 1-INDIA IST | U20: 2012 | V20: -1 | W20: -1 | X20: 1 | Y20: -1 | Z20: -1 | AA20: -1 | AB20: -1
A21: {=_xludf.XLOOKUP(S21,Master_Registrations!P:P,Master_Registrations!A:A,"")} -> #NAME? | B21: VED-01 | C21: 2026 | D21: BR | E21: 2 | F21: =CONCATENATE(B21,"-",C21,"-",D21,"-",E21) -> VED-01-2026-BR-2 | G21: Damodaram Tekuru | H21: Mavuduru Uma Maheshwar | J21: Active | K21: 1 | N21: R6 | O21: Kuppa | P21: Saketh Ram | Q21: =_xludf.TEXTJOIN(" ",TRUE,O21:P21) -> #NAME? | R21: +91 | S21: 6305438951 | T21: 1-INDIA IST | U21: 2014 | V21: 1 | W21: -1 | X21: -1 | Y21: -1 | Z21: -1 | AA21: -1 | AB21: -1
A22: {=_xludf.XLOOKUP(S22,Master_Registrations!P:P,Master_Registrations!A:A,"")} -> #NAME? | B22: VED-01 | C22: 2026 | D22: BR | E22: 2 | F22: =CONCATENATE(B22,"-",C22,"-",D22,"-",E22) -> VED-01-2026-BR-2 | G22: Damodaram Tekuru | H22: Mavuduru Uma Maheshwar | J22: Active | N22: R8 | O22: Mylavarapu | P22: Advaith | Q22: Mylavarapu Advaith | R22: +1 | S22: 5135601785 | T22: 2-USA EST | U22: 2016 | V22: -1 | W22: -1 | X22: -1 | Y22: -1 | Z22: -1 | AA22: -1 | AB22: -1
A23: {=_xludf.XLOOKUP(S23,Master_Registrations!P:P,Master_Registrations!A:A,"")} -> #NAME? | B23: VED-01 | C23: 2026 | D23: BR | E23: 2 | F23: =CONCATENATE(B23,"-",C23,"-",D23,"-",E23) -> VED-01-2026-BR-2 | G23: Damodaram Tekuru | H23: Mavuduru Uma Maheshwar | J23: Active | N23: R9 | O23: Niraghatam | P23: Surya | Q23: Niraghatam Surya | R23: +1 | S23: 4805932217 | T23: 3-USA CST | U23: 2014 | V23: -1 | W23: -1 | X23: -1 | Y23: -1 | Z23: -1 | AA23: -1 | AB23: -1
A24: {=_xludf.XLOOKUP(S24,Master_Registrations!P:P,Master_Registrations!A:A,"")} -> #NAME? | B24: VED-01 | C24: 2026 | D24: BR | E24: 2 | F24: =CONCATENATE(B24,"-",C24,"-",D24,"-",E24) -> VED-01-2026-BR-2 | G24: Damodaram Tekuru | H24: Mavuduru Uma Maheshwar | J24: Active | N24: R10 | O24: Puranam | P24: Shanmukhaditya | Q24: =_xludf.TEXTJOIN(" ",TRUE,O24:P24) -> #NAME? | R24: +91 | S24: 9848847831 | T24: 1-INDIA IST | U24: 2013 | V24: -1 | W24: -1 | X24: -1 | Y24: -1 | Z24: -1 | AA24: -1 | AB24: -1
A25: {=_xludf.XLOOKUP(S25,Master_Registrations!P:P,Master_Registrations!A:A,"")} -> #NAME? | B25: VED-01 | C25: 2026 | D25: BR | E25: 2 | F25: =CONCATENATE(B25,"-",C25,"-",D25,"-",E25) -> VED-01-2026-BR-2 | G25: Damodaram Tekuru | H25: Mavuduru Uma Maheshwar | J25: Active | K25: 1 | N25: R11 | O25: Saripalli | P25: Subhrahmanya Aditya | Q25: =_xludf.TEXTJOIN(" ",TRUE,O25:P25) -> #NAME? | R25: +91 | S25: 9886333667 | T25: 1-INDIA IST | U25: 2017 | V25: 1 | W25: -1 | X25: 1 | Y25: 1 | Z25: -1 | AA25: -1 | AB25: -1
A26: {=_xludf.XLOOKUP(S26,Master_Registrations!P:P,Master_Registrations!A:A,"")} -> #NAME? | B26: VED-01 | C26: 2026 | D26: BR | E26: 2 | F26: =CONCATENATE(B26,"-",C26,"-",D26,"-",E26) -> VED-01-2026-BR-2 | G26: Damodaram Tekuru | H26: Mavuduru Uma Maheshwar | J26: Active | K26: 1 | N26: R12 | O26: Tenjerla | P26: Sri Dhruva Mahesh | Q26: =_xludf.TEXTJOIN(" ",TRUE,O26:P26) -> #NAME? | R26: +91 | S26: 8147232263 | T26: 1-INDIA IST | U26: 2012 | V26: 1 | W26: -1 | X26: -1 | Y26: 1 | Z26: 1 | AA26: -1 | AB26: -1
A27: {=_xludf.XLOOKUP(S27,Master_Registrations!P:P,Master_Registrations!A:A,"")} -> #NAME? | B27: VED-01 | C27: 2026 | D27: BR | E27: 2 | F27: =CONCATENATE(B27,"-",C27,"-",D27,"-",E27) -> VED-01-2026-BR-2 | G27: Damodaram Tekuru | H27: Mavuduru Uma Maheshwar | J27: Active | N27: R13 | O27: Tenjerla | P27: Ganesh Karthik | Q27: Tenjerla Ganesh Karthik | R27: +91 | S27: 8147232263 | T27: 1-INDIA IST | U27: 2010 | V27: -1 | W27: -1 | X27: -1 | Y27: -1 | Z27: -1 | AA27: -1 | AB27: -1
A28: {=_xludf.XLOOKUP(S28,Master_Registrations!P:P,Master_Registrations!A:A,"")} -> #NAME? | B28: VED-01 | C28: 2026 | D28: BR | E28: 2 | F28: =CONCATENATE(B28,"-",C28,"-",D28,"-",E28) -> VED-01-2026-BR-2 | G28: Damodaram Tekuru | H28: Mavuduru Uma Maheshwar | J28: Active | N28: R14 | O28: Varanasi | P28: Savarni | Q28: =_xludf.TEXTJOIN(" ",TRUE,O28:P28) -> #NAME? | R28: +91 | S28: 9866707774 | T28: 1-INDIA IST | U28: 2013 | V28: -1 | W28: -1 | X28: -1 | Y28: -1 | Z28: -1 | AA28: -1 | AB28: -1
A29: {=_xludf.XLOOKUP(S29,Master_Registrations!P:P,Master_Registrations!A:A,"")} -> #NAME? | B29: VED-01 | C29: 2026 | D29: BR | E29: 2 | F29: =CONCATENATE(B29,"-",C29,"-",D29,"-",E29) -> VED-01-2026-BR-2 | G29: Damodaram Tekuru | H29: Mavuduru Uma Maheshwar | J29: Active | N29: R15 | O29: Vedula | P29: Jithamithra | Q29: =_xludf.TEXTJOIN(" ",TRUE,O29:P29) -> #NAME? | R29: +1 | S29: 2488021056 | T29: 2-USA EST | U29: 2016 | V29: 1 | W29: -1 | X29: 1 | Y29: 1 | Z29: 1 | AA29: -1 | AB29: -1
A30: {=_xludf.XLOOKUP(S30,Master_Registrations!P:P,Master_Registrations!A:A,"")} -> #NAME? | B30: VED-01 | C30: 2026 | D30: BR | E30: 3 | F30: =CONCATENATE(B30,"-",C30,"-",D30,"-",E30) -> VED-01-2026-BR-3 | G30: Sripada Srinivas | H30: Shivakumar Challa | J30: Active | K30: 1 | N30: R1 | O30: Ayyalasomayajula | P30: Soorya Manoo | Q30: =_xludf.TEXTJOIN(" ",TRUE,O30:P30) -> #NAME? | R30: +1 | S30: 8327481679 | T30: 3-USA CST | U30: 2015 | V30: -1 | W30: -1 | X30: -1
A31: {=_xludf.XLOOKUP(S31,Master_Registrations!P:P,Master_Registrations!A:A,"")} -> #NAME? | B31: VED-01 | C31: 2026 | D31: BR | E31: 3 | F31: =CONCATENATE(B31,"-",C31,"-",D31,"-",E31) -> VED-01-2026-BR-3 | G31: Sripada Srinivas | H31: Shivakumar Challa | J31: Active | K31: 1 | N31: R2 | O31: Bhattar | P31: Vaishnav | Q31: =_xludf.TEXTJOIN(" ",TRUE,O31:P31) -> #NAME? | R31: +1 | S31: 8382620227 | T31: 2-USA EST | U31: 2010 | V31: -1 | W31: -1 | X31: -1
A32: {=_xludf.XLOOKUP(S32,Master_Registrations!P:P,Master_Registrations!A:A,"")} -> #NAME? | B32: VED-01 | C32: 2026 | D32: BR | E32: 3 | F32: =CONCATENATE(B32,"-",C32,"-",D32,"-",E32) -> VED-01-2026-BR-3 | G32: Sripada Srinivas | H32: Shivakumar Challa | J32: Active | K32: 1 | N32: R3 | O32: Burugula | P32: Abhiram | Q32: =_xludf.TEXTJOIN(" ",TRUE,O32:P32) -> #NAME? | R32: +1 | S32: 6099370666 | T32: 3-USA CST | U32: 2018 | V32: -1 | W32: -1 | X32: -1
A33: {=_xludf.XLOOKUP(S33,Master_Registrations!P:P,Master_Registrations!A:A,"")} -> #NAME? | B33: VED-01 | C33: 2026 | D33: BR | E33: 3 | F33: =CONCATENATE(B33,"-",C33,"-",D33,"-",E33) -> VED-01-2026-BR-3 | G33: Sripada Srinivas | H33: Shivakumar Challa | J33: Active | K33: 1 | N33: R4 | O33: Julakanti | P33: Venkata Vishruth Vachan | Q33: =_xludf.TEXTJOIN(" ",TRUE,O33:P33) -> #NAME? | R33: +1 | S33: 5129034955 | T33: 3-USA CST | U33: 2011 | V33: -1 | W33: -1 | X33: -1
A34: {=_xludf.XLOOKUP(S34,Master_Registrations!P:P,Master_Registrations!A:A,"")} -> #NAME? | B34: VED-01 | C34: 2026 | D34: BR | E34: 3 | F34: =CONCATENATE(B34,"-",C34,"-",D34,"-",E34) -> VED-01-2026-BR-3 | G34: Sripada Srinivas | H34: Shivakumar Challa | J34: Active | N34: R5 | O34: Kandukuri | P34: Veda Rushi | Q34: =_xludf.TEXTJOIN(" ",TRUE,O34:P34) -> #NAME? | R34: +91 | S34: 8688328602 | T34: 1-INDIA IST | U34: 2013 | V34: -1 | W34: -1 | X34: -1
A35: {=_xludf.XLOOKUP(S35,Master_Registrations!P:P,Master_Registrations!A:A,"")} -> #NAME? | B35: VED-01 | C35: 2026 | D35: BR | E35: 3 | F35: =CONCATENATE(B35,"-",C35,"-",D35,"-",E35) -> VED-01-2026-BR-3 | G35: Sripada Srinivas | H35: Shivakumar Challa | J35: Active | K35: 1 | N35: R6 | O35: Kota | P35: Karthikeya | Q35: =_xludf.TEXTJOIN(" ",TRUE,O35:P35) -> #NAME? | R35: +91 | S35: 8106966654 | T35: 1-INDIA IST | U35: 2014 | V35: -1 | W35: -1 | X35: -1
A36: =_xlfn.XLOOKUP(S36,Master_Registrations!P:P,Master_Registrations!A:A,"") -> 2025 | B36: VED-01 | C36: 2026 | D36: BR | E36: 3 | F36: =CONCATENATE(B36,"-",C36,"-",D36,"-",E36) -> VED-01-2026-BR-3 | G36: Sripada Srinivas | H36: Shivakumar Challa | J36: Active | N36: R7 | O36: Mellachervu | P36: Srikar | Q36: =_xludf.TEXTJOIN(" ",TRUE,O36:P36) -> #NAME? | R36: +1 | S36: 8609048328 | T36: 3-USA CST | U36: 2013 | V36: -1 | W36: -1 | X36: -1
A37: {=_xludf.XLOOKUP(S37,Master_Registrations!P:P,Master_Registrations!A:A,"")} -> #NAME? | B37: VED-01 | C37: 2026 | D37: BR | E37: 3 | F37: =CONCATENATE(B37,"-",C37,"-",D37,"-",E37) -> VED-01-2026-BR-3 | G37: Sripada Srinivas | H37: Shivakumar Challa | J37: Active | K37: 1 | N37: R8 | O37: Murthinty | P37: Venkata Shivark | Q37: =_xludf.TEXTJOIN(" ",TRUE,O37:P37) -> #NAME? | R37: +1 | S37: 3068804239 | T37: 2-USA EST | U37: 2013 | V37: -1 | W37: -1 | X37: -1
A38: {=_xludf.XLOOKUP(S38,Master_Registrations!P:P,Master_Registrations!A:A,"")} -> #NAME? | B38: VED-01 | C38: 2026 | D38: BR | E38: 3 | F38: =CONCATENATE(B38,"-",C38,"-",D38,"-",E38) -> VED-01-2026-BR-3 | G38: Sripada Srinivas | H38: Shivakumar Challa | J38: Active | K38: 1 | N38: R9 | O38: Patiballa | P38: Krishna Vamsee | Q38: =_xludf.TEXTJOIN(" ",TRUE,O38:P38) -> #NAME? | R38: +91 | S38: 8341673687 | T38: 1-INDIA IST | U38: 2011 | V38: -1 | W38: -1 | X38: -1
A39: {=_xludf.XLOOKUP(S39,Master_Registrations!P:P,Master_Registrations!A:A,"")} -> #NAME? | B39: VED-01 | C39: 2026 | D39: BR | E39: 3 | F39: =CONCATENATE(B39,"-",C39,"-",D39,"-",E39) -> VED-01-2026-BR-3 | G39: Sripada Srinivas | H39: Shivakumar Challa | J39: Active | K39: 1 | N39: R10 | O39: Potukuchi | P39: Sivateja | Q39: =_xludf.TEXTJOIN(" ",TRUE,O39:P39) -> #NAME? | R39: +1 | S39: 8036293505 | T39: 4-USA MST/PST | U39: 2014 | V39: -1 | W39: -1 | X39: -1
A40: {=_xludf.XLOOKUP(S40,Master_Registrations!P:P,Master_Registrations!A:A,"")} -> #NAME? | B40: VED-01 | C40: 2026 | D40: BR | E40: 4 | F40: =CONCATENATE(B40,"-",C40,"-",D40,"-",E40) -> VED-01-2026-BR-4 | G40: Penumarthi Niranjana | H40: Gundu Rama Murthy | J40: Active | K40: 1 | N40: R1 | O40: Kandukuri | P40: Poorna Sashi | Q40: =_xludf.TEXTJOIN(" ",TRUE,O40:P40) -> #NAME? | R40: +91 | S40: 8688328602 | T40: 1-INDIA IST | U40: 2017 | V40: -1 | W40: -1 | X40: -1
A41: {=_xludf.XLOOKUP(S41,Master_Registrations!P:P,Master_Registrations!A:A,"")} -> #NAME? | B41: VED-01 | C41: 2026 | D41: BR | E41: 4 | F41: =CONCATENATE(B41,"-",C41,"-",D41,"-",E41) -> VED-01-2026-BR-4 | G41: Penumarthi Niranjana | H41: Gundu Rama Murthy | J41: Active | K41: 1 | N41: R2 | O41: Mandagondi | P41: Ravi Krishna Sathwik | Q41: =_xludf.TEXTJOIN(" ",TRUE,O41:P41) -> #NAME? | R41: +91 | S41: 9248585989 | T41: 1-INDIA IST | U41: 2012 | V41: -1 | W41: -1 | X41: -1
A42: {=_xludf.XLOOKUP(S42,Master_Registrations!P:P,Master_Registrations!A:A,"")} -> #NAME? | B42: VED-01 | C42: 2026 | D42: BR | E42: 4 | F42: =CONCATENATE(B42,"-",C42,"-",D42,"-",E42) -> VED-01-2026-BR-4 | G42: Penumarthi Niranjana | H42: Gundu Rama Murthy | J42: Active | N42: R3 | O42: Mutnuru | P42: Venkata Satya Surya Abhiram | Q42: =_xludf.TEXTJOIN(" ",TRUE,O42:P42) -> #NAME? | R42: +91 | S42: 9985404530 | T42: 1-INDIA IST | U42: 2010 | V42: -1 | W42: -1 | X42: -1
A43: {=_xludf.XLOOKUP(S43,Master_Registrations!P:P,Master_Registrations!A:A,"")} -> #NAME? | B43: VED-01 | C43: 2026 | D43: BR | E43: 4 | F43: =CONCATENATE(B43,"-",C43,"-",D43,"-",E43) -> VED-01-2026-BR-4 | G43: Penumarthi Niranjana | H43: Gundu Rama Murthy | J43: Active | K43: 1 | N43: R4 | O43: Mutnuru | P43: Aditya Sri Krishna | Q43: =_xludf.TEXTJOIN(" ",TRUE,O43:P43) -> #NAME? | R43: +91 | S43: 9985404530 | T43: 1-INDIA IST | U43: 2014 | V43: -1 | W43: -1 | X43: -1
A44: {=_xludf.XLOOKUP(S44,Master_Registrations!P:P,Master_Registrations!A:A,"")} -> #NAME? | B44: VED-01 | C44: 2026 | D44: BR | E44: 4 | F44: =CONCATENATE(B44,"-",C44,"-",D44,"-",E44) -> VED-01-2026-BR-4 | G44: Penumarthi Niranjana | H44: Gundu Rama Murthy | J44: Active | K44: 1 | N44: R5 | O44: Ponnada | P44: Aayansh | Q44: =_xludf.TEXTJOIN(" ",TRUE,O44:P44) -> #NAME? | R44: +91 | S44: 9010586515 | T44: 1-INDIA IST | U44: 2019 | V44: -1 | W44: -1 | X44: -1
A45: {=_xludf.XLOOKUP(S45,Master_Registrations!P:P,Master_Registrations!A:A,"")} -> #NAME? | B45: VED-01 | C45: 2026 | D45: BR | E45: 4 | F45: =CONCATENATE(B45,"-",C45,"-",D45,"-",E45) -> VED-01-2026-BR-4 | G45: Penumarthi Niranjana | H45: Gundu Rama Murthy | J45: Active | K45: 1 | N45: R6 | O45: Swayampakula | P45: Layakari | Q45: =_xludf.TEXTJOIN(" ",TRUE,O45:P45) -> #NAME? | R45: +91 | S45: 7386662938 | T45: 1-INDIA IST | U45: 2015 | V45: -1 | W45: -1 | X45: -1
A46: {=_xludf.XLOOKUP(S46,Master_Registrations!P:P,Master_Registrations!A:A,"")} -> #NAME? | B46: VED-01 | C46: 2026 | D46: BR | E46: 4 | F46: =CONCATENATE(B46,"-",C46,"-",D46,"-",E46) -> VED-01-2026-BR-4 | G46: Penumarthi Niranjana | H46: Gundu Rama Murthy | J46: Active | K46: 1 | N46: R7 | O46: Tondapi | P46: Abhiram | Q46: =_xludf.TEXTJOIN(" ",TRUE,O46:P46) -> #NAME? | R46: +91 | S46: 9440514090 | T46: 1-INDIA IST | U46: 2012 | V46: -1 | W46: -1 | X46: -1
A47: {=_xludf.XLOOKUP(S47,Master_Registrations!P:P,Master_Registrations!A:A,"")} -> #NAME? | B47: VED-03 | C47: 2026 | D47: BR | E47: 1 | F47: =CONCATENATE(B47,"-",C47,"-",D47,"-",E47) -> VED-03-2026-BR-1 | G47: Jagarlapudi Surya Venkata Srikanth | H47: Penumarthy Niranjana | J47: Active | N47: R1 | O47: Challa | P47: Aditya | Q47: =_xludf.TEXTJOIN(" ",TRUE,O47:P47) -> #NAME? | R47: +91 | S47: 7702962333 | T47: 1-INDIA IST | U47: 2009 | V47: 2 | W47: 2 | X47: 2 | Y47: 2 | Z47: 2 | AA47: 2 | AB47: 2 | AC47: 2 | AD47: 2 | AE47: 2 | AF47: 2 | AG47: 2 | AH47: 2 | AI47: 4 | AJ47: 2 | AK47: -1 | AL47: 2 | AM47: -1 | AN47: 1 | AO47: 1 | AP47: -1 | AQ47: 1 | AR47: 1 | AS47: 1 | AT47: -1 | AU47: -1 | AV47: -1 | AW47: -1 | AX47: -1 | AY47: 1 | AZ47: -1 | BA47: -1 | BB47: -1 | BC47: -1 | BD47: -1
A48: {=_xludf.XLOOKUP(S48,Master_Registrations!P:P,Master_Registrations!A:A,"")} -> #NAME? | B48: VED-03 | C48: 2026 | D48: BR | E48: 1 | F48: =CONCATENATE(B48,"-",C48,"-",D48,"-",E48) -> VED-03-2026-BR-1 | G48: Jagarlapudi Surya Venkata Srikanth | H48: Penumarthy Niranjana | J48: Active | N48: R2 | O48: Gantasala | P48: Agasthya | Q48: =_xludf.TEXTJOIN(" ",TRUE,O48:P48) -> #NAME? | R48: +91 | S48: 9866462617 | T48: 1-INDIA IST | U48: 2010 | V48: 2 | W48: 2 | X48: 2 | Y48: 2 | Z48: 2 | AA48: 2 | AB48: 2 | AC48: 2 | AD48: 2 | AE48: 2 | AF48: 2 | AG48: 2 | AH48: 2 | AI48: 3 | AJ48: 2 | AK48: 2 | AL48: 2 | AM48: 2 | AN48: 2 | AO48: 2 | AP48: 2 | AQ48: 2 | AR48: 2 | AS48: 2 | AT48: 2 | AU48: 2 | AV48: 4 | AW48: -1 | AX48: -1 | AY48: 2 | AZ48: -1 | BA48: -1 | BB48: -1 | BC48: -1 | BD48: -1
A49: {=_xludf.XLOOKUP(S49,Master_Registrations!P:P,Master_Registrations!A:A,"")} -> #NAME? | B49: VED-03 | C49: 2026 | D49: BR | E49: 1 | F49: =CONCATENATE(B49,"-",C49,"-",D49,"-",E49) -> VED-03-2026-BR-1 | G49: Jagarlapudi Surya Venkata Srikanth | H49: Penumarthy Niranjana | J49: Active | N49: R3 | O49: Gobburu | P49: Vishnu Sreevardhan | Q49: =_xludf.TEXTJOIN(" ",TRUE,O49:P49) -> #NAME? | R49: +91 | S49: 9491380172 | T49: 1-INDIA IST | U49: 2014 | V49: 2 | W49: 2 | X49: 2 | Y49: 2 | Z49: 2 | AA49: 2 | AB49: 2 | AC49: 2 | AD49: 2 | AE49: 2 | AF49: 2 | AG49: 2 | AH49: 2 | AI49: 3 | AJ49: 2 | AK49: 2 | AL49: 2 | AM49: 2 | AN49: 2 | AO49: 2 | AP49: 2 | AQ49: 2 | AR49: 2 | AS49: 2 | AT49: 2 | AU49: 2 | AV49: 4 | AW49: -1 | AX49: -1 | AY49: 2 | AZ49: -1 | BA49: -1 | BB49: -1 | BC49: -1 | BD49: -1
A50: {=_xludf.XLOOKUP(S50,Master_Registrations!P:P,Master_Registrations!A:A,"")} -> #NAME? | B50: VED-03 | C50: 2026 | D50: BR | E50: 1 | F50: =CONCATENATE(B50,"-",C50,"-",D50,"-",E50) -> VED-03-2026-BR-1 | G50: Jagarlapudi Surya Venkata Srikanth | H50: Penumarthy Niranjana | J50: Active | N50: R4 | O50: Jagarlapudi | P50: Surya Abhiram | Q50: Jagarlapudi Surya Abhiram | R50: +91 | S50: 9958562369 | T50: 1-INDIA IST | U50: 2011 | V50: 2 | W50: 2 | X50: 2 | Y50: 2 | Z50: 2 | AA50: 2 | AB50: 2 | AC50: 2 | AD50: 2 | AE50: 2 | AF50: 2 | AG50: 2 | AH50: 2 | AI50: 4 | AJ50: 2 | AK50: 2 | AL50: 2 | AM50: 2 | AN50: 2 | AO50: 2 | AP50: 2 | AQ50: 2 | AR50: 2 | AS50: 2 | AT50: 2 | AU50: 2 | AV50: 4 | AW50: -1 | AX50: -1 | AY50: 2 | AZ50: -1 | BA50: -1 | BB50: -1 | BC50: -1 | BD50: -1
A51: =_xlfn.XLOOKUP(S51,Master_Registrations!P:P,Master_Registrations!A:A,"") -> 2024 | B51: VED-03 | C51: 2026 | D51: BR | E51: 1 | F51: =CONCATENATE(B51,"-",C51,"-",D51,"-",E51) -> VED-03-2026-BR-1 | G51: Jagarlapudi Surya Venkata Srikanth | H51: Penumarthy Niranjana | J51: Active | N51: R5 | O51: Kamasamudram | P51: Rishi Subhanshu | Q51: =_xludf.TEXTJOIN(" ",TRUE,O51:P51) -> #NAME? | R51: +91 | S51: 9160044414 | T51: 1-INDIA IST | U51: 2010 | V51: 2 | W51: 2 | X51: 2 | Y51: 2 | Z51: 2 | AA51: 2 | AB51: 2 | AC51: 2 | AD51: 2 | AE51: 2 | AF51: 2 | AG51: 2 | AH51: 2 | AI51: 3 | AJ51: 2 | AK51: 2 | AL51: 2 | AM51: 2 | AN51: 2 | AO51: 2 | AP51: 2 | AQ51: 2 | AR51: 2 | AS51: 2 | AT51: 2 | AU51: 2 | AV51: 4 | AW51: -1 | AX51: -1 | AY51: 2 | AZ51: -1 | BA51: -1 | BB51: -1 | BC51: -1 | BD51: -1
A52: =_xlfn.XLOOKUP(S52,Master_Registrations!P:P,Master_Registrations!A:A,"") -> 2023 | B52: VED-03 | C52: 2026 | D52: BR | E52: 1 | F52: =CONCATENATE(B52,"-",C52,"-",D52,"-",E52) -> VED-03-2026-BR-1 | G52: Jagarlapudi Surya Venkata Srikanth | H52: Penumarthy Niranjana | J52: Active | N52: R6 | O52: Kotamraju | P52: Hanumath Shanmukh | Q52: =_xludf.TEXTJOIN(" ",TRUE,O52:P52) -> #NAME? | R52: +91 | S52: 8985971092 | T52: 1-INDIA IST | U52: 2011 | V52: 2 | W52: 2 | X52: 2 | Y52: 2 | Z52: 2 | AA52: 2 | AB52: 2 | AC52: 2 | AD52: 2 | AE52: 2 | AF52: 2 | AG52: 2 | AH52: 2 | AI52: 4 | AJ52: 2 | AK52: 2 | AL52: 2 | AM52: 2 | AN52: 2 | AO52: 2 | AP52: 2 | AQ52: 2 | AR52: 2 | AS52: 2 | AT52: 2 | AU52: 2 | AV52: -1 | AW52: -1 | AX52: -1 | AY52: 2 | AZ52: -1 | BA52: -1 | BB52: -1 | BC52: -1 | BD52: -1
A53: {=_xludf.XLOOKUP(S53,Master_Registrations!P:P,Master_Registrations!A:A,"")} -> #NAME? | B53: VED-03 | C53: 2026 | D53: BR | E53: 1 | F53: =CONCATENATE(B53,"-",C53,"-",D53,"-",E53) -> VED-03-2026-BR-1 | G53: Jagarlapudi Surya Venkata Srikanth | H53: Penumarthy Niranjana | J53: Active | N53: R7 | O53: Kotumraju | P53: Bharavi | Q53: =_xludf.TEXTJOIN(" ",TRUE,O53:P53) -> #NAME? | R53: +91 | S53: 9007684641 | T53: 1-INDIA IST | U53: 2010 | V53: 1 | W53: 1 | X53: 1 | Y53: 1 | Z53: 1 | AA53: 1 | AB53: 1 | AC53: 1 | AD53: 1 | AE53: 1 | AF53: 1 | AG53: 1 | AH53: 1 | AI53: -1 | AJ53: -1 | AK53: -1 | AL53: 1 | AM53: -1 | AN53: 1 | AO53: 2 | AP53: -1 | AQ53: -1 | AR53: 2 | AS53: -1 | AT53: -1 | AU53: -1 | AV53: -1 | AW53: -1 | AX53: -1 | AY53: -1 | AZ53: -1 | BA53: -1 | BB53: -1 | BC53: -1 | BD53: -1
A54: {=_xludf.XLOOKUP(S54,Master_Registrations!P:P,Master_Registrations!A:A,"")} -> #NAME? | B54: VED-03 | C54: 2026 | D54: BR | E54: 1 | F54: =CONCATENATE(B54,"-",C54,"-",D54,"-",E54) -> VED-03-2026-BR-1 | G54: Jagarlapudi Surya Venkata Srikanth | H54: Penumarthy Niranjana | J54: Active | N54: R8 | O54: Maganti | P54: Venkata Siva Subrahamanya Abhinava Charan | Q54: =_xludf.TEXTJOIN(" ",TRUE,O54:P54) -> #NAME? | R54: +91 | S54: 8105178555 | T54: 1-INDIA IST | U54: 2013 | V54: 2 | W54: 2 | X54: 2 | Y54: 2 | Z54: 2 | AA54: 2 | AB54: 2 | AC54: 2 | AD54: 2 | AE54: 2 | AF54: 2 | AG54: 2 | AH54: 2 | AI54: 4 | AJ54: 2 | AK54: 2 | AL54: 2 | AM54: 2 | AN54: 2 | AO54: 2 | AP54: 2 | AQ54: 2 | AR54: 2 | AS54: 2 | AT54: 2 | AU54: 2 | AV54: 4 | AW54: -1 | AX54: -1 | AY54: 2 | AZ54: -1 | BA54: -1 | BB54: -1 | BC54: -1 | BD54: -1
A55: {=_xludf.XLOOKUP(S55,Master_Registrations!P:P,Master_Registrations!A:A,"")} -> #NAME? | B55: VED-03 | C55: 2026 | D55: BR | E55: 1 | F55: =CONCATENATE(B55,"-",C55,"-",D55,"-",E55) -> VED-03-2026-BR-1 | G55: Jagarlapudi Surya Venkata Srikanth | H55: Penumarthy Niranjana | J55: Active | N55: R9 | O55: Manikonda | P55: Yathin Chandra | Q55: =_xludf.TEXTJOIN(" ",TRUE,O55:P55) -> #NAME? | R55: +91 | S55: 7799558759 | T55: 1-INDIA IST | U55: 2010 | V55: 2 | W55: 2 | X55: 2 | Y55: 2 | Z55: 2 | AA55: 2 | AB55: 2 | AC55: 2 | AD55: 2 | AE55: 2 | AF55: 2 | AG55: 2 | AH55: 2 | AI55: 4 | AJ55: 2 | AK55: 2 | AL55: 2 | AM55: 2 | AN55: 2 | AO55: 2 | AP55: 2 | AQ55: 2 | AR55: 2 | AS55: 2 | AT55: 2 | AU55: 2 | AV55: 4 | AW55: -1 | AX55: -1 | AY55: 1 | AZ55: -1 | BA55: -1 | BB55: -1 | BC55: -1 | BD55: -1
A56: {=_xludf.XLOOKUP(S56,Master_Registrations!P:P,Master_Registrations!A:A,"")} -> #NAME? | B56: VED-03 | C56: 2026 | D56: BR | E56: 2 | F56: =CONCATENATE(B56,"-",C56,"-",D56,"-",E56) -> VED-03-2026-BR-2 | G56: Jagarlapudi Surya Venkata Srikanth | H56: Sri Teja Burra | J56: Active | N56: R1 | O56: Balantrapu | P56: Sai Sri Vallabh | Q56: =_xludf.TEXTJOIN(" ",TRUE,O56:P56) -> #NAME? | R56: +91 | S56: 7702648904 | T56: 1-INDIA IST | U56: 2012 | V56: 1 | W56: 1 | X56: 2 | Y56: 2 | Z56: 2 | AA56: 2 | AB56: 2 | AC56: 1 | AD56: 2 | AE56: 2 | AF56: 2 | AG56: 2 | AH56: 1 | AI56: -1 | AJ56: -1 | AK56: -1 | AL56: -1 | AM56: -1 | AN56: -1 | AO56: -1 | AP56: -1 | AQ56: -1 | AR56: -1 | AS56: -1 | AT56: -1 | AU56: -1 | AV56: -1 | AW56: -1 | AX56: -1 | AY56: -1 | AZ56: -1 | BA56: -1
A57: {=_xludf.XLOOKUP(S57,Master_Registrations!P:P,Master_Registrations!A:A,"")} -> #NAME? | B57: VED-03 | C57: 2026 | D57: BR | E57: 2 | F57: =CONCATENATE(B57,"-",C57,"-",D57,"-",E57) -> VED-03-2026-BR-2 | G57: Jagarlapudi Surya Venkata Srikanth | H57: Sri Teja Burra | J57: Active | N57: R2 | O57: Chitta | P57: Achyutha Krishna Murthy | Q57: =_xludf.TEXTJOIN(" ",TRUE,O57:P57) -> #NAME? | R57: +91 | S57: 9182608457 | T57: 1-INDIA IST | U57: 2010 | V57: 2 | W57: 2 | X57: 2 | Y57: 2 | Z57: 2 | AA57: 2 | AB57: 2 | AC57: 2 | AD57: 2 | AE57: 2 | AF57: 2 | AG57: 2 | AH57: 2 | AI57: 4 | AJ57: 1 | AK57: 1 | AL57: 1 | AM57: 1 | AN57: 1 | AO57: 1 | AP57: 1 | AQ57: -1 | AR57: 1 | AS57: 1 | AT57: -1 | AU57: 1 | AV57: -1 | AW57: -1 | AX57: -1 | AY57: -1 | AZ57: -1 | BA57: -1 | BB57: -1 | BC57: -1 | BD57: -1
A58: {=_xludf.XLOOKUP(S58,Master_Registrations!P:P,Master_Registrations!A:A,"")} -> #NAME? | B58: VED-03 | C58: 2026 | D58: BR | E58: 2 | F58: =CONCATENATE(B58,"-",C58,"-",D58,"-",E58) -> VED-03-2026-BR-2 | G58: Jagarlapudi Surya Venkata Srikanth | H58: Sri Teja Burra | J58: Active | N58: R3 | O58: Devarakonda | P58: Siva Karthik | Q58: =_xludf.TEXTJOIN(" ",TRUE,O58:P58) -> #NAME? | R58: +91 | S58: 9538199720 | T58: 1-INDIA IST | U58: 2012 | V58: 2 | W58: 2 | X58: 2 | Y58: 2 | Z58: 2 | AA58: 2 | AB58: 2 | AC58: 2 | AD58: 2 | AE58: 2 | AF58: 2 | AG58: 2 | AH58: 2 | AI58: -1 | AJ58: 1 | AK58: 1 | AL58: 1 | AM58: 1 | AN58: 1 | AO58: 1 | AP58: -1 | AQ58: -1 | AR58: -1 | AS58: -1 | AT58: -1 | AU58: 1 | AV58: -1 | AW58: -1 | AX58: -1 | AY58: -1 | AZ58: -1 | BA58: -1
A59: {=_xludf.XLOOKUP(S59,Master_Registrations!P:P,Master_Registrations!A:A,"")} -> #NAME? | B59: VED-03 | C59: 2026 | D59: BR | E59: 2 | F59: =CONCATENATE(B59,"-",C59,"-",D59,"-",E59) -> VED-03-2026-BR-2 | G59: Jagarlapudi Surya Venkata Srikanth | H59: Sri Teja Burra | J59: Active | N59: R4 | O59: Jagarlapudi | P59: Surya Venkata Shanmukha Sai Pranav | Q59: =_xludf.TEXTJOIN(" ",TRUE,O59:P59) -> #NAME? | R59: +91 | S59: 9440766356 | T59: 1-INDIA IST | U59: 2016 | V59: 2 | W59: 2 | X59: 2 | Y59: 2 | Z59: 2 | AA59: 2 | AB59: 2 | AC59: 2 | AD59: 2 | AE59: 2 | AF59: 2 | AG59: 2 | AH59: 2 | AI59: 4 | AJ59: 1 | AK59: 1 | AL59: 1 | AM59: -1 | AN59: 1 | AO59: 1 | AP59: 1 | AQ59: 1 | AR59: -1 | AS59: -1 | AT59: -1 | AU59: -1 | AV59: -1 | AW59: -1 | AX59: -1 | AY59: -1 | AZ59: -1 | BA59: -1
A60: {=_xludf.XLOOKUP(S60,Master_Registrations!P:P,Master_Registrations!A:A,"")} -> #NAME? | B60: VED-03 | C60: 2026 | D60: BR | E60: 2 | F60: =CONCATENATE(B60,"-",C60,"-",D60,"-",E60) -> VED-03-2026-BR-2 | G60: Jagarlapudi Surya Venkata Srikanth | H60: Sri Teja Burra | J60: Active | N60: R5 | O60: Kuppa | P60: Ganesha vamsidhar | Q60: =_xludf.TEXTJOIN(" ",TRUE,O60:P60) -> #NAME? | R60: +91 | S60: 9966238978 | T60: 1-INDIA IST | U60: 2012 | V60: 2 | W60: 2 | X60: 2 | Y60: 2 | Z60: 2 | AA60: 2 | AB60: 2 | AC60: 2 | AD60: 2 | AE60: 2 | AF60: 2 | AG60: 2 | AH60: 2 | AI60: 4
A61: {=_xludf.XLOOKUP(S61,Master_Registrations!P:P,Master_Registrations!A:A,"")} -> #NAME? | B61: VED-03 | C61: 2026 | D61: BR | E61: 2 | F61: =CONCATENATE(B61,"-",C61,"-",D61,"-",E61) -> VED-03-2026-BR-2 | G61: Jagarlapudi Surya Venkata Srikanth | H61: Sri Teja Burra | J61: Active | N61: R6 | O61: Manikonda | P61: Parthasaradhi | Q61: =_xludf.TEXTJOIN(" ",TRUE,O61:P61) -> #NAME? | R61: +91 | S61: 7995955739 | T61: 1-INDIA IST | U61: 2004 | V61: 1 | W61: 1 | X61: 1 | Y61: 1 | Z61: 1 | AA61: 1 | AB61: -1 | AC61: 1 | AD61: -1 | AE61: 1 | AF61: 1 | AG61: 1 | AH61: 1 | AI61: -1 | AJ61: -1 | AK61: -1 | AL61: -1 | AM61: -1 | AN61: -1 | AO61: -1 | AP61: -1 | AQ61: -1 | AR61: -1 | AS61: -1 | AT61: -1 | AU61: -1 | AV61: -1 | AW61: -1 | AX61: -1 | AY61: -1 | AZ61: -1 | BA61: -1
A62: {=_xludf.XLOOKUP(S62,Master_Registrations!P:P,Master_Registrations!A:A,"")} -> #NAME? | B62: VED-03 | C62: 2026 | D62: BR | E62: 2 | F62: =CONCATENATE(B62,"-",C62,"-",D62,"-",E62) -> VED-03-2026-BR-2 | G62: Jagarlapudi Surya Venkata Srikanth | H62: Sri Teja Burra | J62: Active | N62: R7 | O62: Muthyam | P62: Abhiram Rao | Q62: =_xludf.TEXTJOIN(" ",TRUE,O62:P62) -> #NAME? | R62: +91 | S62: 9121432011 | T62: 1-INDIA IST | U62: 2009 | V62: 2 | W62: 2 | X62: 2 | Y62: 2 | Z62: 2 | AA62: 2 | AB62: 2 | AC62: 2 | AD62: 2 | AE62: 2 | AF62: 2 | AG62: 2 | AH62: 2 | AI62: 4 | AJ62: 1 | AK62: 1 | AL62: -1 | AM62: 1 | AN62: 1 | AO62: 1 | AP62: -1 | AQ62: -1 | AR62: -1 | AS62: -1 | AT62: -1 | AU62: -1 | AV62: -1 | AW62: -1 | AX62: -1 | AY62: -1 | AZ62: -1 | BA62: -1
A63: {=_xludf.XLOOKUP(S63,Master_Registrations!P:P,Master_Registrations!A:A,"")} -> #NAME? | B63: VED-03 | C63: 2026 | D63: BR | E63: 2 | F63: =CONCATENATE(B63,"-",C63,"-",D63,"-",E63) -> VED-03-2026-BR-2 | G63: Jagarlapudi Surya Venkata Srikanth | H63: Sri Teja Burra | J63: Active | N63: R8 | O63: Tadepally | P63: Sri Rama Karthikeya Sharma | Q63: =_xludf.TEXTJOIN(" ",TRUE,O63:P63) -> #NAME? | R63: +91 | S63: 9940343476 | T63: 1-INDIA IST | U63: 2013 | V63: 2 | W63: 2 | X63: 2 | Y63: 2 | Z63: 2 | AA63: 2 | AB63: 2 | AC63: 2 | AD63: 2 | AE63: 2 | AF63: 2 | AG63: 2 | AH63: 2 | AI63: -1 | AJ63: -1 | AK63: -1 | AL63: -1 | AM63: 1 | AN63: -1 | AO63: -1 | AP63: -1 | AQ63: -1 | AR63: -1 | AS63: -1 | AT63: -1 | AU63: -1 | AV63: -1 | AW63: -1 | AX63: -1 | AY63: -1 | AZ63: -1 | BA63: -1
A64: {=_xludf.XLOOKUP(S64,Master_Registrations!P:P,Master_Registrations!A:A,"")} -> #NAME? | B64: VED-03 | C64: 2026 | D64: BR | E64: 2 | F64: =CONCATENATE(B64,"-",C64,"-",D64,"-",E64) -> VED-03-2026-BR-2 | G64: Jagarlapudi Surya Venkata Srikanth | H64: Sri Teja Burra | J64: Active | N64: R9 | O64: Yasasvi | P64: Krishna | Q64: =_xludf.TEXTJOIN(" ",TRUE,O64:P64) -> #NAME? | R64: +91 | S64: 9414349343 | T64: 1-INDIA IST | U64: 2013 | V64: 2 | W64: 2 | X64: 2 | Y64: 2 | Z64: 2 | AA64: 2 | AB64: 2 | AC64: 2 | AD64: 2 | AE64: 2 | AF64: 2 | AG64: 2 | AH64: 2 | AI64: 4 | AJ64: 1 | AK64: 1 | AL64: 1 | AM64: 1 | AN64: 1 | AO64: 1 | AP64: 1 | AQ64: -1 | AR64: 1 | AS64: -1 | AT64: -1 | AU64: -1 | AV64: -1 | AW64: -1 | AX64: -1 | AY64: -1 | AZ64: -1 | BA64: -1 | BB64: -1 | BC64: -1 | BD64: -1
A65: {=_xludf.XLOOKUP(S65,Master_Registrations!P:P,Master_Registrations!A:A,"")} -> #NAME? | B65: VED-03 | C65: 2026 | D65: BR | E65: 3 | F65: =CONCATENATE(B65,"-",C65,"-",D65,"-",E65) -> VED-03-2026-BR-3 | G65: Shiva Kumar Challa | H65: Aniruddha Pochimcherla | J65: Active | N65: R1 | O65: Bandhakavi | P65: Harikesa | Q65: =_xludf.TEXTJOIN(" ",TRUE,O65:P65) -> #NAME? | R65: +1 | S65: 3477527257 | T65: 3-USA CST | U65: 2011 | V65: 2 | W65: 2 | X65: 2 | Y65: 2 | Z65: 2 | AA65: 2 | AB65: 2 | AC65: 2 | AD65: 2 | AE65: 2 | AF65: 2 | AG65: 2 | AH65: 2 | AI65: 3 | AJ65: 2 | AK65: 2 | AL65: 2 | AM65: 2 | AN65: 2 | AO65: 2 | AP65: 2 | AQ65: 2 | AR65: 2 | AS65: 2 | AT65: -1 | AU65: 2 | AV65: -1 | AW65: -1 | AX65: -1 | AY65: -1 | AZ65: -1 | BA65: -1
A66: {=_xludf.XLOOKUP(S66,Master_Registrations!P:P,Master_Registrations!A:A,"")} -> #NAME? | B66: VED-03 | C66: 2026 | D66: BR | E66: 3 | F66: =CONCATENATE(B66,"-",C66,"-",D66,"-",E66) -> VED-03-2026-BR-3 | G66: Shiva Kumar Challa | H66: Aniruddha Pochimcherla | J66: Active | N66: R2 | O66: Punyamurtula | P66: Jay Shanmukha | Q66: =_xludf.TEXTJOIN(" ",TRUE,O66:P66) -> #NAME? | R66: +1 | S66: 6192046933 | T66: 4-USA MST/PST | U66: 2015 | V66: 2 | W66: 2 | X66: 2 | Y66: 2 | Z66: 2 | AA66: 2 | AB66: 2 | AC66: 2 | AD66: 2 | AE66: 2 | AF66: 2 | AG66: 2 | AH66: 2 | AI66: 4 | AJ66: 2 | AK66: 2 | AL66: 2 | AM66: 2 | AN66: 2 | AO66: 2 | AP66: 2 | AQ66: 2 | AR66: -1 | AS66: 2 | AT66: -1 | AU66: -1 | AV66: -1 | AW66: -1 | AX66: -1 | AY66: -1 | AZ66: -1 | BA66: -1
A67: {=_xludf.XLOOKUP(S67,Master_Registrations!P:P,Master_Registrations!A:A,"")} -> #NAME? | B67: VED-03 | C67: 2026 | D67: BR | E67: 3 | F67: =CONCATENATE(B67,"-",C67,"-",D67,"-",E67) -> VED-03-2026-BR-3 | G67: Shiva Kumar Challa | H67: Aniruddha Pochimcherla | J67: Active | N67: R3 | O67: Sistla | P67: Kaarthikeya | Q67: Sistla Kaarthikeya | R67: +1 | S67: 4702725998 | T67: 2-USA EST | U67: 2012 | V67: 2 | W67: 2 | X67: 2 | Y67: 2 | Z67: 2 | AA67: 2 | AB67: 2 | AC67: 2 | AD67: 2 | AE67: 2 | AF67: 2 | AG67: 2 | AH67: 2 | AI67: 4 | AJ67: 2 | AK67: 2 | AL67: 2 | AM67: 2 | AN67: 2 | AO67: 2 | AP67: 2 | AQ67: 2 | AR67: -1 | AS67: 2 | AT67: -1 | AU67: -1 | AV67: -1 | AW67: -1 | AX67: -1 | AY67: -1 | AZ67: -1 | BA67: -1
A68: {=_xludf.XLOOKUP(S68,Master_Registrations!P:P,Master_Registrations!A:A,"")} -> #NAME? | B68: VED-03 | C68: 2026 | D68: BR | E68: 3 | F68: =CONCATENATE(B68,"-",C68,"-",D68,"-",E68) -> VED-03-2026-BR-3 | G68: Shiva Kumar Challa | H68: Aniruddha Pochimcherla | J68: Active | N68: R4 | O68: Valiveti | P68: Akshath | Q68: Valiveti Akshath | R68: +1 | S68: 2409949102 | T68: 3-USA CST | U68: 2011 | V68: 2 | W68: 2 | X68: 2 | Y68: 2 | Z68: 2 | AA68: 2 | AB68: 2 | AC68: 2 | AD68: 2 | AE68: 2 | AF68: 2 | AG68: 2 | AH68: 2 | AI68: 3 | AJ68: 2 | AK68: 2 | AL68: 2 | AM68: 2 | AN68: 2 | AO68: 2 | AP68: -1 | AQ68: -1 | AR68: -1 | AS68: -1 | AT68: -1 | AU68: -1 | AV68: -1 | AW68: -1 | AX68: -1 | AY68: -1 | AZ68: -1 | BA68: -1
A69: {=_xludf.XLOOKUP(S69,Master_Registrations!P:P,Master_Registrations!A:A,"")} -> #NAME? | B69: VED-07 | C69: 2026 | D69: BR | E69: 1 | F69: =CONCATENATE(B69,"-",C69,"-",D69,"-",E69) -> VED-07-2026-BR-1 | G69: Chinna Guruvu Garu | H69: Chinna Guruvu Garu | J69: Active | N69: R1 | O69: Gorugantu | P69: Saaketh | Q69: Gorugantu Saaketh | R69: +1 | S69: 4083293168 | T69: 3-USA CST | U69: 2012 | V69: 2 | W69: 2 | X69: 2 | Y69: 2 | Z69: 2 | AA69: 2 | AB69: 2 | AC69: 2 | AD69: 2 | AE69: 2 | AF69: 2 | AG69: 2 | AH69: 2 | AI69: 4 | AJ69: 2 | AK69: 2 | AL69: 2 | AM69: 2 | AN69: 2 | AO69: 2 | AP69: 2 | AQ69: 2 | AR69: 2 | AS69: 2 | AT69: 2 | AU69: 2 | AV69: 4 | AW69: 2 | AX69: 2 | AY69: 2 | AZ69: 2 | BA69: 2 | BB69: 2 | BC69: 2 | BD69: 2 | BE69: 2 | BF69: 4 | BG69: 2 | BH69: 2 | BI69: 2 | BJ69: 2 | BK69: 2 | BL69: 2 | BM69: 4 | BN69: 2 | BO69: 2 | BP69: 2 | BQ69: 2 | BR69: 2 | BS69: 2 | BT69: 2 | BU69: 2 | BV69: 4 | BW69: 1 | BX69: 1 | BY69: -1 | BZ69: -1 | CA69: -1 | CB69: -1 | CC69: -1 | CD69: -1 | CE69: -1 | CF69: -1 | CG69: -1 | CH69: -1 | CI69: -1 | CJ69: -1 | CK69: -1 | CL69: -1 | CM69: -1 | CN69: -1 | CO69: -1 | CP69: -1 | CQ69: -1 | CR69: -1 | CS69: -1 | CT69: -1 | CU69: -1 | CV69: -1 | CW69: -1 | CX69: -1 | CY69: -1
A70: {=_xludf.XLOOKUP(S70,Master_Registrations!P:P,Master_Registrations!A:A,"")} -> #NAME? | B70: VED-07 | C70: 2026 | D70: BR | E70: 1 | F70: =CONCATENATE(B70,"-",C70,"-",D70,"-",E70) -> VED-07-2026-BR-1 | G70: Chinna Guruvu Garu | H70: Chinna Guruvu Garu | J70: Active | N70: R2 | O70: Nanduri | P70: Varun Aditya | Q70: Nanduri Varun Aditya | R70: +1 | S70: 5122001974 | T70: 3-USA CST | U70: 2009 | V70: 2 | W70: 2 | X70: 2 | Y70: 2 | Z70: 2 | AA70: 2 | AB70: 2 | AC70: 2 | AD70: 2 | AE70: 2 | AF70: 2 | AG70: 2 | AH70: 2 | AI70: 4 | AJ70: 2 | AK70: 2 | AL70: 2 | AM70: 2 | AN70: 2 | AO70: 2 | AP70: 2 | AQ70: 2 | AR70: 2 | AS70: 2 | AT70: 2 | AU70: 2 | AV70: 4 | AW70: 2 | AX70: 2 | AY70: 2 | AZ70: 2 | BA70: 2 | BB70: 2 | BC70: 2 | BD70: 2 | BE70: 2 | BF70: 4 | BG70: 2 | BH70: 2 | BI70: 2 | BJ70: 2 | BK70: 2 | BL70: 2 | BM70: 4 | BN70: 2 | BO70: 2 | BP70: 2 | BQ70: 2 | BR70: 2 | BS70: 2 | BT70: 2 | BU70: 2 | BV70: 4 | BW70: 1 | BX70: 1 | BY70: -1 | BZ70: -1 | CA70: -1 | CB70: -1 | CC70: -1 | CD70: -1 | CE70: -1 | CF70: -1 | CG70: -1 | CH70: -1 | CI70: -1 | CJ70: -1 | CK70: -1 | CL70: -1 | CM70: -1 | CN70: -1 | CO70: -1 | CP70: -1 | CQ70: -1 | CR70: -1 | CS70: -1 | CT70: -1 | CU70: -1 | CV70: -1 | CW70: -1 | CX70: -1 | CY70: -1
A71: {=_xludf.XLOOKUP(S71,Master_Registrations!P:P,Master_Registrations!A:A,"")} -> #NAME? | B71: VED-07 | C71: 2026 | D71: BR | E71: 1 | F71: =CONCATENATE(B71,"-",C71,"-",D71,"-",E71) -> VED-07-2026-BR-1 | G71: Chinna Guruvu Garu | H71: Chinna Guruvu Garu | J71: Active | N71: R3 | O71: Penumarthy | P71: Jaigeeshavya Vasishta | Q71: =_xludf.TEXTJOIN(" ",TRUE,O71:P71) -> #NAME? | R71: +91 | S71: 8767128990 | T71: 1-INDIA IST | U71: 2009 | V71: 2 | W71: 2 | X71: 2 | Y71: 2 | Z71: 2 | AA71: 2 | AB71: 2 | AC71: 2 | AD71: 2 | AE71: 2 | AF71: 2 | AG71: 2 | AH71: 2 | AI71: 4 | AJ71: 2 | AK71: 2 | AL71: 2 | AM71: 2 | AN71: 2 | AO71: 2 | AP71: 2 | AQ71: 2 | AR71: 2 | AS71: 2 | AT71: 2 | AU71: 2 | AV71: 4 | AW71: 2 | AX71: 2 | AY71: 2 | AZ71: 2 | BA71: 2 | BB71: 2 | BC71: 2 | BD71: 2 | BE71: 2 | BF71: 4 | BG71: 2 | BH71: 2 | BI71: 2 | BJ71: 2 | BK71: 2 | BL71: 2 | BM71: 4 | BN71: 2 | BO71: 2 | BP71: 2 | BQ71: 2 | BR71: 2 | BS71: 2 | BT71: 2 | BU71: 2 | BV71: 4 | BW71: 1 | BX71: 1 | BY71: -1 | BZ71: -1 | CA71: -1 | CB71: -1 | CC71: -1 | CD71: -1 | CE71: -1 | CF71: 2 | CG71: 2 | CH71: 2 | CI71: 2 | CJ71: 2 | CK71: 2 | CL71: 2 | CM71: 4 | CN71: -1 | CO71: -1 | CP71: -1 | CQ71: -1 | CR71: -1 | CS71: -1 | CT71: -1 | CU71: -1 | CV71: -1 | CW71: -1 | CX71: -1 | CY71: -1
A72: {=_xludf.XLOOKUP(S72,Master_Registrations!P:P,Master_Registrations!A:A,"")} -> #NAME? | B72: VED-07 | C72: 2026 | D72: BR | E72: 1 | F72: =CONCATENATE(B72,"-",C72,"-",D72,"-",E72) -> VED-07-2026-BR-1 | G72: Chinna Guruvu Garu | H72: Chinna Guruvu Garu | J72: Active | N72: R4 | O72: Prabhala | P72: Sai Vivek | Q72: =_xludf.TEXTJOIN(" ",TRUE,O72:P72) -> #NAME? | R72: +1 | S72: 5129065000 | T72: 2-USA EST | U72: 1997 | V72: 2 | W72: 2 | X72: 2 | Y72: 2 | Z72: 2 | AA72: 2 | AB72: 2 | AC72: 2 | AD72: 2 | AE72: 2 | AF72: 2 | AG72: 2 | AH72: 2 | AI72: 3 | AJ72: 2 | AK72: 2 | AL72: 2 | AM72: 2 | AN72: 2 | AO72: 2 | AP72: 2 | AQ72: 2 | AR72: 2 | AS72: 2 | AT72: 2 | AU72: 2 | AV72: 3 | AW72: 2 | AX72: 2 | AY72: 2 | AZ72: 2 | BA72: 2 | BB72: 2 | BC72: 2 | BD72: 2 | BE72: 2 | BF72: 4 | BG72: 2 | BH72: 2 | BI72: 2 | BJ72: 2 | BK72: 2 | BL72: 2 | BM72: 4 | BN72: 1 | BO72: -1 | BP72: -1 | BQ72: 0 | BR72: 0 | BS72: -1 | BT72: -1 | BU72: -1 | BV72: -1 | BW72: 1 | BX72: 1 | BY72: -1 | BZ72: -1 | CA72: -1 | CB72: -1 | CC72: -1 | CD72: -1 | CE72: -1 | CF72: 2 | CG72: 2 | CH72: 2 | CI72: 2 | CJ72: 2 | CK72: 2 | CL72: 2 | CM72: 3 | CN72: -1 | CO72: -1 | CP72: -1 | CQ72: -1 | CR72: -1 | CS72: -1 | CT72: -1 | CU72: -1 | CV72: -1 | CW72: -1 | CX72: -1 | CY72: -1
A73: {=_xludf.XLOOKUP(S73,Master_Registrations!P:P,Master_Registrations!A:A,"")} -> #NAME? | B73: VED-07 | C73: 2026 | D73: BR | E73: 1 | F73: =CONCATENATE(B73,"-",C73,"-",D73,"-",E73) -> VED-07-2026-BR-1 | G73: Chinna Guruvu Garu | H73: Chinna Guruvu Garu | J73: Active | N73: R5 | O73: Swayampakula | P73: Devachandra | Q73: =_xludf.TEXTJOIN(" ",TRUE,O73:P73) -> #NAME? | R73: +91 | S73: 9490175140 | T73: 1-INDIA IST | U73: 2011 | V73: 2 | W73: 2 | X73: 2 | Y73: 2 | Z73: 2 | AA73: 2 | AB73: 2 | AC73: 2 | AD73: 2 | AE73: 2 | AF73: 2 | AG73: 2 | AH73: 2 | AI73: 4 | AJ73: 2 | AK73: 2 | AL73: 2 | AM73: 2 | AN73: 2 | AO73: 2 | AP73: 2 | AQ73: 2 | AR73: 2 | AS73: 2 | AT73: 2 | AU73: 2 | AV73: 4 | AW73: 2 | AX73: 2 | AY73: 2 | AZ73: 2 | BA73: 2 | BB73: 2 | BC73: 2 | BD73: 2 | BE73: 2 | BF73: 4 | BG73: 2 | BH73: 2 | BI73: 2 | BJ73: 2 | BK73: 2 | BL73: 2 | BM73: 4 | BN73: 2 | BO73: 2 | BP73: 2 | BQ73: 2 | BR73: 2 | BS73: 2 | BT73: 2 | BU73: 2 | BV73: 4 | BW73: 1 | BX73: 1 | BY73: -1 | BZ73: -1 | CA73: -1 | CB73: -1 | CC73: -1 | CD73: -1 | CE73: -1 | CF73: 2 | CG73: 2 | CH73: 2 | CI73: 2 | CJ73: 2 | CK73: 2 | CL73: 2 | CM73: 4 | CN73: -1 | CO73: -1 | CP73: -1 | CQ73: -1 | CR73: -1 | CS73: -1 | CT73: -1 | CU73: -1 | CV73: -1 | CW73: -1 | CX73: -1 | CY73: -1
A74: {=_xludf.XLOOKUP(S74,Master_Registrations!P:P,Master_Registrations!A:A,"")} -> #NAME? | B74: VED-07 | C74: 2026 | D74: BR | E74: 1 | F74: =CONCATENATE(B74,"-",C74,"-",D74,"-",E74) -> VED-07-2026-BR-1 | G74: Chinna Guruvu Garu | H74: Chinna Guruvu Garu | J74: Active | N74: R6 | O74: Vamaraju | P74: Hariharanadhasai | Q74: =_xludf.TEXTJOIN(" ",TRUE,O74:P74) -> #NAME? | R74: +91 | S74: 9848344167 | T74: 1-INDIA IST | U74: 1998 | V74: 2 | W74: 2 | X74: 2 | Y74: 2 | Z74: 2 | AA74: 2 | AB74: 2 | AC74: 2 | AD74: 2 | AE74: 2 | AF74: 2 | AG74: 2 | AH74: 2 | AI74: 4 | AJ74: 2 | AK74: 2 | AL74: 2 | AM74: 2 | AN74: 2 | AO74: 2 | AP74: 2 | AQ74: 2 | AR74: 2 | AS74: 2 | AT74: 2 | AU74: 2 | AV74: 4 | AW74: 2 | AX74: 2 | AY74: 2 | AZ74: 2 | BA74: 2 | BB74: 2 | BC74: 2 | BD74: 2 | BE74: 2 | BF74: 4 | BG74: 2 | BH74: 2 | BI74: 2 | BJ74: 2 | BK74: 2 | BL74: 2 | BM74: 4 | BN74: 2 | BO74: 2 | BP74: 2 | BQ74: 2 | BR74: 2 | BS74: 2 | BT74: 2 | BU74: 2 | BV74: 4 | BW74: 1 | BX74: 1 | BY74: -1 | BZ74: -1 | CA74: -1 | CB74: -1 | CC74: -1 | CD74: -1 | CE74: -1 | CF74: 2 | CG74: 2 | CH74: 2 | CI74: 2 | CJ74: 2 | CK74: 2 | CL74: 2 | CM74: 4 | CN74: -1 | CO74: -1 | CP74: -1 | CQ74: -1 | CR74: -1 | CS74: -1 | CT74: -1 | CU74: -1 | CV74: -1 | CW74: -1 | CX74: -1 | CY74: -1
A75: {=_xludf.XLOOKUP(S75,Master_Registrations!P:P,Master_Registrations!A:A,"")} -> #NAME? | B75: VED-01 | C75: 2026 | D75: GR | E75: 1 | F75: =CONCATENATE(B75,"-",C75,"-",D75,"-",E75) -> VED-01-2026-GR-1 | G75: Siripurapu Srinivasa Rao | H75: Madduri Rajendra Prasad | J75: Active | N75: R1 | O75: Ambatipudi | P75: Nagendra Prasad | Q75: =_xludf.TEXTJOIN(" ",TRUE,O75:P75) -> #NAME? | R75: +91 | S75: 9701562945 | T75: 1-INDIA IST | U75: 1975 | V75: 1 | W75: -1 | X75: -1 | Y75: -1 | Z75: -1 | AA75: -1
A76: {=_xludf.XLOOKUP(S76,Master_Registrations!P:P,Master_Registrations!A:A,"")} -> #NAME? | B76: VED-01 | C76: 2026 | D76: GR | E76: 1 | F76: =CONCATENATE(B76,"-",C76,"-",D76,"-",E76) -> VED-01-2026-GR-1 | G76: Siripurapu Srinivasa Rao | H76: Madduri Rajendra Prasad | J76: Active | N76: R2 | O76: Annavajhala | P76: Radhakrishna | Q76: =_xludf.TEXTJOIN(" ",TRUE,O76:P76) -> #NAME? | R76: +91 | S76: 9490611088 | T76: 1-INDIA IST | U76: 1962 | V76: 1 | W76: -1 | X76: -1 | Y76: -1 | Z76: -1 | AA76: -1
A77: {=_xludf.XLOOKUP(S77,Master_Registrations!P:P,Master_Registrations!A:A,"")} -> #NAME? | B77: VED-01 | C77: 2026 | D77: GR | E77: 1 | F77: =CONCATENATE(B77,"-",C77,"-",D77,"-",E77) -> VED-01-2026-GR-1 | G77: Siripurapu Srinivasa Rao | H77: Madduri Rajendra Prasad | J77: Active | N77: R3 | O77: G | P77: Subramanyam | Q77: =_xludf.TEXTJOIN(" ",TRUE,O77:P77) -> #NAME? | R77: +91 | S77: 7708139933 | T77: 1-INDIA IST | U77: 1995 | V77: -1 | W77: -1 | X77: -1 | Y77: -1 | Z77: -1 | AA77: -1
A78: {=_xludf.XLOOKUP(S78,Master_Registrations!P:P,Master_Registrations!A:A,"")} -> #NAME? | B78: VED-01 | C78: 2026 | D78: GR | E78: 1 | F78: =CONCATENATE(B78,"-",C78,"-",D78,"-",E78) -> VED-01-2026-GR-1 | G78: Siripurapu Srinivasa Rao | H78: Madduri Rajendra Prasad | J78: Active | N78: R4 | O78: Ganti | P78: Srinivas | Q78: =_xludf.TEXTJOIN(" ",TRUE,O78:P78) -> #NAME? | R78: +91 | S78: 9490523130 | T78: 1-INDIA IST | U78: 1974 | V78: 1 | W78: -1 | X78: -1 | Y78: -1 | Z78: -1 | AA78: -1
A79: {=_xludf.XLOOKUP(S79,Master_Registrations!P:P,Master_Registrations!A:A,"")} -> #NAME? | B79: VED-01 | C79: 2026 | D79: GR | E79: 1 | F79: =CONCATENATE(B79,"-",C79,"-",D79,"-",E79) -> VED-01-2026-GR-1 | G79: Siripurapu Srinivasa Rao | H79: Madduri Rajendra Prasad | J79: Active | N79: R5 | O79: Karnam | P79: Krishna Rao | Q79: =_xludf.TEXTJOIN(" ",TRUE,O79:P79) -> #NAME? | R79: +91 | S79: 9030339587 | T79: 1-INDIA IST | U79: 1967 | V79: -1 | W79: -1 | X79: -1 | Y79: -1 | Z79: -1 | AA79: -1
A80: {=_xludf.XLOOKUP(S80,Master_Registrations!P:P,Master_Registrations!A:A,"")} -> #NAME? | B80: VED-01 | C80: 2026 | D80: GR | E80: 1 | F80: =CONCATENATE(B80,"-",C80,"-",D80,"-",E80) -> VED-01-2026-GR-1 | G80: Siripurapu Srinivasa Rao | H80: Madduri Rajendra Prasad | J80: Active | N80: R6 | O80: Kurma | P80: Vinod Kumar | Q80: =_xludf.TEXTJOIN(" ",TRUE,O80:P80) -> #NAME? | R80: +91 | S80: 9030925322 | T80: 1-INDIA IST | U80: 1972 | V80: -1 | W80: -1 | X80: -1 | Y80: -1 | Z80: -1 | AA80: -1
A81: {=_xludf.XLOOKUP(S81,Master_Registrations!P:P,Master_Registrations!A:A,"")} -> #NAME? | B81: VED-01 | C81: 2026 | D81: GR | E81: 1 | F81: =CONCATENATE(B81,"-",C81,"-",D81,"-",E81) -> VED-01-2026-GR-1 | G81: Siripurapu Srinivasa Rao | H81: Madduri Rajendra Prasad | J81: Active | N81: R7 | O81: Madugula | P81: Janakiram | Q81: =_xludf.TEXTJOIN(" ",TRUE,O81:P81) -> #NAME? | R81: +91 | S81: 9959992278 | T81: 1-INDIA IST | U81: 1987 | V81: 1 | W81: -1 | X81: -1 | Y81: -1 | Z81: -1 | AA81: -1
A82: {=_xludf.XLOOKUP(S82,Master_Registrations!P:P,Master_Registrations!A:A,"")} -> #NAME? | B82: VED-01 | C82: 2026 | D82: GR | E82: 1 | F82: =CONCATENATE(B82,"-",C82,"-",D82,"-",E82) -> VED-01-2026-GR-1 | G82: Siripurapu Srinivasa Rao | H82: Madduri Rajendra Prasad | J82: Active | N82: R8 | O82: Madupu | P82: Koushik | Q82: =_xludf.TEXTJOIN(" ",TRUE,O82:P82) -> #NAME? | R82: +91 | S82: 8019478323 | T82: 1-INDIA IST | U82: 2006 | V82: 1 | W82: -1 | X82: -1 | Y82: -1 | Z82: -1 | AA82: -1
A83: {=_xludf.XLOOKUP(S83,Master_Registrations!P:P,Master_Registrations!A:A,"")} -> #NAME? | B83: VED-01 | C83: 2026 | D83: GR | E83: 1 | F83: =CONCATENATE(B83,"-",C83,"-",D83,"-",E83) -> VED-01-2026-GR-1 | G83: Siripurapu Srinivasa Rao | H83: Madduri Rajendra Prasad | J83: Active | N83: R9 | O83: Mynampati | P83: Karthikeya | Q83: =_xludf.TEXTJOIN(" ",TRUE,O83:P83) -> #NAME? | R83: +91 | S83: 9133779696 | T83: 1-INDIA IST | U83: 2008 | V83: 1 | W83: -1 | X83: -1 | Y83: -1 | Z83: -1 | AA83: -1
A84: {=_xludf.XLOOKUP(S84,Master_Registrations!P:P,Master_Registrations!A:A,"")} -> #NAME? | B84: VED-01 | C84: 2026 | D84: GR | E84: 1 | F84: =CONCATENATE(B84,"-",C84,"-",D84,"-",E84) -> VED-01-2026-GR-1 | G84: Siripurapu Srinivasa Rao | H84: Madduri Rajendra Prasad | J84: Active | N84: R10 | O84: Mynampati | P84: Anish | Q84: =_xludf.TEXTJOIN(" ",TRUE,O84:P84) -> #NAME? | R84: +91 | S84: 9133779696 | T84: 1-INDIA IST | U84: 2012 | V84: 1 | W84: -1 | X84: -1 | Y84: -1 | Z84: -1 | AA84: -1
A85: {=_xludf.XLOOKUP(S85,Master_Registrations!P:P,Master_Registrations!A:A,"")} -> #NAME? | B85: VED-01 | C85: 2026 | D85: GR | E85: 1 | F85: =CONCATENATE(B85,"-",C85,"-",D85,"-",E85) -> VED-01-2026-GR-1 | G85: Siripurapu Srinivasa Rao | H85: Madduri Rajendra Prasad | J85: Active | N85: R11 | O85: Nemani | P85: Srinivasa Rao | Q85: =_xludf.TEXTJOIN(" ",TRUE,O85:P85) -> #NAME? | R85: +91 | S85: 9290069069 | T85: 1-INDIA IST | U85: 1965 | V85: 1 | W85: -1 | X85: -1 | Y85: -1 | Z85: -1 | AA85: -1
A86: {=_xludf.XLOOKUP(S86,Master_Registrations!P:P,Master_Registrations!A:A,"")} -> #NAME? | B86: VED-01 | C86: 2026 | D86: GR | E86: 1 | F86: =CONCATENATE(B86,"-",C86,"-",D86,"-",E86) -> VED-01-2026-GR-1 | G86: Siripurapu Srinivasa Rao | H86: Madduri Rajendra Prasad | J86: Active | N86: R12 | O86: Pathibandla | P86: Raghava Sai | Q86: =_xludf.TEXTJOIN(" ",TRUE,O86:P86) -> #NAME? | R86: +91 | S86: 8317601392 | T86: 1-INDIA IST | U86: 1991 | V86: -1 | W86: -1 | X86: -1 | Y86: -1 | Z86: -1 | AA86: -1
... A116: {=_xludf.XLOOKUP(S116,Master_Registrations!P:P,Master_Registrations!A:A,"")} -> #NAME? | B116: VED-01 | C116: 2026 | D116: GR | E116: 3 | F116: =CONCATENATE(B116,"-",C116,"-",D116,"-",E116) -> VED-01-2026-GR-3 | G116: Chakravarthy Panchagnula | H116: Srikant Mellacheruvu | J116: Active | N116: R12 | O116: Sarvepalli | P116: Vasista Phani | Q116: =_xludf.TEXTJOIN(" ",TRUE,O116:P116) -> #NAME? | R116: +61 | S116: 428345193 | T116: 5-OTHER | U116: 1979 | V116: -1 | W116: -1 | X116: -1 | Y116: -1 | Z116: -1 | AA116: -1
A117: {=_xludf.XLOOKUP(S117,Master_Registrations!P:P,Master_Registrations!A:A,"")} -> #NAME? | B117: VED-01 | C117: 2026 | D117: GR | E117: 3 | F117: =CONCATENATE(B117,"-",C117,"-",D117,"-",E117) -> VED-01-2026-GR-3 | G117: Chakravarthy Panchagnula | H117: Srikant Mellacheruvu | J117: Active | L117: -1 | N117: R13 | O117: Vemuri | P117: Shravan Kumar | Q117: =_xludf.TEXTJOIN(" ",TRUE,O117:P117) -> #NAME? | R117: +91 | S117: 9177393167 | T117: 1-INDIA IST | U117: 1987 | V117: 1 | W117: 1 | X117: 1 | Y117: -1 | Z117: 1 | AA117: -1
A118: {=_xludf.XLOOKUP(S118,Master_Registrations!P:P,Master_Registrations!A:A,"")} -> #NAME? | B118: VED-01 | C118: 2026 | D118: GR | E118: 3 | F118: =CONCATENATE(B118,"-",C118,"-",D118,"-",E118) -> VED-01-2026-GR-3 | G118: Chakravarthy Panchagnula | H118: Srikant Mellacheruvu | J118: Active | N118: R14 | O118: Yeleswarapu | P118: Sankar Prasad | Q118: =_xludf.TEXTJOIN(" ",TRUE,O118:P118) -> #NAME? | R118: +91 | S118: 9866020600 | T118: 1-INDIA IST | U118: 1972 | V118: -1 | W118: -1 | X118: -1 | Y118: -1 | Z118: -1 | AA118: -1
A119: {=_xludf.XLOOKUP(S119,Master_Registrations!P:P,Master_Registrations!A:A,"")} -> #NAME? | B119: VED-01 | C119: 2026 | D119: GR | E119: 3 | F119: =CONCATENATE(B119,"-",C119,"-",D119,"-",E119) -> VED-01-2026-GR-3 | G119: Chakravarthy Panchagnula | H119: Srikant Mellacheruvu | J119: Active | N119: R15 | O119: Yellajosyula | P119: Sridhar | Q119: =_xludf.TEXTJOIN(" ",TRUE,O119:P119) -> #NAME? | R119: +1 | S119: 6026533166 | T119: 4-USA MST/PST | U119: 1978 | V119: -1 | W119: -1 | X119: 1 | Y119: -1 | Z119: 1 | AA119: -1
A120: {=_xludf.XLOOKUP(S120,Master_Registrations!P:P,Master_Registrations!A:A,"")} -> #NAME? | B120: VED-01 | C120: 2026 | D120: GR | E120: 4 | F120: =CONCATENATE(B120,"-",C120,"-",D120,"-",E120) -> VED-01-2026-GR-4 | G120: Chinna Guruvu Garu | H120: Vinjamoori Satyanarayana | J120: Active | N120: R1 | O120: Aka | P120: Venkata Pavan Kumar | Q120: =_xludf.TEXTJOIN(" ",TRUE,O120:P120) -> #NAME? | R120: +1 | S120: 2165079464 | T120: 3-USA CST | U120: 1991 | V120: -1 | W120: -1 | X120: -1 | Y120: -1 | Z120: -1 | AA120: -1
A121: {=_xludf.XLOOKUP(S121,Master_Registrations!P:P,Master_Registrations!A:A,"")} -> #NAME? | B121: VED-01 | C121: 2026 | D121: GR | E121: 4 | F121: =CONCATENATE(B121,"-",C121,"-",D121,"-",E121) -> VED-01-2026-GR-4 | G121: Chinna Guruvu Garu | H121: Vinjamoori Satyanarayana | J121: Active | N121: R2 | O121: Ambatipudi | P121: Sridhar | Q121: =_xludf.TEXTJOIN(" ",TRUE,O121:P121) -> #NAME? | R121: +1 | S121: 8328079584 | T121: 3-USA CST | U121: 1973 | V121: -1 | W121: -1 | X121: -1 | Y121: -1 | Z121: -1 | AA121: -1
A122: {=_xludf.XLOOKUP(S122,Master_Registrations!P:P,Master_Registrations!A:A,"")} -> #NAME? | B122: VED-01 | C122: 2026 | D122: GR | E122: 4 | F122: =CONCATENATE(B122,"-",C122,"-",D122,"-",E122) -> VED-01-2026-GR-4 | G122: Chinna Guruvu Garu | H122: Vinjamoori Satyanarayana | J122: Active | N122: R3 | O122: Ayithi | P122: Kowndinya | Q122: =_xludf.TEXTJOIN(" ",TRUE,O122:P122) -> #NAME? | R122: 91 | S122: 7901273185 | T122: 3-USA CST | U122: 2001 | V122: -1 | W122: -1 | X122: -1 | Y122: -1 | Z122: -1 | AA122: -1
A123: {=_xludf.XLOOKUP(S123,Master_Registrations!P:P,Master_Registrations!A:A,"")} -> #NAME? | B123: VED-01 | C123: 2026 | D123: GR | E123: 4 | F123: =CONCATENATE(B123,"-",C123,"-",D123,"-",E123) -> VED-01-2026-GR-4 | G123: Chinna Guruvu Garu | H123: Vinjamoori Satyanarayana | J123: Active | N123: R4 | O123: Chaganty | P123: Brahmar | Q123: =_xludf.TEXTJOIN(" ",TRUE,O123:P123) -> #NAME? | R123: +1 | S123: 9592057245 | T123: 2-USA EST | U123: 1973 | V123: -1 | W123: -1 | X123: -1 | Y123: -1 | Z123: -1 | AA123: -1
A124: {=_xludf.XLOOKUP(S124,Master_Registrations!P:P,Master_Registrations!A:A,"")} -> #NAME? | B124: VED-01 | C124: 2026 | D124: GR | E124: 4 | F124: =CONCATENATE(B124,"-",C124,"-",D124,"-",E124) -> VED-01-2026-GR-4 | G124: Chinna Guruvu Garu | H124: Vinjamoori Satyanarayana | J124: Active | N124: R5 | O124: Chandavarapu | P124: Ramana | Q124: =_xludf.TEXTJOIN(" ",TRUE,O124:P124) -> #NAME? | R124: +91 | S124: 9989688654 | T124: 1-INDIA IST | U124: 1971 | V124: -1 | W124: -1 | X124: -1 | Y124: -1 | Z124: -1 | AA124: -1
A125: {=_xludf.XLOOKUP(S125,Master_Registrations!P:P,Master_Registrations!A:A,"")} -> #NAME? | B125: VED-01 | C125: 2026 | D125: GR | E125: 4 | F125: =CONCATENATE(B125,"-",C125,"-",D125,"-",E125) -> VED-01-2026-GR-4 | G125: Chinna Guruvu Garu | H125: Vinjamoori Satyanarayana | J125: Active | N125: R6 | O125: Chintalapati | P125: Kalyan Chandra | Q125: =_xludf.TEXTJOIN(" ",TRUE,O125:P125) -> #NAME? | R125: +1 | S125: 6315121073 | T125: 2-USA EST | U125: 1990 | V125: -1 | W125: -1 | X125: -1 | Y125: -1 | Z125: -1 | AA125: -1
A126: {=_xludf.XLOOKUP(S126,Master_Registrations!P:P,Master_Registrations!A:A,"")} -> #NAME? | B126: VED-01 | C126: 2026 | D126: GR | E126: 4 | F126: =CONCATENATE(B126,"-",C126,"-",D126,"-",E126) -> VED-01-2026-GR-4 | G126: Chinna Guruvu Garu | H126: Vinjamoori Satyanarayana | J126: Active | N126: R7 | O126: Dasika | P126: Srinivasa Pavan | Q126: =_xludf.TEXTJOIN(" ",TRUE,O126:P126) -> #NAME? | R126: +1 | S126: 7047437476 | T126: 2-USA EST | U126: 1979 | V126: -1 | W126: -1 | X126: -1 | Y126: -1 | Z126: -1 | AA126: -1
A127: {=_xludf.XLOOKUP(S127,Master_Registrations!P:P,Master_Registrations!A:A,"")} -> #NAME? | B127: VED-01 | C127: 2026 | D127: GR | E127: 4 | F127: =CONCATENATE(B127,"-",C127,"-",D127,"-",E127) -> VED-01-2026-GR-4 | G127: Chinna Guruvu Garu | H127: Vinjamoori Satyanarayana | J127: Active | N127: R8 | O127: Duvvuri | P127: Kalyan | Q127: =_xludf.TEXTJOIN(" ",TRUE,O127:P127) -> #NAME? | R127: +1 | S127: 8582310914 | T127: 3-USA CST | U127: 1979 | V127: -1 | W127: -1 | X127: -1 | Y127: -1 | Z127: -1 | AA127: -1
A128: {=_xludf.XLOOKUP(S128,Master_Registrations!P:P,Master_Registrations!A:A,"")} -> #NAME? | B128: VED-01 | C128: 2026 | D128: GR | E128: 4 | F128: =CONCATENATE(B128,"-",C128,"-",D128,"-",E128) -> VED-01-2026-GR-4 | G128: Chinna Guruvu Garu | H128: Vinjamoori Satyanarayana | J128: Active | N128: R9 | O128: Duvvuri | P128: Venkata | Q128: =_xludf.TEXTJOIN(" ",TRUE,O128:P128) -> #NAME? | R128: +91 | S128: 8095210222 | T128: 1-INDIA IST | U128: 1981 | V128: -1 | W128: -1 | X128: -1 | Y128: -1 | Z128: -1 | AA128: -1
A129: {=_xludf.XLOOKUP(S129,Master_Registrations!P:P,Master_Registrations!A:A,"")} -> #NAME? | B129: VED-01 | C129: 2026 | D129: GR | E129: 4 | F129: =CONCATENATE(B129,"-",C129,"-",D129,"-",E129) -> VED-01-2026-GR-4 | G129: Chinna Guruvu Garu | H129: Vinjamoori Satyanarayana | J129: Active | N129: R10 | O129: Machiraju | P129: Venkata Raghunath | Q129: =_xludf.TEXTJOIN(" ",TRUE,O129:P129) -> #NAME? | R129: +1 | S129: 2165542584 | T129: 2-USA EST | U129: 1986 | V129: -1 | W129: -1 | X129: -1 | Y129: -1 | Z129: -1 | AA129: -1
A130: {=_xludf.XLOOKUP(S130,Master_Registrations!P:P,Master_Registrations!A:A,"")} -> #NAME? | B130: VED-01 | C130: 2026 | D130: GR | E130: 4 | F130: =CONCATENATE(B130,"-",C130,"-",D130,"-",E130) -> VED-01-2026-GR-4 | G130: Chinna Guruvu Garu | H130: Vinjamoori Satyanarayana | J130: Active | N130: R11 | O130: Namuduri | P130: Venkata Raghunath | Q130: =_xludf.TEXTJOIN(" ",TRUE,O130:P130) -> #NAME? | R130: +1 | S130: 8607103481 | T130: 2-USA EST | U130: 1972 | V130: 1 | W130: 1 | X130: 1 | Y130: 1 | Z130: 1 | AA130: 1 | AB130: 1
...

Sheet Master_Registrations
A1: REGISTERED | B1: Timestamp | C1: QUALIFIED? | D1: EMAIL SENT? | E1: WHATSAPP SENT? | F1: JOINED COMM GROUP? | G1: CATEGORY | H1: EMAIL ADDRESS | I1: LAST NAME | J1: FIRST NAME | K1: FULL NAME | L1: YEAR OF BIRTH | M1: UPANAYANAM | N1: COUNTRY TIME ZONE | O1: COUNTRY CODE | P1: WHATSAPP | Q1: PRIMARY KEY | R1: CITY | S1: REFERENCE NAME | T1: REFERENCE PHONE | U1: GRUHASTA | V1: BRAHMACHARI | W1: VEDA SHAKA | X1: SPOKEN | Y1: READ | Z1: PARENT NAMES | AA1: JOB | AB1: PARENT STUDYING | AC1: GOAL | AD1: PROFICIENCY | AE1: PRIORITY | AF1: DRESS CODE | AG1: NO MEAT | AH1: NO ALCHOHOL | AI1: NO SMOKING | AJ1: COMMENTS
A2: 2024 | B2: 45372.928 | C2: 3-ARCHAKA? | D2: NO | E2: NO | F2: NO | G2: 1-ADULT OVER 16 YRS | H2: harish19wipro@gmail.com | I2: Cherukuru | J2: Harish Kumar | K2: =_xludf.TEXTJOIN(" ",TRUE,I2:J2) -> #NAME? | L2: 1985 | N2: 1-INDIA IST | O2: +91 | P2: 6303372946 | Q2: =P2&"/"&L2 -> 6303372946/1985 | R2: Hyderabad | S2: Muralidhar | T2: Muralidhar | U2: Kashyapasa, Vishwamitra, N/A | V2: Kashyapasa, Vishwamitra, N/A | W2: Rig Veda | X2: English, Telugu and Kannada | Y2: English, Telugu, Kannada and Hindi | Z2: N/A | AA2: 3-ARCHAKA? | AB2: Not Applicable (Not Registering a Child under 13) | AC2: Archakathvam and have to learn perfectly | AD2: Low - Did not learn from Traditional Guru, but learnt from books/audio and perform daily Sandhya Vandanam and other poojas through books | AE2: Yes, This is High Priority for me | AF2: Yes | AG2: Yes | AH2: Yes | AI2: Yes | AJ2: I would like to learn all sukthas, rudram etc perfectly
A3: 2024 | B3: 45384.322 | C3: 3-ARCHAKA? | D3: NO | E3: NO | F3: NO | G3: 1-ADULT OVER 16 YRS | H3: mphanishwaraprasad@gmail.com | I3: Maddhali | J3: Phanishwara Prasad | K3: =_xludf.TEXTJOIN(" ",TRUE,I3:J3) -> #NAME? | L3: 1988 | N3: 1-INDIA IST | O3: +91 | P3: 9963023525 | Q3: =P3&"/"&L3&"/"&K3 -> #NAME? | R3: WARANGAL | S3: M PHANISHWAR PRASAD | T3: M PHANISHWAR PRASAD | U3: KOUNDINYASA, BHARADWAJASA, N/A | V3: KOUNDINYASA, BHARADWAJASA, N/A | W3: YAJUR VEDA | X3: TELUGU | Y3: TELUGU | Z3: N/A | AA3: 3-ARCHAKA? | AB3: Not Applicable (Not Registering a Child under 13) | AC3: SMATHA | AD3: High - Learnt from Traditional Guru in perfect swaram/uccharana - perform nithya Sandhya Vandanam and can recite few Suktams in su-swaram | AE3: Yes, This is High Priority for me | AF3: Yes | AG3: Yes | AH3: Yes | AI3: Yes
A4: 2025 | B4: 45711.181 | C4: 3-ARCHAKA? | D4: NO | E4: NO | F4: NO | G4: 1-ADULT OVER 16 YRS | H4: vishu.9194@gmail.com | I4: Bethanabatla | J4: Kasi Vishwanath | K4: =_xludf.TEXTJOIN(" ",TRUE,I4:J4) -> #NAME? | L4: 1981 | N4: 1-INDIA IST | O4: +91 | P4: 9182062337 | Q4: =P4&"/"&L4&"/"&K4 -> #NAME? | R4: Hyderabad ,Telangana, India | S4: Gudipati pavan kumar | T4: Gudipati pavan kumar | U4: Bhardwaj, Kaasyapasa, Kaasyapasa | V4: Bhardwaj, Kaasyapasa, Kaasyapasa | W4: Yajur vedam | X4: Telugu | Y4: Telugu | Z4: No | AA4: 3-ARCHAKA? | AB4: Not Applicable (Not Registering a Child under 13) | AC4: I am in purohitam | AD4: High - Learnt from Traditional Guru in perfect swaram/uccharana - perform nithya Sandhya Vandanam and can recite few Suktams in su-swaram | AE4: Yes, This is High Priority for me | AF4: Yes | AG4: Yes | AH4: Yes | AI4: Yes
A5: 2025 | B5: 45856.15 | C5: 3-ARCHAKA? | D5: YES | E5: YES | F5: NO | G5: 1-ADULT OVER 16 YRS | H5: praneeth5599@gmail.com | I5: Vanamali | J5: Praneeth | K5: =_xludf.TEXTJOIN(" ",TRUE,I5:J5) -> #NAME? | L5: 1993 | M5: 2016 | N5: 1-INDIA IST | O5: +91 | P5: 9515248299 | Q5: =P5&"/"&L5&"/"&K5 -> #NAME? | R5: Hyderabad | S5: Mavuduru Umamaheswara rao berhampur | T5: Mavuduru Umamaheswara rao berhampur | U5: Bharadwajasa, Kasyapasa, Kasyapasa | V5: Bharadwajasa, Kasyapasa, Kasyapasa | W5: Rig veda | X5: Telugu english | Y5: Telugu english hindi | Z5: N/A | AA5: Tax Practitioner / Archaka Background | AB5: Not Applicable (Not Registering a Child under 13) | AC5: We have pourohithyam at my village. My dad is a purohith and Srividhya Poorna Dheeksha Parulu | AD5: High - Learnt from Traditional Guru in perfect swaram/uccharana - perform nithya Sandhya Vandanam and can recite few Suktams in su-swaram | AE5: Yes, This is High Priority for me | AF5: Yes | AG5: Yes | AH5: Yes | AI5: Yes | AJ5: I m glad if I able to learn from you.
A6: 2025 | B6: 45869.967 | C6: 3-ARCHAKA? | D6: NO | E6: NO | F6: NO | G6: 1-ADULT OVER 16 YRS | H6: vennampallysharma@gmail.com | I6: Vennampally | J6: Prashanth Sharma | K6: =_xludf.TEXTJOIN(" ",TRUE,I6:J6) -> #NAME? | L6: 1992 | M6: 2005 | N6: 1-INDIA IST | O6: +91 | P6: 8522870346 | Q6: =P6&"/"&L6&"/"&K6 -> #NAME? | R6: Narsampet | S6: B Chandresekar 9849639880 | T6: B Chandresekar 9849639881 | U6: Koundinyasa, Sri vatsasa, N/A | V6: Koundinyasa, Sri vatsasa, N/A | W6: Yajur Veda | X6: Telugu, Hindi, English | Y6: Telugu, Hindi, English | Z6: N/A | AA6: 3-ARCHAKA? | AB6: Not Applicable (Not Registering a Child under 13) | AC6: To upgrade my skills | AD6: Low - Did not learn from Traditional Guru, but learnt from books/audio and perform daily Sandhya Vandanam and other poojas through books | AE6: Yes, This is High Priority for me | AF6: Yes | AG6: Yes | AH6: Yes | AI6: Yes | AJ6: N/A
A7: 2025 | B7: 45912.193 | C7: 3-ARCHAKA? | D7: YES | E7: YES | F7: YES | G7: 1-ADULT OVER 16 YRS | H7: prathaparudrudu181@gmail.com | I7: Marripati | J7: Prathapa Rudrudu | K7: =_xludf.TEXTJOIN(" ",TRUE,I7:J7) -> #NAME? | L7: 1983 | M7: 1999 | N7: 1-INDIA IST | O7: +91 | P7: 9492961359 | Q7: =P7&"/"&L7&"/"&K7 -> #NAME? | R7: Tenali | S7: Ch Ramakrishna garu | T7: 8978416077 | U7: Koundinyasa, Sri vatsasa, Bharadwajasa | V7: N/A | W7: Yajur veda | X7: Telugu, Hindi, English | Y7: Telugu Hindi English | Z7: N/A | AA7: 3-ARCHAKA? | AB7: Not Applicable (Not Registering a Child under 13) | AC7: To improve swaram and sukthas | AD7: Low - Did not learn from Traditional Guru, but learnt from books/audio and perform daily Sandhya Vandanam and other poojas through books | AE7: Yes, This is High Priority for me | AF7: Yes | AG7: Yes | AH7: Yes | AI7: Yes
A8: 2025 | B8: 45913.378 | C8: 3-ARCHAKA? | D8: YES | E8: YES | F8: YES | G8: 1-ADULT OVER 16 YRS | H8: bkalyankumarhyd@gmail.com | I8: Kumar | J8: Kalyan | K8: =_xludf.TEXTJOIN(" ",TRUE,I8:J8) -> #NAME? | L8: 1994 | M8: 2012 | N8: 1-INDIA IST | O8: +91 | P8: 7386749513 | Q8: =P8&"/"&L8&"/"&K8 -> #NAME? | R8: Hyderabad | S8: Rama krishna rtd railway | T8: 98662 09719 | U8: N/A | V8: Kashyapasa, Srivatsasa | W8: Krishna Yajur | X8: Telugu, Hindhi, English | Y8: Telugu, Hindhi, English | Z8: N/A | AA8: 3-ARCHAKA? | AB8: Not Applicable (Not Registering a Child under 13) | AC8: To upgrade myself in Brahmanatva | AD8: Low - Did not learn from Traditional Guru, but learnt from books/audio and perform daily Sandhya Vandanam and other poojas through books | AE8: Yes, This is High Priority for me | AF8: Yes | AG8: Yes | AH8: Yes | AI8: Yes | AJ8: A high need for me to survive too
A9: 2025 | B9: 45913.995 | C9: 3-ARCHAKA? | D9: NO | E9: NO | F9: NO | G9: 1-ADULT OVER 16 YRS | H9: paturi.venkatanagasrinivas@gmail.com | I9: Paturi | J9: Srinivas Venkata Naga | K9: =_xludf.TEXTJOIN(" ",TRUE,I9:J9) -> #NAME? | L9: 1969 | M9: 1991 | N9: 1-INDIA IST | O9: +91 | P9: 9000577424 | Q9: =P9&"/"&L9&"/"&K9 -> #NAME? | R9: HYDERABAD | S9: KALPANA MANGALAMPALLI | T9: 8332914596 | U9: AYHREYASA, HARIDASA, KASYAPASA | V9: N/A | W9: Sukla Yajurveda | X9: Telugu | Y9: Telugu, English n Hindi | Z9: N/A | AA9: Private Emoloyee/Archaka | AB9: Not Applicable (Not Registering a Child under 13) | AC9: Due to financial burden. | AD9: High - Learnt from Traditional Guru in perfect swaram/uccharana - perform nithya Sandhya Vandanam and can recite few Suktams in su-swaram | AE9: Yes, This is High Priority for me | AF9: Yes | AG9: Yes | AH9: Yes | AI9: Yes | AJ9: NO ALTERNATE FOR ME TO LEAD FAMILY... DAUGHTER'S MARRIAGE n Son's higher education. My job is in dilemma as per management decision.
A10: 2025 | B10: 45943.424 | C10: 3-ARCHAKA? | D10: NO | E10: NO | F10: NO | G10: 1-ADULT OVER 16 YRS | H10: arkesharchakam2@gmail.com | I10: Archakam | J10: Arkeshwara Gurukkal | K10: =_xludf.TEXTJOIN(" ",TRUE,I10:J10) -> #NAME? | L10: 1981 | M10: 1997 | N10: 1-INDIA IST | O10: +91 | P10: 6281845580 | Q10: =P10&"/"&L10&"/"&K10 -> #NAME? | R10: Palamaner | S10: Aravinda Sai Kondamari | T10: +14806124302 | U10: Vasistasa, Bhargava, Kasyapasa | V10: N/A | W10: Yajur veda | X10: Telugu, Tamil, Kannada | Y10: Telugu, Kannada | Z10: N/A | AA10: 3-ARCHAKA? | AB10: Not Applicable (Not Registering a Child under 13) | AC10: Homam prakriya | AD10: High - Learnt from Traditional Guru in perfect swaram/uccharana - perform nithya Sandhya Vandanam and can recite few Suktams in su-swaram | AE10: Yes, This is High Priority for me | AF10: Yes | AG10: Yes | AH10: Yes | AI10: Yes | AJ10: I am working as an archaka at Temple. I can recite several suktas, but want to learn higher ceremonies like homam and yagnam.
A11: 2025 | B11: 45972.818 | C11: 3-ARCHAKA? | D11: NO | E11: NO | F11: NO | G11: 2-CHILD UNDER 16 YRS | H11: praveenbonala@gmail.com | I11: Bonala | J11: Arshith Sharma | K11: =_xludf.TEXTJOIN(" ",TRUE,I11:J11) -> #NAME? | L11: 2013 | M11: 2025 | N11: 5-OTHER | O11: +61 | P11: 434852893 | Q11: =P11&"/"&L11&"/"&K11 -> #NAME? | R11: Melbourne Australia | S11: Praveen Kumar Sharma bonala | T11: +61434852893 | U11: N/A | V11: Koundinyasa, Bharadwajasa | W11: Krishna Yajurveda | X11: English, Telugu | Y11: English, Telugu | Z11: Praveen Kumar Sharma Bonala, Gauthami Rajuri | AA11: 3-ARCHAKA? | AB11: Yes. Will Learn 1st Semester Syllabus along with Child | AC11: Praveen Kumar Sharma writing this comment- I feel truly blessed by the grace of God to have taken birth as Brahmin. During my childhood, I didnt get opportunity to learn ouir sacred tradition. My brother learnt something from Shringeri Shankar Matt- Warangal during college days. But I didnt get chance to learn from my brother due to my nature of study and job. Currently I am in Australia and have enough time for work life balance. I wanted to teach my kid about our country and our tradition. Currently he is learning from Youtube videos and books. I wanted him to learn swarayukta and from Guru upadesham. So he will continue our tradition and parampara and wont attract to other wester culture things. | AD11: Low - Did not learn from Traditional Guru, but learnt from books/audio and perform daily Sandhya Vandanam and other poojas through books | AE11: Yes, This is High Priority for me | AF11: Yes | AG11: Yes | AH11: Yes | AI11: Yes
A12: 2025 | B12: 45888.902 | C12: 4-REFERENCE? | D12: NO | E12: NO | F12: NO | G12: 1-ADULT OVER 16 YRS | H12: rudraramaj@gmail.com | I12: Rudra | J12: Rama | K12: =_xludf.TEXTJOIN(" ",TRUE,I12:J12) -> #NAME? | L12: 1987 | M12: 1996 | N12: 1-INDIA IST | O12: +91 | P12: 9392912521 | Q12: =P12&"/"&L12&"/"&K12 -> #NAME? | R12: Hyderabad | S12: Jana rudra Rama lingeswar sharma | T12: 9392912521 | U12: Bharadwajasa | V12: N/A | W12: Yajur veda | X12: Telugu | Y12: Telugu | Z12: N/A | AA12: Self employed | AB12: Not Applicable (Not Registering a Child under 13) | AC12: Intrested and important | AD12: High - Learnt from Traditional Guru in perfect swaram/uccharana - perform nithya Sandhya Vandanam and can recite few Suktams in su-swaram | AE12: Yes, This is High Priority for me | AF12: Yes | AG12: Yes | AH12: Yes | AI12: Yes
A13: 2025 | B13: 45915.457 | C13: 4-REFERENCE? | D13: NO | E13: NO | F13: NO | G13: 1-ADULT OVER 16 YRS | H13: kavi999@gmail.com | I13: Kavikondala | J13: Srinivas | K13: =_xludf.TEXTJOIN(" ",TRUE,I13:J13) -> #NAME? | L13: 1977 | M13: 1993 | N13: 1-INDIA IST | O13: +91 | P13: 9121200454 | Q13: =P13&"/"&L13&"/"&K13 -> #NAME? | R13: Hyderabad | S13: Diwakar | T13: +91 90000 19664 | U13: Bharadwajasa | V13: NA | W13: NA | X13: Telugu, Hindi, English | Y13: Telugu, Hindi, English | Z13: NA | AA13: Software engineer | AB13: Not Applicable (Not Registering a Child under 13) | AC13: Sandhya vandanam | AD13: None - Do not know much about this subject, but committed to learn | AE13: Yes, This is High Priority for me | AF13: Yes | AG13: Yes | AH13: Yes | AI13: Yes
A14: 2025 | B14: 45972.205 | C14: 4-REFERENCE? | D14: NO | E14: NO | F14: NO | G14: 1-ADULT OVER 16 YRS | H14: praffulshakhai@gmail.com | I14: Shakhai | J14: Prafful Sharma | K14: =_xludf.TEXTJOIN(" ",TRUE,I14:J14) -> #NAME? | L14: 1994 | M14: 2005 | N14: 1-INDIA IST | O14: +91 | P14: 7075211712 | Q14: =P14&"/"&L14&"/"&K14 -> #NAME? | R14: Hyderabad | S14: Online sent email | T14: Online | U14: NA | V14: Goutamasa,kashyapasa | W14: Yajur veda | X14: Telugu English hindi marati | Y14: Telugu English hindi | Z14: Na | AA14: Software engineer | AB14: Not Applicable (Not Registering a Child under 13) | AC14: Wanted to learn , follow and implement Veda dharma in daily life for better living | AD14: Low - Did not learn from Traditional Guru, but learnt from books/audio and perform daily Sandhya Vandanam and other poojas through books | AE14: Yes, This is High Priority for me | AF14: Yes | AG14: Yes | AH14: Yes | AI14: Yes
A15: 2025 | B15: 46001.895 | C15: 4-REFERENCE? | D15: NO | E15: NO | F15: NO | G15: 1-ADULT OVER 16 YRS | H15: veda729@gmail.com | I15: Simgavarjula | J15: Vedavyas | K15: =_xludf.TEXTJOIN(" ",TRUE,I15:J15) -> #NAME? | L15: 1996 | M15: 2025 | N15: 1-INDIA IST | O15: +91 | P15: 7893301281 | Q15: =P15&"/"&L15&"/"&K15 -> #NAME? | R15: Khammam | S15: Vedantam Rama Krishna Prasad | T15: 9441087938 | U15: N/A | V15: Srivatsasa, Vardeswasa | W15: Yajur Veda | X15: Telugu, English | Y15: Telugu, Hindi, English | Z15: N/A | AA15: Job Searching | AB15: Not Applicable (Not Registering a Child under 13) | AC15: Interested to learn and to be able to perform when required at home. | AD15: None - Do not know much about this subject, but committed to learn | AE15: Yes, This is High Priority for me | AF15: Yes | AG15: Yes | AH15: Yes | AI15: Yes | AJ15: I am excited to join and learn. Thank you for giving this opportunity of sharing my details with you.
A16: 2025 | B16: 46013.485 | C16: 4-REFERENCE? | D16: NO | E16: NO | F16: NO | G16: 1-ADULT OVER 16 YRS | H16: durgaprasadvaranasi08@gmail.com | I16: Varanasi | J16: Durgaprasad | K16: =_xludf.TEXTJOIN(" ",TRUE,I16:J16) -> #NAME? | L16: 1982 | M16: 2010 | N16: 3-USA CST | O16: +1 | P16: 2039092885 | Q16: =P16&"/"&L16&"/"&K16 -> #NAME? | R16: Aubrey | S16: NA | T16: NA | U16: Koundinyasa, | V16: NA | W16: Yajur | X16: Telugu, Hindi, English | Y16: Telugu , Hindi , English | Z16: NA | AA16: Software engineer | AB16: Not Applicable (Not Registering a Child under 13) | AC16: Ganapathi homam, Rudra homam…etc | AD16: Low - Did not learn from Traditional Guru, but learnt from books/audio and perform daily Sandhya Vandanam and other poojas through books | AE16: Yes, This is High Priority for me | AF16: Yes | AG16: Yes | AH16: Yes | AI16: Yes | AJ16: Main goal is -I have to perform my Poojas at home without anyone’s help ( can be any Pooja or homam). And to retain our culture and spread it to next generations
A17: 2025 | B17: 46014.899 | C17: 4-REFERENCE? | D17: NO | E17: NO | F17: NO | G17: 1-ADULT OVER 16 YRS | H17: nagarajugudipudi@gmail.com | I17: Gudipudi | J17: Nagaraju | K17: =_xludf.TEXTJOIN(" ",TRUE,I17:J17) -> #NAME? | L17: 1963 | M17: 1992 | N17: 1-INDIA IST | O17: +91 | P17: 9866229986 | Q17: =P17&"/"&L17&"/"&K17 -> #NAME? | R17: HYDERABAD | S17: GUDIPUDI PRASUNA | T17: 9491453386 | U17: SHANDILYASA, MAITRAVARANA, KOUNDINYASA | V17: NA | W17: Yajurveda | X17: Telugu, Hindi, English | Y17: Telugu, Hindi, English. | Z17: NA | AA17: SBI Bank Manager Retired | AB17: Not Applicable (Not Registering a Child under 13) | AC17: Nithya Karma, Pancha Suktas, Visesha Suktas, Rudra Pada Patham, Smartha Poojas, Mahanyaasam, Smartham, Upanishads, Maha Narayanam, Arunam, Veda Aseervachanam, Ghana Swasthi., | AD17: Low - Did not learn from Traditional Guru, but learnt from books/audio and perform daily Sandhya Vandanam and other poojas through books | AE17: Not sure due to other commitments | AF17: Yes | AG17: Yes | AH17: Yes | AI17: Yes | AJ17: Atleast now I should be able to byheart the necessary slokas and sutras to do nitya pooja.
A18: 2025 | B18: 46015.121 | C18: 4-REFERENCE? | D18: NO | E18: NO | F18: NO | G18: 1-ADULT OVER 16 YRS | H18: prasadevs@gmail.com | I18: Emani | J18: V S Prasad | K18: =_xludf.TEXTJOIN(" ",TRUE,I18:J18) -> #NAME? | L18: 1961 | M18: 1981 | N18: 1-INDIA IST | O18: +91 | P18: 7095490205 | Q18: =P18&"/"&L18&"/"&K18 -> #NAME? | R18: hyderabad | S18: what app | T18: what app | U18: gowthamasa haritasa Gagresa | V18: not applicable | W18: rig veda | X18: telugu englush | Y18: telugu english | Z18: not applicable | AA18: rtd | AB18: Not Applicable (Not Registering a Child under 13) | AC18: nitya vidhi | AD18: Low - Did not learn from Traditional Guru, but learnt from books/audio and perform daily Sandhya Vandanam and other poojas through books | AE18: Not sure due to other commitments | AF18: Yes | AG18: Yes | AH18: Yes | AI18: Yes
A19: 2025 | B19: 46016.441 | C19: 4-REFERENCE? | D19: NO | E19: NO | F19: NO | G19: 1-ADULT OVER 16 YRS | H19: venkata.yammanuru@gmail.com | I19: Yammanuru | J19: Venkata Phaneendra | K19: =_xludf.TEXTJOIN(" ",TRUE,I19:J19) -> #NAME? | L19: 1992 | M19: 2007 | N19: 1-INDIA IST | O19: +91 | P19: 9154320012 | Q19: =P19&"/"&L19&"/"&K19 -> #NAME? | R19: Kadiri | S19: G Vishnu Sri vardhan | T19: 9491380172 | U19: N/A | V19: Sri vasthasa, Aathreyasa | W19: Yajur veda | X19: Telugu, English, Hindi | Y19: Telugu, English, Hindi | Z19: N/A | AA19: Software engineer | AB19: Not Applicable (Not Registering a Child under 13) | AC19: Self Intrest. | AD19: None - Do not know much about this subject, but committed to learn | AE19: Yes, This is High Priority for me | AF19: Yes | AG19: Yes | AH19: Yes | AI19: Yes | AJ19: To perform daily pooja.
A20: 2025 | B20: 46021.302 | C20: 4-REFERENCE? | D20: NO | E20: NO | F20: NO | G20: 1-ADULT OVER 16 YRS | H20: bharatchandraji@gmail.com | I20: Mukkavalli | J20: Bharat Chandra | K20: =_xludf.TEXTJOIN(" ",TRUE,I20:J20) -> #NAME? | L20: 2002 | M20: 2012 | N20: 1-INDIA IST | O20: +91 | P20: 9121277268 | Q20: =P20&"/"&L20&"/"&K20 -> #NAME? | R20: Mumbai | S20: Viswa Prasad Mukkavalli | T20: 9849406522 | U20: N/A | V20: Kousikasa, Athreyasa | W20: Yajur Veda | X20: Telugu, Hindi, English | Y20: Telugu-Beginner, English-Full Proficiency, Hindi-Proficient | Z20: N/A | AA20: M.Tech Student | AB20: 5- STUDENT OVER 13. Not Applicable | AC20: I have always wanted to learn the vedas. | AD20: Low - Did not learn from Traditional Guru, but learnt from books/audio and perform daily Sandhya Vandanam and other poojas through books | AE20: Yes, This is Top Priority for me | AF20: Yes | AG20: Yes | AH20: Yes | AI20: Yes
A21: 2025 | B21: 46021.849 | C21: 4-REFERENCE? | D21: NO | E21: NO | F21: NO | G21: 1-ADULT OVER 16 YRS | H21: nelapatlasastry@gmail.com | I21: Nelapatla | J21: Subbarama Sastry | K21: =_xludf.TEXTJOIN(" ",TRUE,I21:J21) -> #NAME? | L21: 1994 | M21: 2008 | N21: 1-INDIA IST | O21: +91 | P21: 7675030340 | Q21: =P21&"/"&L21&"/"&K21 -> #NAME? | R21: Hyderabad | S21: Nelabhotla yeswanth kumar | T21: 9381583342 | U21: Bharadhwaja, koundinyasa, kasyapasa | V21: N/A | W21: Krishna Yajurveda | X21: Telugu, English and hindi | Y21: Telugu and english | Z21: N/A | AA21: Public sector employee | AB21: 5- STUDENT OVER 13. Not Applicable | AC21: For peace and teach my kids in future | AD21: None - Do not know much about this subject, but committed to learn | AE21: Yes, This is Top Priority for me | AF21: Yes | AG21: Yes | AH21: Yes | AI21: Yes
A22: 2025 | B22: 46023.034 | C22: 4-REFERENCE? | D22: NO | E22: NO | F22: NO | G22: 1-ADULT OVER 16 YRS | H22: barurao@rediffmail.com | I22: Baru | J22: Narasimha Rao | K22: =_xludf.TEXTJOIN(" ",TRUE,I22:J22) -> #NAME? | L22: 1963 | M22: 1992 | N22: 1-INDIA IST | O22: +91 | P22: 8484970065 | Q22: =P22&"/"&L22&"/"&K22 -> #NAME? | R22: Pune | S22: Raghavendra Rao | T22: 9247465125 | U22: Bharadwaja/ vashishta / kasyapasa | V22: N/A | W22: Rig veda | X22: Telugu | Y22: English; hindi | Z22: N/A | AA22: Retired | AB22: 5- STUDENT OVER 13. Not Applicable | AC22: Veda chanting | AD22: Low - Did not learn from Traditional Guru, but learnt from books/audio and perform daily Sandhya Vandanam and other poojas through books | AE22: Yes, This is Top Priority for me | AF22: Yes | AG22: Yes | AH22: Yes | AI22: Yes
A23: 2026 | B23: 46154.016 | C23: 4-REFERENCE? | D23: TBD | E23: TBD | F23: TBD | G23: 1-ADULT OVER 16 YRS | H23: vasishtaswarna@gmail.com | I23: Swarna | J23: Srikrishna Vasishta | K23: =_xludf.TEXTJOIN(" ",TRUE,I23:J23) -> #NAME? | L23: 2008 | M23: 2019 | N23: 1-INDIA IST | O23: +91 | P23: 7013164026 | Q23: =P23&"/"&L23&"/"&K23 -> #NAME? | R23: Hyderabad | S23: Nadendla Sudheer Kumar | T23: 8885578787 | U23: N/A | V23: Koundinyasa, Kasyapasa | W23: Yajurvedam | X23: Telugu, English, Hindi | Y23: Telugu, English, Hindi | Z23: Swarna Siva Subrahmanyam, Swarna Harichandana | AA23: Student | AB23: 5- STUDENT OVER 13. Not Applicable | AC23: Smartam | AD23: None - Do not know much about this subject, but committed to learn | AE23: Not sure due to other commitments | AF23: Yes | AG23: Yes | AH23: Yes | AI23: Yes
A24: 2024 | B24: 45386.869 | C24: 5-WHATSAPP? | D24: YES | E24: NO | F24: NO | G24: 2-CHILD UNDER 16 YRS | H24: mvbhavani86@gmail.com | I24: Neelalohith | J24: Hanumath | K24: =_xludf.TEXTJOIN(" ",TRUE,I24:J24) -> #NAME? | L24: 2014 | N24: 2-USA EST | O24: +1 | P24: 9492728342 | Q24: =P24&"/"&L24&"/"&K24 -> #NAME? | R24: North carolina | S24: Kotam Raju srinivas rao | T24: Kotam Raju srinivas rao | U24: Koundinyasa, Kasyapasa, Brahmachari | V24: Koundinyasa, Kasyapasa, Brahmachari | W24: Yajur veda | X24: Telugu | Y24: English | Z24: M.chandra Kaladhar | AA24: N/A | AB24: Yes. Will Learn 1st Year Syllabus along with Child | AC24: To learn nityakarma puja | AD24: None - Do not know much about this subject, but committed to learn | AE24: Yes, This is High Priority for me | AF24: Yes | AG24: Yes | AH24: Yes | AI24: Yes
A25: 2024 | B25: 45273.483 | C25: YES | D25: YES | E25: YES | F25: YES | G25: 1-ADULT OVER 16 YRS | H25: tlbhaskar@gmail.com | I25: Lakshman | J25: Bhaskar | K25: =_xludf.TEXTJOIN(" ",TRUE,I25:J25) -> #NAME? | L25: 1960 | N25: 2-USA EST | O25: +1 | P25: 2487676387 | Q25: =P25&"/"&L25&"/"&K25 -> #NAME? | R25: Detroit | S25: Srinath Kunduruthy | T25: Srinath Kunduruthy | U25: Srivatsa, Haridasa, Kashyapa | V25: Srivatsa, Haridasa, Kashyapa | W25: Yajur | X25: Tamil, Telugu, English | Y25: Tamil, English | Z25: NA | AA25: IT professional | AB25: Not Applicable (Not Registering a Child under 13) | AC25: I want improve my chanting of vedas as I already learnt Guru Mula Rudram, Chamakam. Suktas basic ones | AD25: High - Learnt from Traditional Guru in perfect swaram/uccharana - perform nithya Sandhya Vandanam and can recite few Suktams in su-swaram | AE25: Yes, This is High Priority for me | AF25: Yes | AG25: Yes | AH25: Yes | AI25: Yes | AJ25: I want to learn Mahanyasam which is being taught in AP which is very elaborate to start with
A26: 2024 | B26: 45278.249 | C26: YES | D26: YES | E26: YES | F26: YES | G26: 1-ADULT OVER 16 YRS | H26: bvmk_rao27@rediffmail.com | I26: Bhattiprolu | J26: Venkata Murali Krishna Rao | K26: =_xludf.TEXTJOIN(" ",TRUE,I26:J26) -> #NAME? | L26: 1976 | N26: 1-INDIA IST | O26: +91 | P26: 9440378057 | Q26: =P26&"/"&L26&"/"&K26 -> #NAME? | R26: Hyderabad | S26: Satish sarma tumuluri guruvugaru (Budwel veda patasala) | T26: Satish sarma tumuluri guruvugaru (Budwel veda patasala) | U26: Koundinyasa, Bharadwajasa, Bharadwajasa | V26: Koundinyasa, Bharadwajasa, Bharadwajasa | W26: Yajur veda | X26: Telugu, English ,Hindi | Y26: Telugu ,English, Hindi | Z26: N/A | AA26: Private Sector. | AB26: Not Applicable (Not Registering a Child under 13) | AC26: I want to be able to do nitya karma that brahmin should be doing. Want to lead life as per Sanatana dharma. | AD26: Low - Did not learn from Traditional Guru, but learnt from books/audio and perform daily Sandhya Vandanam and other poojas through books | AE26: Yes, This is High Priority for me | AF26: Yes | AG26: Yes | AH26: Yes | AI26: Yes | AJ26: I am Sandhyavandanam 3 times a day but want sookthams and other nitya karma's like pitru tarpanas and daily Puja with proper shodasa vidhanam. Budwel vedapatasala guruvu garu suggested your classes.
A27: 2024 | B27: 45294.75 | C27: YES | D27: YES | E27: YES | F27: YES | G27: 1-ADULT OVER 16 YRS | H27: ssripada@gmail.com | I27: Shripada | J27: Subrahmanya Srinivasa | K27: =_xludf.TEXTJOIN(" ",TRUE,I27:J27) -> #NAME? | L27: 1963 | N27: 2-USA EST | O27: +1 | P27: 6474041774 | Q27: =P27&"/"&L27&"/"&K27 -> #NAME? | R27: Toronto, Canada | S27: SRINIVAS MARLA | T27: SRINIVAS MARLA | U27: Kaushikasa, Kaundinyasa, Gauthamasa | V27: Kaushikasa, Kaundinyasa, Gauthamasa | W27: Yajur Veda | X27: Telugu, English, Hindi, Kannada | Y27: Telugu, English | Z27: N/A | AA27: Civil Enginner | AB27: Not Applicable (Not Registering a Child under 13) | AC27: To better understand and knowing of Vedas and to gain spiritual knowledge | AD27: Low - Did not learn from Traditional Guru, but learnt from books/audio and perform daily Sandhya Vandanam and other poojas through books | AE27: Yes, This is High Priority for me | AF27: Yes | AG27: Yes | AH27: Yes | AI27: Yes | AJ27: I would like to join the course and develop my skills. Thanks
A28: 2024 | B28: 45298.909 | C28: YES | D28: YES | E28: YES | F28: YES | G28: 1-ADULT OVER 16 YRS | H28: vedula.abhishek1@gmail.com | I28: Vedula | J28: Abhishek | K28: =_xludf.TEXTJOIN(" ",TRUE,I28:J28) -> #NAME? | L28: 1995 | N28: 1-INDIA IST | O28: +91 | P28: 7207128428 | Q28: =P28&"/"&L28&"/"&K28 -> #NAME? | R28: Hyderabad | S28: VEDULA ABHISHEK | T28: VEDULA ABHISHEK | U28: Bharadwaja, Srivatsa, Kaundinyasa | V28: Bharadwaja, Srivatsa, Kaundinyasa | W28: SAMA VEDA | X28: Telugu, English | Y28: Telugu, English | Z28: N/A | AA28: Software Engineer | AB28: Not Applicable (Not Registering a Child under 13) | AC28: I couldn't learn this during my childhood. I have interest in learning nithyakarma, smartham , pooja vidhis so that I can stick to my cultural roots. | AD28: None - Do not know much about this subject, but committed to learn | AE28: Yes, This is High Priority for me | AF28: Yes | AG28: Yes | AH28: Yes | AI28: Yes | AJ28: Although many of my family members are into paurohitham unfortunately I couldn't learn from them during my childhood. I will be privileged if I get into the course and find a guru. 🙏
A29: 2024 | B29: 45298.993 | C29: YES | D29: YES | E29: YES | F29: YES | G29: 2-CHILD UNDER 16 YRS | H29: raviec04@gmail.com | I29: Tadepally | J29: Sri Rama Karthikeya Sharma | K29: =_xludf.TEXTJOIN(" ",TRUE,I29:J29) -> #NAME? | L29: 2013 | N29: 1-INDIA IST | O29: +91 | P29: 9940343476 | Q29: =P29&"/"&L29&"/"&K29 -> #NAME? | R29: Hyderabad | S29: Sai Srinivas Jagarlamudi | T29: Sai Srinivas Jagarlamudi | U29: Harithasa, Gauthamasa, N/A | V29: Harithasa, Gauthamasa, N/A | W29: Yajur | X29: Telugu | Y29: Telugu, Hindi, English | Z29: Ravikanth Sharma Tadepally | AA29: 5th Grade | AB29: Yes. Will Learn 1st Year Syllabus along with Child | AC29: To follow sanatana dharmam as prescribed in Vedas | AD29: Low - Did not learn from Traditional Guru, but learnt from books/audio and perform daily Sandhya Vandanam and other poojas through books | AE29: Yes, This is High Priority for me | AF29: Yes | AG29: Yes | AH29: Yes | AI29: Yes
A30: 2024 | B30: 45323.017 | C30: YES | D30: YES | E30: YES | F30: YES | G30: 1-ADULT OVER 16 YRS | H30: sudan1955@gmail.com | I30: Kurada | J30: Madhusudana Rao | K30: =_xludf.TEXTJOIN(" ",TRUE,I30:J30) -> #NAME? | L30: 1955 | N30: 1-INDIA IST | O30: +91 | P30: 8500945799 | Q30: =P30&"/"&L30&"/"&K30 -> #NAME? | R30: Hyderabad | S30: Venkata Satya Vijay Kommaraju | T30: Venkata Satya Vijay Kommaraju | U30: Srivatsasa, Sandilyasa, Sandilyasa | V30: Srivatsasa, Sandilyasa, Sandilyasa | W30: Yajur Veda Krishna Sakha | X30: Telugu | Y30: Telugu, English, Hindi | Z30: N/A | AA30: General Manager BSNL Retired | AB30: Not Applicable (Not Registering a Child under 13) | AC30: Interested in our tradition. Know Sandhyavandanam etc and some sukthas | AD30: Low - Did not learn from Traditional Guru, but learnt from books/audio and perform daily Sandhya Vandanam and other poojas through books | AE30: Yes, This is High Priority for me | AF30: Yes | AG30: Yes | AH30: Yes | AI30: Yes | AJ30: Once occasional smoker. Stopped long back
A31: 2024 | B31: 45323.074 | C31: YES | D31: YES | E31: YES | F31: YES | G31: 1-ADULT OVER 16 YRS | H31: charans92@gmail.com | I31: Indrakanti | J31: Shiva Charan | K31: =_xludf.TEXTJOIN(" ",TRUE,I31:J31) -> #NAME? | L31: 1992 | N31: 4-USA MST/PST | O31: +1 | P31: 8509806681 | Q31: =P31&"/"&L31&"/"&K31 -> #NAME? | R31: Seattle | S31: Rama Krishna | T31: Rama Krishna | U31: Srivatsasa, Bharadwajasa, N/A | V31: Srivatsasa, Bharadwajasa, N/A | W31: Yajur Veda | X31: Telugu English Hindi | Y31: Telugu English Hindi | Z31: N/A | AA31: Hardware Engineer | AB31: Not Applicable (Not Registering a Child under 13) | AC31: Out of Passion | AD31: Low - Did not learn from Traditional Guru, but learnt from books/audio and perform daily Sandhya Vandanam and other poojas through books | AE31: Yes, This is High Priority for me | AF31: Yes | AG31: Yes | AH31: Yes | AI31: Yes | AJ31: Phone Number is +18509806681
A32: 2024 | B32: 45323.179 | C32: YES | D32: YES | E32: YES | F32: YES | G32: 1-ADULT OVER 16 YRS | H32: narasimharaokvn@rediffmail.com | I32: Kommaraju | J32: Venkata Narasimha Rao | K32: =_xludf.TEXTJOIN(" ",TRUE,I32:J32) -> #NAME? | L32: 1956 | N32: 1-INDIA IST | O32: +91 | P32: 9949093634 | Q32: =P32&"/"&L32&"/"&K32 -> #NAME? | R32: HYDERABAD | S32: Kommaraju venkata sarya vijay | T32: Kommaraju venkata sarya vijay | U32: Koundinyasa, Bharadwaja, Bharadwaja | V32: Koundinyasa, Bharadwaja, Bharadwaja | W32: Krishna Yajur Veda | X32: Telugu/hindi/english | Y32: Telugu/hindi/english | Z32: N/A | AA32: Bank AGM RETD. | AB32: Not Applicable (Not Registering a Child under 13) | AC32: Vedas meanings and nitya karmalu vidhanam | AD32: None - Do not know much about this subject, but committed to learn | AE32: Yes, This is High Priority for me | AF32: Yes | AG32: Yes | AH32: Yes | AI32: Yes | AJ32: Please allow me to participate
A33: 2024 | B33: 45329.44 | C33: YES | D33: YES | E33: YES | F33: YES | G33: 1-ADULT OVER 16 YRS | H33: praveendaita@gmail.com | I33: Daita | J33: Praveen | K33: =_xludf.TEXTJOIN(" ",TRUE,I33:J33) -> #NAME? | L33: 1979 | N33: 1-INDIA IST | O33: +91 | P33: 9885981818 | Q33: =P33&"/"&L33&"/"&K33 -> #NAME? | R33: Hyderabad | S33: M Ravi Kiran Sharma | T33: M Ravi Kiran Sharma | U33: Srivathsa, Bharadwajas, Haritasa | V33: Srivathsa, Bharadwajas, Haritasa | W33: Krishna yajur veda | X33: Telugu, English, Hindi | Y33: Telugu, English, Hindi | Z33: N/A | AA33: Operations Manager | AB33: Not Applicable (Not Registering a Child under 13) | AC33: To practice my daily rituals | AD33: Low - Did not learn from Traditional Guru, but learnt from books/audio and perform daily Sandhya Vandanam and other poojas through books | AE33: Yes, This is High Priority for me | AF33: Yes | AG33: Yes | AH33: Yes | AI33: Yes
A34: 2024 | B34: 45337.445 | C34: YES | D34: YES | E34: YES | F34: YES | G34: 1-ADULT OVER 16 YRS | H34: srivatsakurada@gmail.com | I34: Kurada | J34: Srivatsa | K34: =_xludf.TEXTJOIN(" ",TRUE,I34:J34) -> #NAME? | L34: 1997 | N34: 4-USA MST/PST | O34: +1 | P34: 2067781986 | Q34: =P34&"/"&L34&"/"&K34 -> #NAME? | R34: Redmond | S34: Vijay Kommaraju | T34: Vijay Kommaraju | U34: Srivatsasa, Sandilyasa, N/A | V34: Srivatsasa, Sandilyasa, N/A | W34: Krishna Yajur Veda | X34: Telugu, Hindi, English | Y34: English, Hindi, Telugu | Z34: N/A | AA34: Software Engineer | AB34: Not Applicable (Not Registering a Child under 13) | AC34: I want to learn ancient culture | AD34: None - Do not know much about this subject, but committed to learn | AE34: Not sure due to other commitments | AF34: Yes | AG34: Yes | AH34: Yes | AI34: Yes
A35: 2024 | B35: 45341.015 | C35: YES | D35: YES | E35: YES | F35: YES | G35: 1-ADULT OVER 16 YRS | H35: srkvsagar@gmail.com | I35: Sathuvalli | J35: Vidyasagar | K35: =_xludf.TEXTJOIN(" ",TRUE,I35:J35) -> #NAME? | L35: 1980 | N35: 4-USA MST/PST | O35: +1 | P35: 5412231699 | Q35: =P35&"/"&L35&"/"&K35 -> #NAME? | R35: Kennewick | S35: Bharat Vyakaranam | T35: Bharat Vyakaranam | U35: Bharadwaja, Koundinasya, Vishwamitra | V35: Bharadwaja, Koundinasya, Vishwamitra | W35: Yajur Veda | X35: Telugu, Kannada, English, Tamil, Hindi | Y35: Telugu, Kannada, English | Z35: N/A | AA35: Associate Professor | AB35: Not Applicable (Not Registering a Child under 13) | AC35: Complete Veda | AD35: None - Do not know much about this subject, but committed to learn | AE35: Yes, This is High Priority for me | AF35: Yes | AG35: Yes | AH35: Yes | AI35: Yes
A36: 2024 | B36: 45350.935 | C36: YES | D36: YES | E36: YES | F36: YES | G36: 1-ADULT OVER 16 YRS | H36: nirapavankumar@gmail.com | I36: Niraghatam | J36: Pavan | K36: =_xludf.TEXTJOIN(" ",TRUE,I36:J36) -> #NAME? | L36: 1981 | N36: 3-USA CST | O36: +1 | P36: 5123178882 | Q36: =P36&"/"&L36&"/"&K36 -> #NAME? | R36: Austin | S36: Pravallika Kautha | T36: Pravallika Kautha | U36: Bhargavasa, Kaundinyasa, N/A | V36: Bhargavasa, Kaundinyasa, N/A | W36: Yajur Veda | X36: Telugu, English | Y36: Telugu, English | Z36: Niraghatam Subbarao, Niraghatam Parvathi Prasanna | AA36: IT | AB36: Not Applicable (Not Registering a Child under 13) | AC36: To learn Vedam and correct pronunciation | AD36: Low - Did not learn from Traditional Guru, but learnt from books/audio and perform daily Sandhya Vandanam and other poojas through books | AE36: Yes, This is High Priority for me | AF36: Yes | AG36: Yes | AH36: Yes | AI36: Yes
A37: 2024 | B37: 45372.905 | C37: YES | D37: YES | E37: YES | F37: YES | G37: 1-ADULT OVER 16 YRS | H37: parthumanikonda04@gmail.com | I37: Manikonda | J37: Parthasaradhi | K37: =_xludf.TEXTJOIN(" ",TRUE,I37:J37) -> #NAME? | L37: 2004 | N37: 1-INDIA IST | O37: +91 | P37: 7995955739 | Q37: =P37&"/"&L37&"/"&K37 -> #NAME? | R37: Hyderabad | S37: Yathin Chandra Manikonda | T37: Yathin Chandra Manikonda | U37: Kowndinyasa, Harithasa, N/A | V37: Kowndinyasa, Harithasa, N/A | W37: Krishna Yajur vedam | X37: Telugu, English | Y37: Telugu , English | Z37: N/A | AA37: Btech 3rd year student | AB37: Not Applicable (Not Registering a Child under 13) | AC37: To practice our Vedic dharma | AD37: Low - Did not learn from Traditional Guru, but learnt from books/audio and perform daily Sandhya Vandanam and other poojas through books | AE37: Yes, This is High Priority for me | AF37: Yes | AG37: Yes | AH37: Yes | AI37: Yes | AJ37: NA
A38: 2024 | B38: 45372.915 | C38: YES | D38: YES | E38: YES | F38: YES | G38: 1-ADULT OVER 16 YRS | H38: siva.tatavarthi@yahoo.co.in | I38: Tatavarthi | J38: Sivaramakrishna | K38: =_xludf.TEXTJOIN(" ",TRUE,I38:J38) -> #NAME? | L38: 1973 | N38: 1-INDIA IST | O38: +91 | P38: 9962557438 | Q38: =P38&"/"&L38&"/"&K38 -> #NAME? | R38: Hyderabad | S38: Manikonda yatin chandra | T38: Manikonda yatin chandra | U38: Koundinyasa, Bharadwajasa, Kousikasa | V38: Koundinyasa, Bharadwajasa, Kousikasa | W38: Yajur veda | X38: Telugu | Y38: Telugu | Z38: NA | AA38: Architect | AB38: Not Applicable (Not Registering a Child under 13) | AC38: As per syllabus | AD38: High - Learnt from Traditional Guru in perfect swaram/uccharana - perform nithya Sandhya Vandanam and can recite few Suktams in su-swaram | AE38: Yes, This is High Priority for me | AF38: Yes | AG38: Yes | AH38: Yes | AI38: Yes | AJ38: Very keen
A39: 2024 | B39: 45372.939 | C39: YES | D39: YES | E39: YES | F39: YES | G39: 1-ADULT OVER 16 YRS | H39: sreekararockzz@gmail.com | I39: Mokshagundam | J39: Sreekara | K39: =_xludf.TEXTJOIN(" ",TRUE,I39:J39) -> #NAME? | L39: 1995 | N39: 1-INDIA IST | O39: +91 | P39: 9035023670 | Q39: =P39&"/"&L39&"/"&K39 -> #NAME? | R39: Bangalore | S39: N/A | T39: N/A | U39: Bharadwajasa, kowndinyasa, N/A | V39: Bharadwajasa, kowndinyasa, N/A | W39: Yajur veda | X39: English, Telugu | Y39: English, Telugu | Z39: N/A | AA39: Software engineer | AB39: Not Applicable (Not Registering a Child under 13) | AC39: To be able to perform my nitya karma and daily Pooja | AD39: Low - Did not learn from Traditional Guru, but learnt from books/audio and perform daily Sandhya Vandanam and other poojas through books | AE39: Yes, This is High Priority for me | AF39: Yes | AG39: Yes | AH39: Yes | AI39: Yes
A40: 2024 | B40: 45372.951 | C40: YES | D40: YES | E40: YES | F40: YES | G40: 2-CHILD UNDER 16 YRS | H40: nandanrags@gmail.com | I40: Pandilla | J40: Narahari Sharma | K40: =_xludf.TEXTJOIN(" ",TRUE,I40:J40) -> #NAME? | L40: 2012 | N40: 1-INDIA IST | O40: +91 | P40: 9701055200 | Q40: =P40&"/"&L40&"/"&K40 -> #NAME? | R40: Hyderabad | S40: Raghu Nandan | T40: Raghu Nandan | U40: Gowthamasa, Parasara, N/A | V40: Gowthamasa, Parasara, N/A | W40: Rig veda | X40: Telugu, English, hindi | Y40: English | Z40: Raghu Nandan Pandilla | AA40: 7th Grade Student | AB40: Already know 1st year Syllabus. Hence will help the child at home | AC40: Being Brahmin in stress in learning vedas | AD40: Low - Did not learn from Traditional Guru, but learnt from books/audio and perform daily Sandhya Vandanam and other poojas through books | AE40: Yes, This is High Priority for me | AF40: Yes | AG40: Yes | AH40: Yes | AI40: Yes | AJ40: Very much intrested to join , preferably offline classes (face to face)
A41: 2024 | B41: 45372.955 | C41: YES | D41: YES | E41: YES | F41: YES | G41: 1-ADULT OVER 16 YRS | H41: bharani.rayaprolu@gmail.com | I41: Rayaprolu | J41: Bharani Kumar | K41: =_xludf.TEXTJOIN(" ",TRUE,I41:J41) -> #NAME? | L41: 1985 | N41: 1-INDIA IST | O41: +91 | P41: 9989244903 | Q41: =P41&"/"&L41&"/"&K41 -> #NAME? | R41: Hyderabad | S41: Rayaprolu pavan kumar | T41: Rayaprolu pavan kumar | U41: Athreyasa, Bharadwajasa, Kousikasa | V41: Athreyasa, Bharadwajasa, Kousikasa | W41: Yajur veda | X41: Telugu, english | Y41: Telugu, english | Z41: Na | AA41: Private employee | AB41: Not Applicable (Not Registering a Child under 13) | AC41: To educate myself and keep the dharmic things into practice. | AD41: None - Do not know much about this subject, but committed to learn | AE41: Yes, This is High Priority for me | AF41: Yes | AG41: Yes | AH41: Yes | AI41: Yes | AJ41: Please consider me for this year and i will ensure i will join classes without fail and practice what i learnt.
A42: 2024 | B42: 45372.977 | C42: YES | D42: YES | E42: YES | F42: NO | G42: 1-ADULT OVER 16 YRS | H42: venkatesh.kottapalli@gmail.com | I42: Kothapalli | J42: Venkatesh | K42: =_xludf.TEXTJOIN(" ",TRUE,I42:J42) -> #NAME? | L42: 1988 | N42: 4-USA MST/PST | O42: +1 | P42: 5144661621 | Q42: =P42&"/"&L42&"/"&K42 -> #NAME? | R42: Calgary | S42: Pavan Rayaprolu | T42: Pavan Rayaprolu | U42: Harithasa, Koundinyasa, Bhagavatula | V42: Harithasa, Koundinyasa, Bhagavatula | W42: Rig veda | X42: Telugu English | Y42: Telugu English | Z42: N/a | AA42: Recruiter | AB42: Not Applicable (Not Registering a Child under 13) | AC42: To learn about culture process | AD42: None - Do not know much about this subject, but committed to learn | AE42: Yes, This is High Priority for me | AF42: Yes | AG42: Yes | AH42: Yes | AI42: Yes
A43: 2024 | B43: 45372.993 | C43: YES | D43: YES | E43: YES | F43: YES | G43: 1-ADULT OVER 16 YRS | H43: murthykothapalli5959@gmail.com | I43: Kothapalli | J43: Narasimha Murthy | K43: =_xludf.TEXTJOIN(" ",TRUE,I43:J43) -> #NAME? | L43: 1962 | N43: 1-INDIA IST | O43: +91 | P43: 9346834357 | Q43: =P43&"/"&L43&"/"&K43 -> #NAME? | R43: Khammam | S43: R.K.V.Pavan kumar | T43: R.K.V.Pavan kumar | U43: Harithasa, Kousikasa, Koundinyasa | V43: Harithasa, Kousikasa, Koundinyasa | W43: Yajurvweda | X43: Telugu | Y43: Telugu | Z43: N/A | AA43: Retired | AB43: Not Applicable (Not Registering a Child under 13) | AC43: Total | AD43: None - Do not know much about this subject, but committed to learn | AE43: Yes, This is High Priority for me | AF43: Yes | AG43: Yes | AH43: Yes | AI43: Yes | AJ43: Good service
A44: 2024 | B44: 45372.995 | C44: YES | D44: YES | E44: YES | F44: YES | G44: 1-ADULT OVER 16 YRS | H44: potharajuvenkat824@gmail.com | I44: Potharaju | J44: Venkat Sharma | K44: =_xludf.TEXTJOIN(" ",TRUE,I44:J44) -> #NAME? | L44: 2001 | N44: 1-INDIA IST | O44: +91 | P44: 9581698919 | Q44: =P44&"/"&L44&"/"&K44 -> #NAME? | R44: Bengaluru | S44: Manikanta Chillara | T44: Manikanta Chillara | U44: Kaundinyasa, Kashyapasa, NA | V44: Kaundinyasa, Kashyapasa, NA | W44: Yajur Vedam | X44: Telugu, English, Hindi | Y44: Telugu, English, Hindi | Z44: Dr P Venkateswara Rao | AA44: Analog Design Engineer | AB44: Not Applicable (Not Registering a Child under 13) | AC44: I want to learn Vedas because it’s my duty. Aadhyana, Adhyapana are the basic duties of Brahmin | AD44: Low - Did not learn from Traditional Guru, but learnt from books/audio and perform daily Sandhya Vandanam and other poojas through books | AE44: Yes, This is High Priority for me | AF44: Yes | AG44: Yes | AH44: Yes | AI44: Yes | AJ44: I am very much excited to learn and be part of this wonderful course. I am blessed. Sharade Pahimam Shankar Rakshamam
A45: 2024 | B45: 45373.004 | C45: YES | D45: YES | E45: YES | F45: YES | G45: 1-ADULT OVER 16 YRS | H45: kameswarasastrya@gmail.com | I45: Amanamanchi | J45: Kameswara Sastry | K45: =_xludf.TEXTJOIN(" ",TRUE,I45:J45) -> #NAME? | L45: 1988 | N45: 1-INDIA IST | O45: +91 | P45: 9959167555 | Q45: =P45&"/"&L45&"/"&K45 -> #NAME? | R45: Hyderabad | S45: Self | T45: Self | U45: Bharadwajasa, Srivatsa, Koundinyasa | V45: Bharadwajasa, Srivatsa, Koundinyasa | W45: Yajur Veda | X45: Telugu, English | Y45: Telugu, English | Z45: N/A | AA45: Software Engineer | AB45: Not Applicable (Not Registering a Child under 13) | AC45: For performing daily rituals | AD45: Low - Did not learn from Traditional Guru, but learnt from books/audio and perform daily Sandhya Vandanam and other poojas through books | AE45: Yes, This is High Priority for me | AF45: Yes | AG45: Yes | AH45: Yes | AI45: Yes | AJ45: I am committed to lernt
A46: 2024 | B46: 45373.018 | C46: YES | D46: YES | E46: YES | F46: YES | G46: 1-ADULT OVER 16 YRS | H46: mallikarjun.kasibhatta@gmail.com | I46: Kasibhatta | J46: Mallikarjun | K46: =_xludf.TEXTJOIN(" ",TRUE,I46:J46) -> #NAME? | L46: 1971 | N46: 1-INDIA IST | O46: +91 | P46: 9885030611 | Q46: =P46&"/"&L46&"/"&K46 -> #NAME? | R46: Hyderabad | S46: SGB group | T46: SGB group | U46: Koundinyasa, Harithasa, Kashyapa | V46: Koundinyasa, Harithasa, Kashyapa | W46: Yajur veda | X46: Telugu | Y46: Telugu, hindi, english | Z46: N/A | AA46: Self employed | AB46: Yes. Will Learn 1st Year Syllabus along with Child | AC46: Jagadguru Sri ADI SANKARA said "Vedo nityamadiyatam..." | AD46: High - Learnt from Traditional Guru in perfect swaram/uccharana - perform nithya Sandhya Vandanam and can recite few Suktams in su-swaram | AE46: Yes, This is High Priority for me | AF46: Yes | AG46: Yes | AH46: Yes | AI46: Yes | AJ46: I and my 9 yr old son are doing regular nitya karma, so we want from year 1 part B syllabus onwards. I recite rudram regularly, my child learnt namakam and chamakam is pending. Other suktas my son needs to learn. Hence asking from part B onwards.
A47: 2024 | B47: 45373.025 | C47: YES | D47: YES | E47: YES | F47: YES | G47: 1-ADULT OVER 16 YRS | H47: smdu1967@gmail.com | I47: Samavedam | J47: Malleshwara Sharma | K47: =_xludf.TEXTJOIN(" ",TRUE,I47:J47) -> #NAME? | L47: 1967 | N47: 1-INDIA IST | O47: +91 | P47: 8978544100 | Q47: =P47&"/"&L47&"/"&K47 -> #NAME? | R47: హైదరాబాద్ | S47: తూములూరి కృష్ణ ప్రసాద్ | T47: తూములూరి కృష్ణ ప్రసాద్ | U47: హరిత సగోత్రం, భరద్వాజ, గౌతమ సగోత్రం | V47: హరిత సగోత్రం, భరద్వాజ, గౌతమ సగోత్రం | W47: కృష్ణ యాజర్వేద | X47: తెలుగు | Y47: తెలుగు | Z47: Na | AA47: ప్రైవేట్ | AB47: Not Applicable (Not Registering a Child under 13) | AC47: బ్రాహ్మణ పరంపారా విద్య నేర్చుకోవాలని | AD47: High - Learnt from Traditional Guru in perfect swaram/uccharana - perform nithya Sandhya Vandanam and can recite few Suktams in su-swaram | AE47: Yes, This is High Priority for me | AF47: Yes | AG47: Yes | AH47: Yes | AI47: Yes
A48: 2024 | B48: 45373.032 | C48: YES | D48: YES | E48: YES | F48: YES | G48: 2-CHILD UNDER 16 YRS | H48: boochulu.ss@gmail.com | I48: Sharma | J48: Saket Ram | K48: =_xludf.TEXTJOIN(" ",TRUE,I48:J48) -> #NAME? | L48: 2014 | N48: 1-INDIA IST | O48: +91 | P48: 9440149494 | Q48: =P48&"/"&L48&"/"&K48 -> #NAME? | R48: Hyderabad | S48: Sankarmutt | T48: Sankarmutt | U48: Koundinyasa, Srivatsasa, N/A | V48: Koundinyasa, Srivatsasa, N/A | W48: Yajurveda | X48: Telugu | Y48: Telugu | Z48: Employee LIC | AA48: Student | AB48: Already know 1st year Syllabus. Hence will help the child at home | AC48: Dharmika jeevanam | AD48: Low - Did not learn from Traditional Guru, but learnt from books/audio and perform daily Sandhya Vandanam and other poojas through books | AE48: Yes, This is High Priority for me | AF48: Yes | AG48: Yes | AH48: Yes | AI48: Yes | AJ48: Hare Krishna
A49: 2024 | B49: 45373.058 | C49: YES | D49: YES | E49: YES | F49: YES | G49: 2-CHILD UNDER 16 YRS | H49: gushagiridhar@gmail.com | I49: Yasasvi | J49: Krishna | K49: =_xludf.TEXTJOIN(" ",TRUE,I49:J49) -> #NAME? | L49: 2013 | N49: 1-INDIA IST | O49: +91 | P49: 9414349343 | Q49: =P49&"/"&L49&"/"&K49 -> #NAME? | R49: Hyderabad | S49: Shyam. Kuppa | T49: Shyam. Kuppa | U49: Haritasa, Koundinyasa, N/A | V49: Haritasa, Koundinyasa, N/A | W49: Yajur | X49: Telugu, English | Y49: Tell, English and Hindi | Z49: G. V.GIRIDHAR, G USHA | AA49: 6th grade student | AB49: Yes. Will Learn 1st Year Syllabus along with Child | AC49: We want to make our kid aware of sanathana Dharma and learn Vedam along with regular studies | AD49: Low - Did not learn from Traditional Guru, but learnt from books/audio and perform daily Sandhya Vandanam and other poojas through books | AE49: Yes, This is High Priority for me | AF49: Yes | AG49: Yes | AH49: Yes | AI49: Yes | AJ49: Very good initiative , we are eagerly waiting for the classes to start
A50: 2024 | B50: 45373.066 | C50: YES | D50: YES | E50: YES | F50: YES | G50: 1-ADULT OVER 16 YRS | H50: bhanumscgitam@gmail.com | I50: Karanam | J50: Bhanu Chander | K50: =_xludf.TEXTJOIN(" ",TRUE,I50:J50) -> #NAME? | L50: 1984 | N50: 1-INDIA IST | O50: +91 | P50: 9290103468 | Q50: =P50&"/"&L50&"/"&K50 -> #NAME? | R50: Hyderabad | S50: SGB SV YAJUR TELUGU WHATSAPPGROUP , Mani Kanta Chillara Garu | T50: SGB SV YAJUR TELUGU WHATSAPPGROUP , Mani Kanta Chillara Garu | U50: Bhardwajasa, SriVastasa, SriVastasa | V50: Bhardwajasa, SriVastasa, SriVastasa | W50: Yajur Veda | X50: Telugu , Hindi, English | Y50: Telugu, Hindi, English | Z50: NA | AA50: Software Employee | AB50: Not Applicable (Not Registering a Child under 13) | AC50: Interested in Suktam, Rudram, Mahanysam, Aruna prashna, Nitya Karma & Sanatana Dharama teachings. | AD50: High - Learnt from Traditional Guru in perfect swaram/uccharana - perform nithya Sandhya Vandanam and can recite few Suktams in su-swaram | AE50: Yes, This is High Priority for me | AF50: Yes | AG50: Yes | AH50: Yes | AI50: Yes | AJ50: Thank you for this Opportunity.
A51: 2024 | B51: 45373.101 | C51: YES | D51: YES | E51: YES | F51: YES | G51: 1-ADULT OVER 16 YRS | H51: sv_manjunath@yahoo.com | I51: Sridharam Venkatraman | J51: Manjunath | K51: =_xludf.TEXTJOIN(" ",TRUE,I51:J51) -> #NAME? | L51: 1968 | N51: 1-INDIA IST | O51: +91 | P51: 9845157430 | Q51: =P51&"/"&L51&"/"&K51 -> #NAME? | R51: Bengaluru | S51: Sri Manikanta Chillara via SGB-SV-Yajur Telugu group | T51: Sri Manikanta Chillara via SGB-SV-Yajur Telugu group | U51: Gowthama gothram, Vishwamitra gothram, Kutsava gothram | V51: Gowthama gothram, Vishwamitra gothram, Kutsava gothram | W51: Yajur Veda | X51: Telugu, Hindi, English | Y51: Telugu, Hindi, Marathi, English | Z51: N/A | AA51: Independent Consultant - Chartered Accountant | AB51: Not Applicable (Not Registering a Child under 13) | AC51: I think it is important for every Hindu to know. I was highly interested, but no opportunities where I stayed before. Now, since it is online, I am very interested to fill the gap in my education. | AD51: High - Learnt from Traditional Guru in perfect swaram/uccharana - perform nithya Sandhya Vandanam and can recite few Suktams in su-swaram | AE51: Yes, This is High Priority for me | AF51: Yes | AG51: Yes | AH51: Yes | AI51: Yes | AJ51: I do not smoke, drink alcohol or eat meat. Those questions are not applicable to me.
A52: 2024 | B52: 45373.127 | C52: YES | D52: YES | E52: YES | F52: YES | G52: 1-ADULT OVER 16 YRS | H52: nivas.pasumarthi@gmail.com | I52: Pasumarthi | J52: Srinivas | K52: =_xludf.TEXTJOIN(" ",TRUE,I52:J52) -> #NAME? | L52: 1965 | N52: 1-INDIA IST | O52: +91 | P52: 9441026448 | Q52: =P52&"/"&L52&"/"&K52 -> #NAME? | R52: Hyderabad | S52: Kommu Srinivasa Bhaskar | T52: Kommu Srinivasa Bhaskar | U52: Kasyapa, కుత్సస, Harithasa | V52: Kasyapa, కుత్సస, Harithasa | W52: Krishna yajur veda | X52: Telugu, English | Y52: Telugu, English | Z52: N/A | AA52: Lecturer | AB52: Not Applicable (Not Registering a Child under 13) | AC52: To perform Abhishekam on my own | AD52: Low - Did not learn from Traditional Guru, but learnt from books/audio and perform daily Sandhya Vandanam and other poojas through books | AE52: Yes, This is High Priority for me | AF52: Yes | AG52: Yes | AH52: Yes | AI52: Yes | AJ52: I sincerely follow the above rules
A53: 2024 | B53: 45373.129 | C53: YES | D53: YES | E53: YES | F53: YES | G53: 1-ADULT OVER 16 YRS | H53: kpadmakar@gmail.com | I53: Kocherlakota | J53: Padmakar | K53: =_xludf.TEXTJOIN(" ",TRUE,I53:J53) -> #NAME? | L53: 1957 | N53: 1-INDIA IST | O53: +91 | P53: 7981517172 | Q53: =P53&"/"&L53&"/"&K53 -> #NAME? | R53: Hyderabad | S53: Tumuluri Krishna Prasad | T53: Tumuluri Krishna Prasad | U53: Kasyapasa, Harithasa, Bharadwajasa | V53: Kasyapasa, Harithasa, Bharadwajasa | W53: Yajur Veda | X53: Telugu, English | Y53: Telugu, English | Z53: Ramana Murthy | AA53: Retired Bank Manager | AB53: Not Applicable (Not Registering a Child under 13) | AC53: To upkeep the hindu traditions and rituals | AD53: Low - Did not learn from Traditional Guru, but learnt from books/audio and perform daily Sandhya Vandanam and other poojas through books | AE53: Yes, This is High Priority for me | AF53: Not sure | AG53: Yes | AH53: Yes | AI53: Yes
A54: 2024 | B54: 45373.135 | C54: YES | D54: YES | E54: YES | F54: YES | G54: 1-ADULT OVER 16 YRS | H54: k.sricharan@gmail.com | I54: Kocherlakota | J54: Sricharan | K54: =_xludf.TEXTJOIN(" ",TRUE,I54:J54) -> #NAME? | L54: 1974 | N54: 1-INDIA IST | O54: +91 | P54: 9885571274 | Q54: =P54&"/"&L54&"/"&K54 -> #NAME? | R54: Hyderabad | S54: Peddada Radha Krishna | T54: Peddada Radha Krishna | U54: Kasyapasa, Srivatsasa, Vasishtasa | V54: Kasyapasa, Srivatsasa, Vasishtasa | W54: Yajur Veda | X54: Telugu, English, Hindi | Y54: Telugu, English, Hindi | Z54: N/A | AA54: Director | AB54: Not Applicable (Not Registering a Child under 13) | AC54: To perfor Nitya Karma on my own and have basic knowledge about Veda. To get cultural knowledge and spread it and encourage younger generation | AD54: None - Do not know much about this subject, but committed to learn | AE54: Not sure due to other commitments | AF54: Yes | AG54: Yes | AH54: Yes | AI54: Yes | AJ54: Even though this is not high priority, I want to be a committed learner and want to practice nitya karma without fail
A55: 2024 | B55: 45373.146 | C55: YES | D55: YES | E55: YES | F55: YES | G55: 1-ADULT OVER 16 YRS | H55: medurivamsi@gmail.com | I55: Meduri | J55: Vamsikanth | K55: =_xludf.TEXTJOIN(" ",TRUE,I55:J55) -> #NAME? | L55: 1982 | N55: 1-INDIA IST | O55: +91 | P55: 9100402750 | Q55: =P55&"/"&L55&"/"&K55 -> #NAME? | R55: Hyderabad | S55: SGB group | T55: SGB group | U55: Kousikasa, Athreyasa, Koundinyasa | V55: Kousikasa, Athreyasa, Koundinyasa | W55: Yajur | X55: Telugu,Tamil, english | Y55: Telugu English Sanskrit hindhi | Z55: N/A | AA55: Software prfeasional | AB55: Not Applicable (Not Registering a Child under 13) | AC55: To save vedas | AD55: High - Learnt from Traditional Guru in perfect swaram/uccharana - perform nithya Sandhya Vandanam and can recite few Suktams in su-swaram | AE55: Yes, This is High Priority for me | AF55: Yes | AG55: Yes | AH55: Yes | AI55: Yes
A56: 2024 | B56: 45373.215 | C56: YES | D56: YES | E56: YES | F56: YES | G56: 2-CHILD UNDER 16 YRS | H56: shravanikondapaka@gmail.com | I56: Kondapaka | J56: Sriniketh | K56: =_xludf.TEXTJOIN(" ",TRUE,I56:J56) -> #NAME? | L56: 2013 | N56: 1-INDIA IST | O56: +91 | P56: 7569238056 | Q56: =P56&"/"&L56&"/"&K56 -> #NAME? | R56: Hyderabad | S56: Self | T56: Self | U56: Koundniyasa, Athryasa, Brahmachari | V56: Koundniyasa, Athryasa, Brahmachari | W56: Yajurveda | X56: Telugu | Y56: Telugu and English | Z56: Praveen kumar | AA56: 5th grade completing | AB56: Already know 1st year Syllabus. Hence will help the child at home | AC56: Sandhya vandanam and suktams and more with swaram | AD56: Low - Did not learn from Traditional Guru, but learnt from books/audio and perform daily Sandhya Vandanam and other poojas through books | AE56: Yes, This is High Priority for me | AF56: Yes | AG56: Yes | AH56: Yes | AI56: Yes | AJ56: V r shri vaishnav completely traditional and pure veg and I like to learn veda
A57: 2024 | B57: 45373.299 | C57: YES | D57: YES | E57: YES | F57: YES | G57: 1-ADULT OVER 16 YRS | H57: durgasairam1979@gmail.com | I57: Krovi | J57: Durga Sairam | K57: =_xludf.TEXTJOIN(" ",TRUE,I57:J57) -> #NAME? | L57: 1979 | N57: 1-INDIA IST | O57: +91 | P57: 9397054888 | Q57: =P57&"/"&L57&"/"&K57 -> #NAME? | R57: Vijayawada | S57: M Ravi Kiran Sharma | T57: M Ravi Kiran Sharma | U57: Harithasa, KoundinyasY, Koundinyas | V57: Harithasa, KoundinyasY, Koundinyas | W57: Krishna Yajur Veda | X57: Telugu | Y57: Telugu and English | Z57: NA | AA57: Accounts Manager | AB57: Not Applicable (Not Registering a Child under 13) | AC57: Pooja kriya learning | AD57: High - Learnt from Traditional Guru in perfect swaram/uccharana - perform nithya Sandhya Vandanam and can recite few Suktams in su-swaram | AE57: Yes, This is High Priority for me | AF57: Yes | AG57: Yes | AH57: Yes | AI57: Yes | AJ57: Thank you for this opportunity
A58: 2024 | B58: 45373.34 | C58: YES | D58: YES | E58: YES | F58: YES | G58: 1-ADULT OVER 16 YRS | H58: srikrishnanelapatla@gmail.com | I58: Nelapatla | J58: Srikrishna | K58: =_xludf.TEXTJOIN(" ",TRUE,I58:J58) -> #NAME? | L58: 1989 | N58: 1-INDIA IST | O58: +91 | P58: 9059397397 | Q58: =P58&"/"&L58&"/"&K58 -> #NAME? | R58: Ongole | S58: None | T58: None | U58: Bharadwajasa, Kaundinyasa, Kasyapasa | V58: Bharadwajasa, Kaundinyasa, Kasyapasa | W58: Yajur Veda | X58: Telugu, English | Y58: Telugu, English | Z58: N/A | AA58: IT Professional | AB58: Not Applicable (Not Registering a Child under 13) | AC58: I'm Interested in learning Vedam | AD58: None - Do not know much about this subject, but committed to learn | AE58: Yes, This is High Priority for me | AF58: Not sure | AG58: Yes | AH58: Yes | AI58: Yes
A59: 2024 | B59: 45373.346 | C59: YES | D59: YES | E59: YES | F59: YES | G59: 1-ADULT OVER 16 YRS | H59: ramakn@gmail.com | I59: Nibhanapuri | J59: Ramakrishna | K59: =_xludf.TEXTJOIN(" ",TRUE,I59:J59) -> #NAME? | L59: 1978 | N59: 1-INDIA IST | O59: +91 | P59: 9866130638 | Q59: =P59&"/"&L59&"/"&K59 -> #NAME? | R59: HYDERABAD | S59: Bharavi sharma sarabu | T59: Bharavi sharma sarabu | U59: koundinyasa, Haritasya, KOUSHIKA | V59: koundinyasa, Haritasya, KOUSHIKA | W59: Yajur Veda | X59: Telugu,English | Y59: Telugu,English | Z59: N/A | AA59: Faculty, ETE department, GNITS, Hyderabad | AB59: Not Applicable (Not Registering a Child under 13) | AC59: life ambition and continues improvement | AD59: Low - Did not learn from Traditional Guru, but learnt from books/audio and perform daily Sandhya Vandanam and other poojas through books | AE59: Yes, This is High Priority for me | AF59: Yes | AG59: Yes | AH59: Yes | AI59: Yes | AJ59: happy to be part of this course
A60: 2024 | B60: 45373.413 | C60: YES | D60: YES | E60: YES | F60: YES | G60: 1-ADULT OVER 16 YRS | H60: anandkappa@gmail.com | I60: Kappagantula | J60: Anand | K60: =_xludf.TEXTJOIN(" ",TRUE,I60:J60) -> #NAME? | L60: 1974 | N60: 4-USA MST/PST | O60: +1 | P60: 9257193072 | Q60: =P60&"/"&L60&"/"&K60 -> #NAME? | R60: Milpitas | S60: Sri Shiva Rama Krishna | T60: Sri Shiva Rama Krishna | U60: Kousikasa, Koundinyasa, NA | V60: Kousikasa, Koundinyasa, NA | W60: Krishna Yajur Veda | X60: Telugu | Y60: Sanskrit, Hindi | Z60: NA | AA60: IT Condultant | AB60: Not Applicable (Not Registering a Child under 13) | AC60: For Jñāna | AD60: High - Learnt from Traditional Guru in perfect swaram/uccharana - perform nithya Sandhya Vandanam and can recite few Suktams in su-swaram | AE60: Yes, This is High Priority for me | AF60: Yes | AG60: Yes | AH60: Yes | AI60: Yes
A61: 2024 | B61: 45373.486 | C61: YES | D61: YES | E61: YES | F61: YES | G61: 1-ADULT OVER 16 YRS | H61: sridhar.kvs@gmail.com | I61: Kuruganti | J61: Sridhar | K61: =_xludf.TEXTJOIN(" ",TRUE,I61:J61) -> #NAME? | L61: 1968 | N61: 3-USA CST | O61: +1 | P61: 2816855734 | Q61: =P61&"/"&L61&"/"&K61 -> #NAME? | R61: Houston | S61: Last year student | T61: Last year student | U61: Harithasa, Bharadwaja, Bharadwaja | V61: Harithasa, Bharadwaja, Bharadwaja | W61: Yajur Veda | X61: Telugu | Y61: Telugu | Z61: N/A | AA61: Software consultant | AB61: Not Applicable (Not Registering a Child under 13) | AC61: To practice Sanatana Dharma | AD61: Low - Did not learn from Traditional Guru, but learnt from books/audio and perform daily Sandhya Vandanam and other poojas through books | AE61: Yes, This is High Priority for me | AF61: Yes | AG61: Yes | AH61: Yes | AI61: Yes
A62: 2024 | B62: 45373.53 | C62: YES | D62: YES | E62: YES | F62: YES | G62: 1-ADULT OVER 16 YRS | H62: dbasrinivasr@gmail.com | I62: Rangavajhala | J62: Srinivas | K62: =_xludf.TEXTJOIN(" ",TRUE,I62:J62) -> #NAME? | L62: 1975 | N62: 1-INDIA IST | O62: +91 | P62: 8886665546 | Q62: =P62&"/"&L62&"/"&K62 -> #NAME? | R62: Hyderabad | S62: Online | T62: Online | U62: Bharadwajasa, Kasyapasa, Koundinyasa | V62: Bharadwajasa, Kasyapasa, Koundinyasa | W62: Yajur Veda | X62: Telugu, English | Y62: Telugu and English | Z62: NA | AA62: Software Engg | AB62: Not Applicable (Not Registering a Child under 13) | AC62: To become the path of Sanatana Dharma | AD62: Low - Did not learn from Traditional Guru, but learnt from books/audio and perform daily Sandhya Vandanam and other poojas through books | AE62: Yes, This is High Priority for me | AF62: Yes | AG62: Yes | AH62: Yes | AI62: Yes | AJ62: I am interested in this course and waiting for the same.
A63: 2024 | B63: 45373.533 | C63: YES | D63: YES | E63: YES | F63: YES | G63: 2-CHILD UNDER 16 YRS | H63: rsrinivas04@gmail.com | I63: Rangavajhala | J63: Yegna Datta | K63: =_xludf.TEXTJOIN(" ",TRUE,I63:J63) -> #NAME? | L63: 2010 | N63: 1-INDIA IST | O63: +91 | P63: 9133099933 | Q63: =P63&"/"&L63&"/"&K63 -> #NAME? | R63: Hyderabad | S63: Online | T63: Online | U63: Bharadwajasa, Koundinyasa, NA | V63: Bharadwajasa, Koundinyasa, NA | W63: Yajur Veda | X63: Telugu, English | Y63: Telugu and English | Z63: SRINIVAS R | AA63: NA | AB63: Yes. Will Learn 1st Year Syllabus along with Child | AC63: For upgrade my self | AD63: High - Learnt from Traditional Guru in perfect swaram/uccharana - perform nithya Sandhya Vandanam and can recite few Suktams in su-swaram | AE63: Yes, This is High Priority for me | AF63: Yes | AG63: Yes | AH63: Yes | AI63: Yes | AJ63: I am interested for this course
A64: 2024 | B64: 45373.683 | C64: YES | D64: YES | E64: YES | F64: YES | G64: 1-ADULT OVER 16 YRS | H64: sreedatta.rallabhandi@gmail.com | I64: Rallabhandi | J64: Sri Datta Sharma | K64: =_xludf.TEXTJOIN(" ",TRUE,I64:J64) -> #NAME? | L64: 2002 | N64: 1-INDIA IST | O64: +91 | P64: 8374522975 | Q64: =P64&"/"&L64&"/"&K64 -> #NAME? | R64: Hyderabad | S64: I got to know through WhatsApp group (Manikanta chillara) | T64: I got to know through WhatsApp group (Manikanta chillara) | U64: Bharadwajasa, Koundinyasa, N/A | V64: Bharadwajasa, Koundinyasa, N/A | W64: Krishna yajur vedam | X64: Telugu, english, hindi | Y64: Telugu Hindi English | Z64: N/A | AA64: Student (doing internship) | AB64: Not Applicable (Not Registering a Child under 13) | AC64: I'm interested to learn regarding Vedas, upanishads and their importance that's helps me improve myself to follow the responsibilities and dharmam, i learnt some parts like namakam chamakam sri suktam, purusha suuktam, durga suktam, ganapati atharvasheersham like this | AD64: Low - Did not learn from Traditional Guru, but learnt from books/audio and perform daily Sandhya Vandanam and other poojas through books | AE64: Yes, This is High Priority for me | AF64: Yes | AG64: Yes | AH64: Yes | AI64: Yes | AJ64: I'm very much interested to learn vedas upanishads and ill ensure myself that I'll learn and practice to full extent
A65: 2024 | B65: 45373.812 | C65: YES | D65: YES | E65: YES | F65: YES | G65: 1-ADULT OVER 16 YRS | H65: girimsp@gmail.com | I65: Malladi | J65: Srinivas Pavan Giri | K65: =_xludf.TEXTJOIN(" ",TRUE,I65:J65) -> #NAME? | L65: 1987 | N65: 1-INDIA IST | O65: +91 | P65: 8123277057 | Q65: =P65&"/"&L65&"/"&K65 -> #NAME? | R65: Bangalore | S65: Malladi Venkata Sita Ram Anjaneya Sarma | T65: Malladi Venkata Sita Ram Anjaneya Sarma | U65: Haritha, Bharadwaja, Srivatsa | V65: Haritha, Bharadwaja, Srivatsa | W65: Yajur Veda | X65: Telugu, Tamil, English, Kannada, Hindi | Y65: Sanskrit, English | Z65: N/A | AA65: Senior Project Manager | AB65: Not Applicable (Not Registering a Child under 13) | AC65: Nithya Anushtanam, Sooktam, | AD65: Low - Did not learn from Traditional Guru, but learnt from books/audio and perform daily Sandhya Vandanam and other poojas through books | AE65: Yes, This is High Priority for me | AF65: Yes | AG65: Yes | AH65: Yes | AI65: Yes | AJ65: Not too sure of the field "Reference Person". I gave the Reference person of a person who can vouch me as. Brahmin
A66: 2024 | B66: 45373.919 | C66: YES | D66: YES | E66: YES | F66: YES | G66: 1-ADULT OVER 16 YRS | H66: siripurapusrinivas64@gmail.com | I66: Siripurapu | J66: Srinivas | K66: =_xludf.TEXTJOIN(" ",TRUE,I66:J66) -> #NAME? | L66: 1963 | N66: 1-INDIA IST | O66: +91 | P66: 9391944044 | Q66: =P66&"/"&L66&"/"&K66 -> #NAME? | R66: GUNTUR (AP) | S66: Karanam Bhanu Chander | T66: Karanam Bhanu Chander | U66: GOUTHAMA, KOUNDINYA, BHARADWAJA | V66: GOUTHAMA, KOUNDINYA, BHARADWAJA | W66: Krishna Yajurveda | X66: Telugu, English, Hindi | Y66: Telugu, English, Hindi | Z66: N/A | AA66: Bank Manager 3rd Grade | AB66: Not Applicable (Not Registering a Child under 13) | AC66: To improve vedic skills and to practise sanathana dharma | AD66: High - Learnt from Traditional Guru in perfect swaram/uccharana - perform nithya Sandhya Vandanam and can recite few Suktams in su-swaram | AE66: Yes, This is High Priority for me | AF66: Yes | AG66: Yes | AH66: Yes | AI66: Yes | AJ66: Happy to know that SLPTS is striving hard to inculcate the habit of learning vedas through guru shishys parampara among the sanathanis.
A67: 2024 | B67: 45373.955 | C67: YES | D67: YES | E67: YES | F67: YES | G67: 1-ADULT OVER 16 YRS | H67: pksk4u@yahoo.com | I67: Mellacheruvu | J67: Venkata Radha Krishna Murthy | K67: =_xludf.TEXTJOIN(" ",TRUE,I67:J67) -> #NAME? | L67: 1964 | N67: 1-INDIA IST | O67: +91 | P67: 9440631176 | Q67: =P67&"/"&L67&"/"&K67 -> #NAME? | R67: Hyderabad | S67: Karanam Bhanu Chander | T67: Karanam Bhanu Chander | U67: Bharadwajasa, Haridasa, Haridasa | V67: Bharadwajasa, Haridasa, Haridasa | W67: Yajurveda | X67: Telugu, English &Hindi | Y67: Telugu, English | Z67: N,/A | AA67: Deputy Secretary to Government, A.P. Secretariat, Amaravati | AB67: Not Applicable (Not Registering a Child under 13) | AC67: To learn Sanathana Dharma,Veda Vidhya and the same is passing next generation | AD67: High - Learnt from Traditional Guru in perfect swaram/uccharana - perform nithya Sandhya Vandanam and can recite few Suktams in su-swaram | AE67: Yes, This is High Priority for me | AF67: Yes | AG67: Yes | AH67: Yes | AI67: Yes | AJ67: I am very much thankful to Sri Gurukrupa Veda Samrakshana Educational Society to give me this great opportunity
A68: 2024 | B68: 45374.048 | C68: YES | D68: YES | E68: YES | F68: YES | G68: 1-ADULT OVER 16 YRS | H68: shantharamsa.ch@gmail.com | I68: Chintapenta | J68: Shantaram | K68: =_xludf.TEXTJOIN(" ",TRUE,I68:J68) -> #NAME? | L68: 1980 | N68: 1-INDIA IST | O68: +91 | P68: 7893677746 | Q68: =P68&"/"&L68&"/"&K68 -> #NAME? | R68: Riyadh | S68: Whatapp group | T68: Whatapp group | U68: Bharadhawasaja, Harithasa, Gauthamasa | V68: Bharadhawasaja, Harithasa, Gauthamasa | W68: Yajur veda | X68: Telugu | Y68: Telugu | Z68: N/A | AA68: Software | AB68: Not Applicable (Not Registering a Child under 13) | AC68: To do rituals every day | AD68: None - Do not know much about this subject, but committed to learn | AE68: Yes, This is High Priority for me | AF68: Yes | AG68: Yes | AH68: Yes | AI68: Yes
A69: 2024 | B69: 45374.084 | C69: YES | D69: YES | E69: YES | F69: NO | G69: 1-ADULT OVER 16 YRS | H69: cssravan@gmail.com | I69: Chavali | J69: Subrahmanya Sravan | K69: =_xludf.TEXTJOIN(" ",TRUE,I69:J69) -> #NAME? | L69: 1986 | N69: 1-INDIA IST | O69: +91 | P69: 9491031078 | Q69: =P69&"/"&L69&"/"&K69 -> #NAME? | R69: Hyderabad | S69: Aditya Yadavalli | T69: Aditya Yadavalli | U69: Kousikasa, Goutamasa, Haritasa | V69: Kousikasa, Goutamasa, Haritasa | W69: Yajurveda | X69: Telugu, Hindi, English | Y69: Telugu, English, Hindi | Z69: N/A | AA69: Software Engineer | AB69: Not Applicable (Not Registering a Child under 13) | AC69: Nitya karma | AD69: Low - Did not learn from Traditional Guru, but learnt from books/audio and perform daily Sandhya Vandanam and other poojas through books | AE69: Yes, This is High Priority for me | AF69: Yes | AG69: Yes | AH69: Yes | AI69: Yes | AJ69: గురుబ్యో నమః
A70: 2024 | B70: 45374.094 | C70: YES | D70: YES | E70: YES | F70: YES | G70: 2-CHILD UNDER 16 YRS | H70: hemanthkumarsfdc@gmail.com | I70: Jagannadhula | J70: Vidwath | K70: =_xludf.TEXTJOIN(" ",TRUE,I70:J70) -> #NAME? | L70: 2015 | N70: 1-INDIA IST | O70: +91 | P70: 9573826562 | Q70: =P70&"/"&L70&"/"&K70 -> #NAME? | R70: HYDERABAD-TL | S70: Satyam Takkarsu | T70: Satyam Takkarsu | U70: Vishnuvardhasa, Parasara, NA | V70: Vishnuvardhasa, Parasara, NA | W70: Yajur Veda | X70: Telugu | Y70: Telugu | Z70: Girija Hemanth | AA70: Student | AB70: Yes. Will Learn 1st Year Syllabus along with Child | AC70: Wanna continue our traditional learning. | AD70: Low - Did not learn from Traditional Guru, but learnt from books/audio and perform daily Sandhya Vandanam and other poojas through books | AE70: Yes, This is High Priority for me | AF70: Yes | AG70: Yes | AH70: Yes | AI70: Yes
A71: 2024 | B71: 45374.116 | C71: YES | D71: YES | E71: YES | F71: YES | G71: 1-ADULT OVER 16 YRS | H71: mavuduru@gmail.com | I71: Mavuduru | J71: Uma Maheswar Rao | K71: =_xludf.TEXTJOIN(" ",TRUE,I71:J71) -> #NAME? | L71: 1961 | N71: 1-INDIA IST | O71: +91 | P71: 9437176540 | Q71: =P71&"/"&L71&"/"&K71 -> #NAME? | R71: BERHAMPUR ODISHA | S71: SRI WADALAMANI YAGESWAR RAO | T71: SRI WADALAMANI YAGESWAR RAO | U71: KASYAPA, UPAMANYASYA, UPAMANYASYA | V71: KASYAPA, UPAMANYASYA, UPAMANYASYA | W71: YAJURVEDA | X71: TELUGU ODIYA ENGLISH HINDI | Y71: TELUGU ODIYA ENGLISH | Z71: N/A | AA71: RETIRED SECTION OFFICER, GOVT ODISHA | AB71: Not Applicable (Not Registering a Child under 13) | AC71: To have knowledge and recite vedas | AD71: Low - Did not learn from Traditional Guru, but learnt from books/audio and perform daily Sandhya Vandanam and other poojas through books | AE71: Yes, This is High Priority for me | AF71: Yes | AG71: Yes | AH71: Yes | AI71: Yes | AJ71: I am very much privileged have this opportunity
A72: 2024 | B72: 45374.313 | C72: YES | D72: YES | E72: YES | F72: YES | G72: 1-ADULT OVER 16 YRS | H72: sriramasarma1971@gmail.com | I72: Kondaveeti | J72: S V V S S S Ramasarma | K72: =_xludf.TEXTJOIN(" ",TRUE,I72:J72) -> #NAME? | L72: 1971 | N72: 1-INDIA IST | O72: +91 | P72: 8790788333 | Q72: =P72&"/"&L72&"/"&K72 -> #NAME? | R72: Yanam | S72: Sasikanth garu | T72: Sasikanth garu | U72: Kowsikasa, Kashyapasa, Koundinyasa | V72: Kowsikasa, Kashyapasa, Koundinyasa | W72: Yajurvedam | X72: Telugu, english | Y72: Telugu, english , hindi | Z72: NA | AA72: Accounts Manager at private sector | AB72: Not Applicable (Not Registering a Child under 13) | AC72: Personal | AD72: Low - Did not learn from Traditional Guru, but learnt from books/audio and perform daily Sandhya Vandanam and other poojas through books | AE72: Yes, This is High Priority for me | AF72: Yes | AG72: Yes | AH72: Yes | AI72: Yes | AJ72: I joined your పాఠశాల 2 years back. But due to family troubles I didn't attend regularly. Now I request to give opertunity again sir.
A73: 2024 | B73: 45374.336 | C73: YES | D73: YES | E73: YES | F73: NO | G73: 1-ADULT OVER 16 YRS | H73: satish.munnagi@gmail.com | I73: Munnagi | J73: Satish | K73: =_xludf.TEXTJOIN(" ",TRUE,I73:J73) -> #NAME? | L73: 1980 | N73: 2-USA EST | O73: +1 | P73: 7347090606 | Q73: =P73&"/"&L73&"/"&K73 -> #NAME? | R73: Lafayette Indiana | S73: Raja sekhar | T73: Raja sekhar | U73: Harithasa, Srivathsa, Bharadwaj | V73: Harithasa, Srivathsa, Bharadwaj | W73: Yajur veda | X73: Telugu | Y73: Telugu | Z73: Na | AA73: Engineer | AB73: Not Applicable (Not Registering a Child under 13) | AC73: Learn traditional methods | AD73: None - Do not know much about this subject, but committed to learn | AE73: Not sure due to other commitments | AF73: Yes | AG73: Yes | AH73: Yes | AI73: Yes
A74: 2024 | B74: 45374.918 | C74: YES | D74: YES | E74: YES | F74: YES | G74: 1-ADULT OVER 16 YRS | H74: vijayakumarasarma@gmail.com | I74: Gouripeddi | J74: Vijaya Kumara Sharma | K74: =_xludf.TEXTJOIN(" ",TRUE,I74:J74) -> #NAME? | L74: 1961 | N74: 1-INDIA IST | O74: +91 | P74: 9490885905 | Q74: =P74&"/"&L74&"/"&K74 -> #NAME? | R74: MANDAPETA | S74: Dr.Boddu Palli Venkata Siva Kumar. Mobile:9346386115. | T74: Dr.Boddu Palli Venkata Siva Kumar. Mobile:9346386115. | U74: Sree BHARADWAJASA, Sree SHYAANDILYASA, Sree SHYAANDILYASA | V74: Sree BHARADWAJASA, Sree SHYAANDILYASA, Sree SHYAANDILYASA | W74: YAJUR VEDA | X74: Telugu, English. | Y74: Telugu, English. | Z74: NA | AA74: Joint Director (Animal Husbandry Dept).(Retired).A.P. | AB74: Not Applicable (Not Registering a Child under 13) | AC74: Vedic Literature in repect of Sanathana Dharma for Brahmanism. | AD74: High - Learnt from Traditional Guru in perfect swaram/uccharana - perform nithya Sandhya Vandanam and can recite few Suktams in su-swaram | AE74: Yes, This is High Priority for me | AF74: Yes | AG74: Yes | AH74: Yes | AI74: Yes | AJ74: Respected Sir. A traditinal family back ground and desire to learn the Vedic Knowledge for perpuation of the wisdom to future generations. Presently, persuing the Sree Rudram and Mahaanyasam from Sree Vadlamani Yagneswara Sarma garu and Dr.B.Siva Kumar garu of Hyderabad. Highly need a systematic appraoch as per your curriculum.
A75: 2024 | B75: 45374.924 | C75: YES | D75: YES | E75: YES | F75: YES | G75: 2-CHILD UNDER 16 YRS | H75: pavan12@gmail.com | I75: Jagarlapudi | J75: Venkata Sai Siddharth | K75: =_xludf.TEXTJOIN(" ",TRUE,I75:J75) -> #NAME? | L75: 2015 | N75: 1-INDIA IST | O75: +91 | P75: 9908321918 | Q75: =P75&"/"&L75&"/"&K75 -> #NAME? | R75: Hyderabad | S75: Ambatipudi Lalith chaitanya | T75: Ambatipudi Lalith chaitanya | U75: Koundinasya, Kousikasa, N/A | V75: Koundinasya, Kousikasa, N/A | W75: Krishna Yajur veda | X75: Telugu, Engligh | Y75: Telugu, English | Z75: Jagarlapudi Venkata Pavan Kumar | AA75: 4th Class | AB75: Yes. Will Learn 1st Year Syllabus along with Child | AC75: To learn our veda practices for my self and my son | AD75: None - Do not know much about this subject, but committed to learn | AE75: Not sure due to other commitments | AF75: Yes | AG75: Yes | AH75: Yes | AI75: Yes | AJ75: Looking forward
A76: 2024 | B76: 45380.436 | C76: YES | D76: YES | E76: YES | F76: YES | G76: 2-CHILD UNDER 16 YRS | H76: krishnagopal.bh@gmail.com | I76: Sistla | J76: Saamdeep Pradyumna | K76: =_xludf.TEXTJOIN(" ",TRUE,I76:J76) -> #NAME? | L76: 2013 | N76: 1-INDIA IST | O76: +91 | P76: 9494858601 | Q76: =P76&"/"&L76&"/"&K76 -> #NAME? | R76: Hyderabad | S76: Krishna Gopal Bhamidipalli | T76: Krishna Gopal Bhamidipalli | U76: Koundinya, Koushika, N/A | V76: Koundinya, Koushika, N/A | W76: Yajurveda | X76: Telugu | Y76: Telugu | Z76: C/o Krishna gopal Bhamidipalli | AA76: 4th class | AB76: Already know 1st year Syllabus. Hence will help the child at home | AC76: Sandhya vandanam,Agni kaaryam etc. | AD76: None - Do not know much about this subject, but committed to learn | AE76: Yes, This is High Priority for me | AF76: Yes | AG76: Yes | AH76: Yes | AI76: Yes | AJ76: Want to learn veda.
A77: 2024 | B77: 45380.454 | C77: YES | D77: YES | E77: YES | F77: YES | G77: 1-ADULT OVER 16 YRS | H77: svlprasad999@gmail.com | I77: Sankaramanchi | J77: Venkata Lakshminarayana Prasad | K77: =_xludf.TEXTJOIN(" ",TRUE,I77:J77) -> #NAME? | L77: 1974 | N77: 1-INDIA IST | O77: +91 | P77: 9866296512 | Q77: =P77&"/"&L77&"/"&K77 -> #NAME? | R77: Hyderabad | S77: Satheesh Kumar sarma | T77: Satheesh Kumar sarma | U77: Atreyasa, Gowthamasa, Gowthamasa | V77: Atreyasa, Gowthamasa, Gowthamasa | W77: Yajur veda | X77: Telugu, English, Hindi | Y77: Telugu English Hindi | Z77: NA | AA77: IT employee | AB77: Not Applicable (Not Registering a Child under 13) | AC77: For namakam chemakam | AD77: None - Do not know much about this subject, but committed to learn | AE77: Not sure due to other commitments | AF77: Yes | AG77: Yes | AH77: Yes | AI77: Yes
A78: 2024 | B78: 45380.455 | C78: YES | D78: YES | E78: YES | F78: YES | G78: 1-ADULT OVER 16 YRS | H78: saiganjam.1992@gmail.com | I78: Ganjam | J78: Anantha Venkata Sesha Talpa Sai | K78: =_xludf.TEXTJOIN(" ",TRUE,I78:J78) -> #NAME? | L78: 1992 | N78: 1-INDIA IST | O78: +91 | P78: 9502020229 | Q78: =P78&"/"&L78&"/"&K78 -> #NAME? | R78: Ongole | S78: Manikanta chillara | T78: Manikanta chillara | U78: Harithasa, Sri vastha, Na | V78: Harithasa, Sri vastha, Na | W78: Yajur Veda | X78: Telugu | Y78: Telugu English | Z78: Na | AA78: Own business | AB78: Not Applicable (Not Registering a Child under 13) | AC78: I am interested in god and vedas our culture | AD78: Low - Did not learn from Traditional Guru, but learnt from books/audio and perform daily Sandhya Vandanam and other poojas through books | AE78: Yes, This is High Priority for me | AF78: Yes | AG78: Yes | AH78: Yes | AI78: Yes
A79: 2024 | B79: 45380.46 | C79: YES | D79: YES | E79: YES | F79: YES | G79: 1-ADULT OVER 16 YRS | H79: visitmsrao@gmail.com | I79: Mutnuru | J79: Srinivasa Rao | K79: =_xludf.TEXTJOIN(" ",TRUE,I79:J79) -> #NAME? | L79: 1970 | N79: 1-INDIA IST | O79: +91 | P79: 9958143242 | Q79: =P79&"/"&L79&"/"&K79 -> #NAME? | R79: DELHI | S79: Boddupalli Siva Kumar | T79: Boddupalli Siva Kumar | U79: KAUNDINYASA గోత్రం, VARDHIYASWASA గోత్రము, BHARADWAJASA గోత్రం | V79: KAUNDINYASA గోత్రం, VARDHIYASWASA గోత్రము, BHARADWAJASA గోత్రం | W79: Yajurveda | X79: Telugu English Hindi | Y79: Telugu English Hindi | Z79: NA | AA79: Associate Professor DSEU Govt of Delhi | AB79: Not Applicable (Not Registering a Child under 13) | AC79: అద్భుతమైన అవకాశం to learn and follow my culture. Dedicate remaining life to my culture and surrender to almighty | AD79: None - Do not know much about this subject, but committed to learn | AE79: Yes, This is High Priority for me | AF79: Yes | AG79: Yes | AH79: Yes | AI79: Yes | AJ79: తప్పకుండా cherchukomani విన్నపము. Learnt rudram, mahanysam and some suktamulu. I wish to Learn from basics from you with the blessings of almighty for all the 4 years. శ్రీ Gurubhyom Namaha
A80: 2024 | B80: 45380.478 | C80: YES | D80: YES | E80: YES | F80: YES | G80: 1-ADULT OVER 16 YRS | H80: bsgsivachandrika@gmail.com | I80: Boddupalli | J80: Venka Siva Kumar | K80: =_xludf.TEXTJOIN(" ",TRUE,I80:J80) -> #NAME? | L80: 1981 | N80: 1-INDIA IST | O80: +91 | P80: 8790358319 | Q80: =P80&"/"&L80&"/"&K80 -> #NAME? | R80: Hyderabad | S80: Madduri Rajender Garu | T80: Madduri Rajender Garu | U80: HARITASA, Kasypasa, Koushikasa | V80: HARITASA, Kasypasa, Koushikasa | W80: Yajurveda | X80: Telugu, English, Hindi | Y80: Telugu , English, Hindi | Z80: NA | AA80: Pharma Employee | AB80: Not Applicable (Not Registering a Child under 13) | AC80: Interested in Vedas/Sanata Dharama Teachings | AD80: High - Learnt from Traditional Guru in perfect swaram/uccharana - perform nithya Sandhya Vandanam and can recite few Suktams in su-swaram | AE80: Yes, This is High Priority for me | AF80: Yes | AG80: Yes | AH80: Yes | AI80: Yes | AJ80: Thankyou for this Opportunity
A81: 2024 | B81: 45380.482 | C81: YES | D81: YES | E81: YES | F81: YES | G81: 1-ADULT OVER 16 YRS | H81: rajendra.madduri@gmail.com | I81: Madduri | J81: Rajendra Prasad | K81: =_xludf.TEXTJOIN(" ",TRUE,I81:J81) -> #NAME? | L81: 1961 | N81: 1-INDIA IST | O81: +91 | P81: 9492927375 | Q81: =P81&"/"&L81&"/"&K81 -> #NAME? | R81: Sangareddy, Telangana | S81: Siripurapu Srinivas | T81: Siripurapu Srinivas | U81: Haritasa, Bharadwaja, Bharadwaja | V81: Haritasa, Bharadwaja, Bharadwaja | W81: Krishna Yajur Veda | X81: Telugu, English | Y81: Telugu English Sanskrit | Z81: N/A | AA81: Retired Manager | AB81: Not Applicable (Not Registering a Child under 13) | AC81: Spiritual uplift, Atma Suddhi | AD81: Low - Did not learn from Traditional Guru, but learnt from books/audio and perform daily Sandhya Vandanam and other poojas through books | AE81: Yes, This is High Priority for me | AF81: Not sure | AG81: Yes | AH81: Yes | AI81: Yes | AJ81: I am committed to improve my learning of Vedic texts.
A82: 2024 | B82: 45380.488 | C82: YES | D82: YES | E82: YES | F82: YES | G82: 1-ADULT OVER 16 YRS | H82: muthyamkanakadurga@gmail.com | I82: Muthyam | J82: Abhiram Rao | K82: =_xludf.TEXTJOIN(" ",TRUE,I82:J82) -> #NAME? | L82: 2009 | N82: 1-INDIA IST | O82: +91 | P82: 9121432011 | Q82: =P82&"/"&L82&"/"&K82 -> #NAME? | R82: Hyderabad | S82: Mahankali Lakshmi prasanna | T82: Mahankali Lakshmi prasanna | U82: Sandilyasa, Kousikasa, N/A | V82: Sandilyasa, Kousikasa, N/A | W82: Yajur vedam | X82: Telugu ,hindi,english | Y82: Telugu and english | Z82: N/A | AA82: 10th grade student | AB82: Not Applicable (Not Registering a Child under 13) | AC82: Im interested learning veda and implement in my personal life . | AD82: Low - Did not learn from Traditional Guru, but learnt from books/audio and perform daily Sandhya Vandanam and other poojas through books | AE82: Yes, This is High Priority for me | AF82: Yes | AG82: Yes | AH82: Yes | AI82: Yes | AJ82: Kindly enroll me for the course .Tq u
A83: 2024 | B83: 45380.493 | C83: YES | D83: YES | E83: YES | F83: YES | G83: 1-ADULT OVER 16 YRS | H83: prasadpannala@gmail.com | I83: Pannala | J83: Srinivasa Prasad | K83: =_xludf.TEXTJOIN(" ",TRUE,I83:J83) -> #NAME? | L83: 1963 | N83: 1-INDIA IST | O83: +91 | P83: 9490366695 | Q83: =P83&"/"&L83&"/"&K83 -> #NAME? | R83: Hyderabad | S83: Lalit Santosh | T83: Lalit Santosh | U83: Koundinysa, Haritasa, NA | V83: Koundinysa, Haritasa, NA | W83: Yajurveda | X83: Telugu English Hindi | Y83: Telugu English Hindi | Z83: NA | AA83: Retired Bank Manager | AB83: Not Applicable (Not Registering a Child under 13) | AC83: I want to learn | AD83: None - Do not know much about this subject, but committed to learn | AE83: Yes, This is High Priority for me | AF83: Yes | AG83: Yes | AH83: Yes | AI83: Yes | AJ83: I am very much interested to learn vedam
A84: 2024 | B84: 45380.497 | C84: YES | D84: YES | E84: YES | F84: YES | G84: 1-ADULT OVER 16 YRS | H84: smyahoo@gmail.com | I84: Mattegunta | J84: Srinivas | K84: =_xludf.TEXTJOIN(" ",TRUE,I84:J84) -> #NAME? | L84: 1971 | N84: 1-INDIA IST | O84: +91 | P84: 9912805900 | Q84: =P84&"/"&L84&"/"&K84 -> #NAME? | R84: Hyderabad | S84: Ragavendhra, Ravi Kiran | T84: Ragavendhra, Ravi Kiran | U84: Bharadwaja, Vasishtha, Kasyapaya | V84: Bharadwaja, Vasishtha, Kasyapaya | W84: Yajur Veda | X84: Telugu, English, Hindi | Y84: Telugu, English, Hindi | Z84: NA | AA84: Manager | AB84: Not Applicable (Not Registering a Child under 13) | AC84: I am interested in learning Veda since many years , I started reciting Narayana Suktham, Purusha Suktham, Sri Rudram as a starting point | AD84: Low - Did not learn from Traditional Guru, but learnt from books/audio and perform daily Sandhya Vandanam and other poojas through books | AE84: Yes, This is High Priority for me | AF84: Yes | AG84: Yes | AH84: Yes | AI84: Yes
A85: 2024 | B85: 45380.503 | C85: YES | D85: YES | E85: YES | F85: YES | G85: 1-ADULT OVER 16 YRS | H85: vasisekhar@gmail.com | I85: Kesiraju | J85: Rajasekhar | K85: =_xludf.TEXTJOIN(" ",TRUE,I85:J85) -> #NAME? | L85: 1975 | N85: 3-USA CST | O85: +1 | P85: 9723421582 | Q85: =P85&"/"&L85&"/"&K85 -> #NAME? | R85: Plano | S85: Prabhakar Prabala | T85: Prabhakar Prabala | U85: Haritasa, Aslesha, Koundinyasa | V85: Haritasa, Aslesha, Koundinyasa | W85: Yajur Veda | X85: Telugu, Hindi, English | Y85: Telugu, Hindi, English | Z85: N/A | AA85: Solution Architect | AB85: Not Applicable (Not Registering a Child under 13) | AC85: I want to improve my uccharana and learn Rudram. Want to learn Vedas and save our ancestors what has done. | AD85: Low - Did not learn from Traditional Guru, but learnt from books/audio and perform daily Sandhya Vandanam and other poojas through books | AE85: Yes, This is High Priority for me | AF85: Yes | AG85: Yes | AH85: Yes | AI85: Yes | AJ85: I don’t smoke, drink… in our home we don’t consume onions and garlic. We are Brahmins
A86: 2024 | B86: 45384.03 | C86: YES | D86: YES | E86: YES | F86: YES | G86: 1-ADULT OVER 16 YRS | H86: purnarao1959@gmail.com | I86: Vemuri | J86: Annapurnananda Rao | K86: =_xludf.TEXTJOIN(" ",TRUE,I86:J86) -> #NAME? | L86: 1959 | N86: 1-INDIA IST | O86: +91 | P86: 6281260746 | Q86: =P86&"/"&L86&"/"&K86 -> #NAME? | R86: Hyderabad | S86: Konduri Venkata Ramana | T86: Konduri Venkata Ramana | U86: Harithasa, Kosikasa, Kanvasa | V86: Harithasa, Kosikasa, Kanvasa | W86: Yajur Veda | X86: Telugu | Y86: Telugu, English | Z86: N/A | AA86: Retired Railway Employee | AB86: Not Applicable (Not Registering a Child under 13) | AC86: To do my daily puja as per procedure | AD86: Low - Did not learn from Traditional Guru, but learnt from books/audio and perform daily Sandhya Vandanam and other poojas through books | AE86: Yes, This is High Priority for me | AF86: Yes | AG86: Yes | AH86: Yes | AI86: Yes | AJ86: I wish to be a part of this Veda learning
A87: 2024 | B87: 45386.031 | C87: YES | D87: YES | E87: YES | F87: YES | G87: 1-ADULT OVER 16 YRS | H87: prasadnssai@gmail.com | I87: NS | J87: Prasad | K87: =_xludf.TEXTJOIN(" ",TRUE,I87:J87) -> #NAME? | L87: 1966 | N87: 1-INDIA IST | O87: +91 | P87: 9483631232 | Q87: =P87&"/"&L87&"/"&K87 -> #NAME? | R87: Kurnool | S87: Online net | T87: Online net | U87: BHARADWJA, KASYAPASA, PARASARA | V87: BHARADWJA, KASYAPASA, PARASARA | W87: KRISHNA YAJURVEDA | X87: Telugu english hindi | Y87: Telugu english hindi | Z87: NA | AA87: Retd professional | AB87: Not Applicable (Not Registering a Child under 13) | AC87: To Know our Hindu culture from gross roots | AD87: None - Do not know much about this subject, but committed to learn | AE87: Yes, This is High Priority for me | AF87: Yes | AG87: Yes | AH87: Yes | AI87: Yes | AJ87: Pl share fee details
A88: 2024 | B88: 45387.358 | C88: YES | D88: YES | E88: YES | F88: YES | G88: 2-CHILD UNDER 16 YRS | H88: mvnvihas@gmail.com | I88: Mamillapalli | J88: Viswanatha Naga Vihas Sharma | K88: =_xludf.TEXTJOIN(" ",TRUE,I88:J88) -> #NAME? | L88: 2013 | N88: 1-INDIA IST | O88: +91 | P88: 7981631827 | Q88: =P88&"/"&L88&"/"&K88 -> #NAME? | R88: Hyderabad | S88: Chandra Kaladhar | T88: Chandra Kaladhar | U88: Koundinyasa, Harithasa, BRAHMACHARI | V88: Koundinyasa, Harithasa, BRAHMACHARI | W88: Yajur Veda | X88: Telugu, English | Y88: Telugu, English, Hindi | Z88: Srikanth Mamillapalli and Kalyani Mamillapalli | AA88: 6th Grade Student | AB88: Yes. Will Learn 1st Year Syllabus along with Child | AC88: to perform Sandhya Vandana daily along with gayatri mata japam | AD88: None - Do not know much about this subject, but committed to learn | AE88: Not sure due to other commitments | AF88: Yes | AG88: Yes | AH88: Yes | AI88: Yes
A89: 2024 | B89: 45387.439 | C89: YES | D89: YES | E89: YES | F89: YES | G89: 1-ADULT OVER 16 YRS | H89: kameshmallela@gmail.com | I89: Mallela | J89: Lalitha Kameswar | K89: =_xludf.TEXTJOIN(" ",TRUE,I89:J89) -> #NAME? | L89: 1991 | N89: 1-INDIA IST | O89: +91 | P89: 9298903940 | Q89: =P89&"/"&L89&"/"&K89 -> #NAME? | R89: Bangalore | S89: Ghantasala Raghu | T89: Ghantasala Raghu | U89: Kausikasa, Harithasa, NA | V89: Kausikasa, Harithasa, NA | W89: Krishna Yajurveda | X89: Telugu | Y89: Telugu | Z89: NA | AA89: IT engineering | AB89: Not Applicable (Not Registering a Child under 13) | AC89: Smartham 4 year course | AD89: None - Do not know much about this subject, but committed to learn | AE89: Not sure due to other commitments | AF89: Yes | AG89: Yes | AH89: Yes | AI89: Yes
A90: 2024 | B90: 45387.858 | C90: YES | D90: YES | E90: YES | F90: YES | G90: 2-CHILD UNDER 16 YRS | H90: mannavadeepu@gmail.com | I90: Rayapati | J90: Naren Karthik | K90: =_xludf.TEXTJOIN(" ",TRUE,I90:J90) -> #NAME? | L90: 2010 | N90: 1-INDIA IST | O90: +91 | P90: 9642433663 | Q90: =P90&"/"&L90&"/"&K90 -> #NAME? | R90: Hyderabad | S90: Ravi kiran Mahankali | T90: Ravi kiran Mahankali | U90: Bharadwaja, Gautamasa, Na | V90: Bharadwaja, Gautamasa, Na | W90: Yajur Veda | X90: Telugu, English, Hindi | Y90: Telugu, English, Hindi | Z90: NA | AA90: Student | AB90: Not Applicable (Not Registering a Child under 13) | AC90: I want to explore the knowledge | AD90: None - Do not know much about this subject, but committed to learn | AE90: Not sure due to other commitments | AF90: Yes | AG90: Yes | AH90: Yes | AI90: Yes
A91: 2024 | B91: 45388.422 | C91: YES | D91: YES | E91: YES | F91: YES | G91: 1-ADULT OVER 16 YRS | H91: ssprakhya@gmail.com | I91: Prakhya | J91: Sadasiva | K91: =_xludf.TEXTJOIN(" ",TRUE,I91:J91) -> #NAME? | L91: 1966 | N91: 1-INDIA IST | O91: +91 | P91: 8801961216 | Q91: =P91&"/"&L91&"/"&K91 -> #NAME? | R91: Hyderabad | S91: Whats app | T91: Whats app | U91: Srivatsa, Bharadwaj, Kounyasa | V91: Srivatsa, Bharadwaj, Kounyasa | W91: Yajurveda | X91: Telugu. Hindi, English | Y91: Telugu, English | Z91: N/A | AA91: Acupuncturist | AB91: Not Applicable (Not Registering a Child under 13) | AC91: Interest | AD91: Low - Did not learn from Traditional Guru, but learnt from books/audio and perform daily Sandhya Vandanam and other poojas through books | AE91: Yes, This is High Priority for me | AF91: Yes | AG91: Yes | AH91: Yes | AI91: Yes
A92: 2024 | B92: 45388.455 | C92: YES | D92: YES | E92: YES | F92: YES | G92: 2-CHILD UNDER 16 YRS | H92: vedantpillutla@gmail.com | I92: Pillutla | J92: Vedant | K92: =_xludf.TEXTJOIN(" ",TRUE,I92:J92) -> #NAME? | L92: 2010 | N92: 3-USA CST | O92: +1 | P92: 5635704029 | Q92: =P92&"/"&L92&"/"&K92 -> #NAME? | R92: Davenport, Iowa | S92: Rajsekhar K.V. | T92: Rajsekhar K.V. | U92: Srivatsa, Koundinya, N/A | V92: Srivatsa, Koundinya, N/A | W92: Yajur | X92: Telugu, English | Y92: Telugu and English, and Sanskrit | Z92: N/A | AA92: 8th grade student | AB92: Not Applicable (Not Registering a Child under 13) | AC92: To get more fluent with my Vedic practices. | AD92: Low - Did not learn from Traditional Guru, but learnt from books/audio and perform daily Sandhya Vandanam and other poojas through books | AE92: Yes, This is High Priority for me | AF92: Yes | AG92: Yes | AH92: Yes | AI92: Yes | AJ92: I'm excited to learn. I appreciate the opportunity afforded to me. Thank you!
A93: 2024 | B93: 45388.958 | C93: YES | D93: YES | E93: YES | F93: YES | G93: 2-CHILD UNDER 16 YRS | H93: cymohan@gmail.com | I93: Yeleswarapu | J93: Sriram | K93: =_xludf.TEXTJOIN(" ",TRUE,I93:J93) -> #NAME? | L93: 2015 | N93: 1-INDIA IST | O93: +91 | P93: 9491340827 | Q93: =P93&"/"&L93&"/"&K93 -> #NAME? | R93: Hyderabad | S93: Mr. Mangipudi Annappa Somayajulu | T93: Mr. Mangipudi Annappa Somayajulu | U93: Kousikasa, Koundinyasa, N/A | V93: Kousikasa, Koundinyasa, N/A | W93: Yajur Veda | X93: Telugu., Hindi, English | Y93: English, learning Telugu and Hindi | Z93: Yeleswarapu Chandramohan, Yeleswarapu Satya Kalyani | AA93: 4th grade | AB93: Yes. Will Learn 1st Year Syllabus along with Child | AC93: To help my son understand the importance our traditions and rituals which if he puts to practice, I believe would help him lead a quality life. | AD93: None - Do not know much about this subject, but committed to learn | AE93: Yes, This is High Priority for me | AF93: Yes | AG93: Yes | AH93: Yes | AI93: Yes
A94: 2024 | B94: 45389.68 | C94: YES | D94: YES | E94: YES | F94: YES | G94: 2-CHILD UNDER 16 YRS | H94: 1followyourpassion@gmail.com | I94: Teegavarapu | J94: Ahil | K94: =_xludf.TEXTJOIN(" ",TRUE,I94:J94) -> #NAME? | L94: 2010 | N94: 2-USA EST | O94: +1 | P94: 3653557220 | Q94: =P94&"/"&L94&"/"&K94 -> #NAME? | R94: Milton, Ontario, Canada | S94: Malavika Nandula | T94: Malavika Nandula | U94: Bharathwaza, Harithasa, NA | V94: Bharathwaza, Harithasa, NA | W94: Yajur Veda | X94: Telugu, English | Y94: English | Z94: VenkataPrabhakar Teegavarapu | AA94: 8th grade | AB94: Yes. Will Learn 1st Year Syllabus along with Child | AC94: To learn Hindu culture | AD94: None - Do not know much about this subject, but committed to learn | AE94: Yes, This is High Priority for me | AF94: Yes | AG94: Yes | AH94: Yes | AI94: Yes
A95: 2024 | B95: 45389.927 | C95: YES | D95: YES | E95: YES | F95: YES | G95: 2-CHILD UNDER 16 YRS | H95: S.Kasyapa@gmail.com | I95: Sistla | J95: Kaarthikeya | K95: =_xludf.TEXTJOIN(" ",TRUE,I95:J95) -> #NAME? | L95: 2012 | N95: 2-USA EST | O95: +1 | P95: 4702725998 | Q95: =P95&"/"&L95&"/"&K95 -> #NAME? | R95: Alpharetta | S95: Challa Siva Sankara Kumar(Aditya Kumar Challa) Austin, TX | T95: Challa Siva Sankara Kumar(Aditya Kumar Challa) Austin, TX | U95: Kasyapasa, Gowtamasa, N/A | V95: Kasyapasa, Gowtamasa, N/A | W95: Yajur Veda (Krishna) | X95: Telugu, English | Y95: English | Z95: Kasyapa Sistla, Alataramani Nandula | AA95: 6th Grade Student | AB95: Yes. Will Learn 1st Year Syllabus along with Child | AC95: Vedam | AD95: None - Do not know much about this subject, but committed to learn | AE95: Yes, This is High Priority for me | AF95: Yes | AG95: Yes | AH95: Yes | AI95: Yes
A96: 2024 | B96: 45392.41 | C96: YES | D96: YES | E96: YES | F96: YES | G96: 1-ADULT OVER 16 YRS | H96: Sasimeduri@gmail.com | I96: Meduri | J96: Sashikanth | K96: =_xludf.TEXTJOIN(" ",TRUE,I96:J96) -> #NAME? | L96: 1980 | N96: 1-INDIA IST | O96: +91 | P96: 9885096301 | Q96: =P96&"/"&L96&"/"&K96 -> #NAME? | R96: Hyderabad | S96: Vamsikanth Meduri | T96: Vamsikanth Meduri | U96: Kousikasa, Athreyasa, Kasyapasa | V96: Kousikasa, Athreyasa, Kasyapasa | W96: Krishna Yajurvedam | X96: Telugu, English, tamil | Y96: Telugu, english, tamil | Z96: NA | AA96: Sw Manager | AB96: Yes. Will Learn 1st Year Syllabus along with Child | AC96: Rudram namkam chamakaal, and ither sthotrams | AD96: Low - Did not learn from Traditional Guru, but learnt from books/audio and perform daily Sandhya Vandanam and other poojas through books | AE96: Not sure due to other commitments | AF96: Yes | AG96: Yes | AH96: Yes | AI96: Yes | AJ96: Registered my kid for veda children class. So I wamt to join on Grihastha class kindly join me
A97: 2024 | B97: 45393.075 | C97: YES | D97: YES | E97: YES | F97: YES | G97: 2-CHILD UNDER 16 YRS | H97: krishnakanth82@gmail.com | I97: Choragudi | J97: Sai Karthikeya Sriram | K97: =_xludf.TEXTJOIN(" ",TRUE,I97:J97) -> #NAME? | L97: 2016 | N97: 1-INDIA IST | O97: +91 | P97: 9966190739 | Q97: =P97&"/"&L97&"/"&K97 -> #NAME? | R97: Hyderabad | S97: Sasikanth Meduri | T97: Sasikanth Meduri | U97: Aathreya, Kasyapa, NA | V97: Aathreya, Kasyapa, NA | W97: Yajur veda | X97: Telugu and English | Y97: Telugu and English | Z97: Naga Krishnakanth choragudi and Sirisha Chaturvedula | AA97: 3rd grade Student | AB97: Yes. Will Learn 1st Year Syllabus along with Child | AC97: To understand and sustain our cultural roots | AD97: Low - Did not learn from Traditional Guru, but learnt from books/audio and perform daily Sandhya Vandanam and other poojas through books | AE97: Not sure due to other commitments | AF97: Yes | AG97: Yes | AH97: Yes | AI97: Yes
A98: 2024 | B98: 45393.125 | C98: YES | D98: YES | E98: YES | F98: YES | G98: 1-ADULT OVER 16 YRS | H98: svmynampati@gmail.com | I98: Mynampati | J98: Venkata Subbaramaiah | K98: =_xludf.TEXTJOIN(" ",TRUE,I98:J98) -> #NAME? | L98: 1977 | N98: 1-INDIA IST | O98: +91 | P98: 9133779696 | Q98: =P98&"/"&L98&"/"&K98 -> #NAME? | R98: HYDERABAD | S98: Dr. Atmakuri Chakravarthy | T98: Dr. Atmakuri Chakravarthy | U98: Bhardwaja, koundinyasa, Satamarshana | V98: Bhardwaja, koundinyasa, Satamarshana | W98: Yajur Veda | X98: telugu | Y98: telugu english hindi | Z98: M V Subbaramaiah | AA98: Civil Engineer | AB98: Yes. Will Learn 1st Year Syllabus along with Child | AC98: vedic program | AD98: Low - Did not learn from Traditional Guru, but learnt from books/audio and perform daily Sandhya Vandanam and other poojas through books | AE98: Yes, This is High Priority for me | AF98: Yes | AG98: Yes | AH98: Yes | AI98: Yes | AJ98: being a Brahmin from traditional family till date I have not taken meat or cigarettes alcohol etc and did upnayanam to my both children at 12 yrs and 11 yrs now they are 15 and 13 doing sandhya vandanam regularly
A99: 2024 | B99: 45393.914 | C99: YES | D99: YES | E99: YES | F99: YES | G99: 1-ADULT OVER 16 YRS | H99: findsatish@gmail.com | I99: Balantrapu | J99: Satish | K99: =_xludf.TEXTJOIN(" ",TRUE,I99:J99) -> #NAME? | L99: 1978 | N99: 1-INDIA IST | O99: +91 | P99: 7702648904 | Q99: =P99&"/"&L99&"/"&K99 -> #NAME? | R99: Hyderabad | S99: Surya Srinivas Chavali | T99: Surya Srinivas Chavali | U99: Vadhulasa, Bharadwaja, Gargeyasa | V99: Vadhulasa, Bharadwaja, Gargeyasa | W99: Yajur Veda | X99: Telugu, English | Y99: Telugu, English | Z99: NA | AA99: Software Professional | AB99: Not Applicable (Not Registering a Child under 13) | AC99: To learn Samskaras | AD99: Low - Did not learn from Traditional Guru, but learnt from books/audio and perform daily Sandhya Vandanam and other poojas through books | AE99: Yes, This is High Priority for me | AF99: Yes | AG99: Yes | AH99: Yes | AI99: Yes
A100: 2024 | B100: 45393.92 | C100: YES | D100: YES | E100: YES | F100: YES | G100: 2-CHILD UNDER 16 YRS | H100: findsatish@gmail.com | I100: Balantrapu | J100: Sai Sri Vallabh | K100: =_xludf.TEXTJOIN(" ",TRUE,I100:J100) -> #NAME? | L100: 2012 | N100: 1-INDIA IST | O100: +91 | P100: 7702648904 | Q100: =P100&"/"&L100&"/"&K100 -> #NAME? | R100: Hyderabad | S100: Surya Srinivas Chavali | T100: Surya Srinivas Chavali | U100: Vadhula, Gargeya, N/A | V100: Vadhula, Gargeya, N/A | W100: Yajur Veda | X100: English, Telugu | Y100: English,Hindi | Z100: Satish, Sowmya | AA100: 7TH GRADE STUDENT | AB100: Yes. Will Learn 1st Year Syllabus along with Child | AC100: Learn our culture | AD100: Low - Did not learn from Traditional Guru, but learnt from books/audio and perform daily Sandhya Vandanam and other poojas through books | AE100: Yes, This is High Priority for me | AF100: Yes | AG100: Yes | AH100: Yes | AI100: Yes
...
